Workbook

Sheet SETUP
B2: Spreadsheet Setup
C5: Categories | D5: Descriptions
C6: Income | D6: CVS Income
C7: Income | D7: Apt 2 Rent
C8: Income | D8: Apt 3 Rent
C9: Income | D9: Uber Driver
C10: Property Expenses | D10: Mortgage
C11: Property Expenses | D11: Owner Contribution to Mortgage
C12: Property Expenses | D12: Landlord Electricity
C13: Property Expenses | D13: Water/Sewer (Monthly)
C14: Property Expenses | D14: Maintenance (Lawn)
C15: Property Expenses | D15: Maintenance (Lawn)
C16: Property Expenses | D16: Maintenance (Snow Removal)
... C46: Credit Card Payments | D46: CITIZENS Clear Value
C47: Savings
C48: Investments

Sheet 202601
C2: Season | D2: Summer
C4: =SUMIFS(E17:E89, D17:D89, "<=14") -> 1986.06 | D4: Expenses: 1st to 15th
C5: =SUMIFS(E17:E89, D17:D89, ">=15") -> 2449.61 | D5: Expenses: 15th to 30th
C7: Description | D7: Expected Due Date | E7: Amount | G7: Date Input? | H7: Description | I7: Expected Due Date | J7: Amount | K7: Pull into CASHFLOW
B8: =IFERROR(NOT(ISBLANK(D8)), FALSE) -> TRUE | C8: CVS Income | D8: 15 | E8: 3205.07 | G8: =NOT(ISBLANK(D8)) -> TRUE | H8: =IFERROR(__xludf.DUMMYFUNCTION("FILTER($C$8:$E$96, $G8:$G$96)"),"CVS Income") -> CVS Income | I8: =IFERROR(__xludf.DUMMYFUNCTION("""COMPUTED_VALUE"""),15) -> 15 | J8: =IFERROR(__xludf.DUMMYFUNCTION("""COMPUTED_VALUE"""),3205.07) -> 3205.07 | K8: =NOT(ISBLANK(H8)) -> TRUE
B9: =IFERROR(NOT(ISBLANK(D9)), FALSE) -> TRUE | C9: CVS Income | D9: 30 | E9: 3205.07 | G9: =NOT(ISBLANK(D9)) -> TRUE | H9: =IFERROR(__xludf.DUMMYFUNCTION("""COMPUTED_VALUE"""),"CVS Income") -> CVS Income | I9: =IFERROR(__xludf.DUMMYFUNCTION("""COMPUTED_VALUE"""),30) -> 30 | J9: =IFERROR(__xludf.DUMMYFUNCTION("""COMPUTED_VALUE"""),3205.07) -> 3205.07 | K9: =NOT(ISBLANK(H9)) -> TRUE
B10: =IFERROR(NOT(ISBLANK(D10)), FALSE) -> FALSE | C10: Apt 2 Rent | G10: =NOT(ISBLANK(D10)) -> FALSE | H10: =IFERROR(__xludf.DUMMYFUNCTION("""COMPUTED_VALUE"""),"BOA Customized Rewards") -> BOA Customized Rewards | I10: =IFERROR(__xludf.DUMMYFUNCTION("""COMPUTED_VALUE"""),9) -> 9 | K10: =NOT(ISBLANK(H10)) -> TRUE
B11: =IFERROR(NOT(ISBLANK(D11)), FALSE) -> FALSE | C11: Apt 3 Rent | G11: =NOT(ISBLANK(D11)) -> FALSE | H11: =IFERROR(__xludf.DUMMYFUNCTION("""COMPUTED_VALUE"""),"BOA Unlimited Rewards") -> BOA Unlimited Rewards | I11: =IFERROR(__xludf.DUMMYFUNCTION("""COMPUTED_VALUE"""),4) -> 4 | J11: =IFERROR(__xludf.DUMMYFUNCTION("""COMPUTED_VALUE"""),151) -> 151 | K11: =NOT(ISBLANK(H11)) -> TRUE
B12: =IFERROR(NOT(ISBLANK(D12)), FALSE) -> FALSE | C12: Uber Income | G12: =NOT(ISBLANK(D12)) -> FALSE | H12: =IFERROR(__xludf.DUMMYFUNCTION("""COMPUTED_VALUE"""),"CHASE Freedom") -> CHASE Freedom | I12: =IFERROR(__xludf.DUMMYFUNCTION("""COMPUTED_VALUE"""),15) -> 15 | K12: =NOT(ISBLANK(H12)) -> TRUE
B13: =IFERROR(NOT(ISBLANK(D13)), FALSE) -> FALSE | G13: =NOT(ISBLANK(D13)) -> FALSE | H13: =IFERROR(__xludf.DUMMYFUNCTION("""COMPUTED_VALUE"""),"CITI Diamond Preferred") -> CITI Diamond Preferred | I13: =IFERROR(__xludf.DUMMYFUNCTION("""COMPUTED_VALUE"""),15) -> 15 | J13: =IFERROR(__xludf.DUMMYFUNCTION("""COMPUTED_VALUE"""),120) -> 120 | K13: =NOT(ISBLANK(H13)) -> TRUE
B14: =IFERROR(NOT(ISBLANK(D14)), FALSE) -> FALSE | C14: Total Income | E14: =SUM(E8:E12) -> 6410.14 | G14: =NOT(ISBLANK(D14)) -> FALSE | H14: =IFERROR(__xludf.DUMMYFUNCTION("""COMPUTED_VALUE"""),"CITIZENS Clear Value") -> CITIZENS Clear Value | I14: =IFERROR(__xludf.DUMMYFUNCTION("""COMPUTED_VALUE"""),13) -> 13 | J14: =IFERROR(__xludf.DUMMYFUNCTION("""COMPUTED_VALUE"""),64) -> 64 | K14: =NOT(ISBLANK(H14)) -> TRUE
B15: =IFERROR(NOT(ISBLANK(D15)), FALSE) -> FALSE | G15: =NOT(ISBLANK(D15)) -> FALSE | H15: =IFERROR(__xludf.DUMMYFUNCTION("""COMPUTED_VALUE"""),"CITIZENS HELOC") -> CITIZENS HELOC | I15: =IFERROR(__xludf.DUMMYFUNCTION("""COMPUTED_VALUE"""),15) -> 15 | J15: =IFERROR(__xludf.DUMMYFUNCTION("""COMPUTED_VALUE"""),95.95) -> 95.95 | K15: =NOT(ISBLANK(H15)) -> TRUE
B16: =IFERROR(NOT(ISBLANK(D16)), FALSE) -> FALSE | C16: Credit Cards | G16: =NOT(ISBLANK(D16)) -> FALSE | H16: =IFERROR(__xludf.DUMMYFUNCTION("""COMPUTED_VALUE"""),"UPSTART Debt Consolidation") -> UPSTART Debt Consolidation | I16: =IFERROR(__xludf.DUMMYFUNCTION("""COMPUTED_VALUE"""),15) -> 15 | J16: =IFERROR(__xludf.DUMMYFUNCTION("""COMPUTED_VALUE"""),181.13) -> 181.13 | K16: =NOT(ISBLANK(H16)) -> TRUE
B17: =IFERROR(NOT(ISBLANK(D17)), FALSE) -> TRUE | C17: BOA Customized Rewards | D17: 9 | G17: =NOT(ISBLANK(D17)) -> TRUE | H17: =IFERROR(__xludf.DUMMYFUNCTION("""COMPUTED_VALUE"""),"AQUA FINANCE Roofing Replacement") -> AQUA FINANCE Roofing Replacement | I17: =IFERROR(__xludf.DUMMYFUNCTION("""COMPUTED_VALUE"""),6) -> 6 | J17: =IFERROR(__xludf.DUMMYFUNCTION("""COMPUTED_VALUE"""),268.44) -> 268.44 | K17: =NOT(ISBLANK(H17)) -> TRUE
C18: BOA Unlimited Rewards | D18: 4 | E18: 151 | G18: =NOT(ISBLANK(D18)) -> TRUE | H18: =IFERROR(__xludf.DUMMYFUNCTION("""COMPUTED_VALUE"""),"TD Auto Loan") -> TD Auto Loan | I18: =IFERROR(__xludf.DUMMYFUNCTION("""COMPUTED_VALUE"""),17) -> 17 | J18: =IFERROR(__xludf.DUMMYFUNCTION("""COMPUTED_VALUE"""),595) -> 595 | K18: =NOT(ISBLANK(H18)) -> TRUE
C19: CHASE Freedom | D19: 15 | G19: =NOT(ISBLANK(D19)) -> TRUE | H19: =IFERROR(__xludf.DUMMYFUNCTION("""COMPUTED_VALUE"""),"Owner Contribution to Mortgage") -> Owner Contribution to Mortgage | I19: =IFERROR(__xludf.DUMMYFUNCTION("""COMPUTED_VALUE"""),1) -> 1 | J19: =IFERROR(__xludf.DUMMYFUNCTION("""COMPUTED_VALUE"""),146.54) -> 146.54 | K19: =NOT(ISBLANK(H19)) -> TRUE
C20: CITI Diamond Preferred | D20: 15 | E20: 120 | G20: =NOT(ISBLANK(D20)) -> TRUE | H20: =IFERROR(__xludf.DUMMYFUNCTION("""COMPUTED_VALUE"""),"Landlord Electricity") -> Landlord Electricity | I20: =IFERROR(__xludf.DUMMYFUNCTION("""COMPUTED_VALUE"""),1) -> 1 | J20: =IFERROR(__xludf.DUMMYFUNCTION("""COMPUTED_VALUE"""),33.16) -> 33.16 | K20: =NOT(ISBLANK(H20)) -> TRUE
B21: =IFERROR(NOT(ISBLANK(D21)), FALSE) -> TRUE | C21: CITIZENS Clear Value | D21: 13 | E21: 64 | G21: =NOT(ISBLANK(D21)) -> TRUE | H21: =IFERROR(__xludf.DUMMYFUNCTION("""COMPUTED_VALUE"""),"Maintenance (Lawn)") -> Maintenance (Lawn) | I21: =IFERROR(__xludf.DUMMYFUNCTION("""COMPUTED_VALUE"""),10) -> 10 | J21: =IFERROR(__xludf.DUMMYFUNCTION("""COMPUTED_VALUE"""),80) -> 80 | K21: =NOT(ISBLANK(H21)) -> TRUE
B22: =IFERROR(NOT(ISBLANK(D22)), FALSE) -> FALSE | G22: =NOT(ISBLANK(D22)) -> FALSE | H22: =IFERROR(__xludf.DUMMYFUNCTION("""COMPUTED_VALUE"""),"Maintenance (Lawn)") -> Maintenance (Lawn) | I22: =IFERROR(__xludf.DUMMYFUNCTION("""COMPUTED_VALUE"""),24) -> 24 | J22: =IFERROR(__xludf.DUMMYFUNCTION("""COMPUTED_VALUE"""),80) -> 80 | K22: =NOT(ISBLANK(H22)) -> TRUE
B23: =IFERROR(NOT(ISBLANK(D23)), FALSE) -> FALSE | C23: Loan Payments | G23: =NOT(ISBLANK(D23)) -> FALSE | H23: =IFERROR(__xludf.DUMMYFUNCTION("""COMPUTED_VALUE"""),"Blink Security") -> Blink Security | I23: =IFERROR(__xludf.DUMMYFUNCTION("""COMPUTED_VALUE"""),1) -> 1 | J23: =IFERROR(__xludf.DUMMYFUNCTION("""COMPUTED_VALUE"""),10.64) -> 10.64 | K23: =NOT(ISBLANK(H23)) -> TRUE
B24: =IFERROR(NOT(ISBLANK(D24)), FALSE) -> TRUE | C24: CITIZENS HELOC | D24: 15 | E24: 380 | G24: =NOT(ISBLANK(D24)) -> TRUE | H24: =IFERROR(__xludf.DUMMYFUNCTION("""COMPUTED_VALUE"""),"Avail Portal") -> Avail Portal | I24: =IFERROR(__xludf.DUMMYFUNCTION("""COMPUTED_VALUE"""),1) -> 1 | J24: =IFERROR(__xludf.DUMMYFUNCTION("""COMPUTED_VALUE"""),18) -> 18 | K24: =NOT(ISBLANK(H24)) -> TRUE
C25: UPSTART Debt Consolidation | D25: 15 | E25: 181.13 | G25: =NOT(ISBLANK(D25)) -> TRUE | H25: =IFERROR(__xludf.DUMMYFUNCTION("""COMPUTED_VALUE"""),"Auto Insurance") -> Auto Insurance | I25: =IFERROR(__xludf.DUMMYFUNCTION("""COMPUTED_VALUE"""),4) -> 4 | J25: =IFERROR(__xludf.DUMMYFUNCTION("""COMPUTED_VALUE"""),353.71) -> 353.71 | K25: =NOT(ISBLANK(H25)) -> TRUE
C26: AQUA FINANCE Roofing Replacement | D26: 6 | E26: 268.44 | G26: =NOT(ISBLANK(D26)) -> TRUE | H26: =IFERROR(__xludf.DUMMYFUNCTION("""COMPUTED_VALUE"""),"Heating/Natural Gas") -> Heating/Natural Gas | I26: =IFERROR(__xludf.DUMMYFUNCTION("""COMPUTED_VALUE"""),15) -> 15 | J26: =IFERROR(__xludf.DUMMYFUNCTION("""COMPUTED_VALUE"""),175) -> 175 | K26: =NOT(ISBLANK(H26)) -> TRUE
B27: =IFERROR(NOT(ISBLANK(D27)), FALSE) -> TRUE | C27: TD Auto Loan | D27: 17 | E27: 595 | G27: =NOT(ISBLANK(D27)) -> TRUE | H27: =IFERROR(__xludf.DUMMYFUNCTION("""COMPUTED_VALUE"""),"Electricity") -> Electricity | I27: =IFERROR(__xludf.DUMMYFUNCTION("""COMPUTED_VALUE"""),1) -> 1 | J27: =IFERROR(__xludf.DUMMYFUNCTION("""COMPUTED_VALUE"""),192.43) -> 192.43 | K27: =NOT(ISBLANK(H27)) -> TRUE
B28: =IFERROR(NOT(ISBLANK(D28)), FALSE) -> FALSE | C28: NELNET Student Loans | G28: =NOT(ISBLANK(D28)) -> FALSE | H28: =IFERROR(__xludf.DUMMYFUNCTION("""COMPUTED_VALUE"""),"Internet") -> Internet | I28: =IFERROR(__xludf.DUMMYFUNCTION("""COMPUTED_VALUE"""),27) -> 27 | J28: =IFERROR(__xludf.DUMMYFUNCTION("""COMPUTED_VALUE"""),74.95) -> 74.95 | K28: =NOT(ISBLANK(H28)) -> TRUE
B29: =IFERROR(NOT(ISBLANK(D29)), FALSE) -> FALSE | G29: =NOT(ISBLANK(D29)) -> FALSE | H29: =IFERROR(__xludf.DUMMYFUNCTION("""COMPUTED_VALUE"""),"Life Insurance") -> Life Insurance | I29: =IFERROR(__xludf.DUMMYFUNCTION("""COMPUTED_VALUE"""),16) -> 16 | J29: =IFERROR(__xludf.DUMMYFUNCTION("""COMPUTED_VALUE"""),82.37) -> 82.37 | K29: =NOT(ISBLANK(H29)) -> TRUE
B30: =IFERROR(NOT(ISBLANK(D30)), FALSE) -> FALSE | C30: Propery Expenses | G30: =NOT(ISBLANK(D30)) -> FALSE | H30: =IFERROR(__xludf.DUMMYFUNCTION("""COMPUTED_VALUE"""),"Groceries + Toiletries") -> Groceries + Toiletries | I30: =IFERROR(__xludf.DUMMYFUNCTION("""COMPUTED_VALUE"""),3) -> 3 | J30: =IFERROR(__xludf.DUMMYFUNCTION("""COMPUTED_VALUE"""),250) -> 250 | K30: =NOT(ISBLANK(H30)) -> TRUE
B31: =IFERROR(NOT(ISBLANK(D31)), FALSE) -> TRUE | C31: Owner Contribution to Mortgage | D31: 1 | E31: 146.54 | G31: =NOT(ISBLANK(D31)) -> TRUE | H31: =IFERROR(__xludf.DUMMYFUNCTION("""COMPUTED_VALUE"""),"Groceries + Toiletries") -> Groceries + Toiletries | I31: =IFERROR(__xludf.DUMMYFUNCTION("""COMPUTED_VALUE"""),10) -> 10 | J31: =IFERROR(__xludf.DUMMYFUNCTION("""COMPUTED_VALUE"""),250) -> 250 | K31: =NOT(ISBLANK(H31)) -> TRUE
B32: =IFERROR(NOT(ISBLANK(D32)), FALSE) -> TRUE | C32: Landlord Electricity | D32: 1 | E32: 33.16 | G32: =NOT(ISBLANK(D32)) -> TRUE | H32: =IFERROR(__xludf.DUMMYFUNCTION("""COMPUTED_VALUE"""),"Groceries + Toiletries") -> Groceries + Toiletries | I32: =IFERROR(__xludf.DUMMYFUNCTION("""COMPUTED_VALUE"""),17) -> 17 | J32: =IFERROR(__xludf.DUMMYFUNCTION("""COMPUTED_VALUE"""),250) -> 250 | K32: =NOT(ISBLANK(H32)) -> TRUE
B33: =IFERROR(NOT(ISBLANK(D33)), FALSE) -> FALSE | C33: Water/Sewer (Monthly) | E33: 130 | G33: =NOT(ISBLANK(D33)) -> FALSE | H33: =IFERROR(__xludf.DUMMYFUNCTION("""COMPUTED_VALUE"""),"Groceries + Toiletries") -> Groceries + Toiletries | I33: =IFERROR(__xludf.DUMMYFUNCTION("""COMPUTED_VALUE"""),24) -> 24 | J33: =IFERROR(__xludf.DUMMYFUNCTION("""COMPUTED_VALUE"""),250) -> 250 | K33: =NOT(ISBLANK(H33)) -> TRUE
B34: =IFERROR(NOT(ISBLANK(D34)), FALSE) -> TRUE | C34: Maintenance (Lawn) | D34: 10 | E34: =IF($D$2="Summer", 80, 0) -> 80 | G34: =NOT(ISBLANK(D34)) -> TRUE | H34: =IFERROR(__xludf.DUMMYFUNCTION("""COMPUTED_VALUE"""),"Phone (Nykosi)") -> Phone (Nykosi) | I34: =IFERROR(__xludf.DUMMYFUNCTION("""COMPUTED_VALUE"""),16) -> 16 | J34: =IFERROR(__xludf.DUMMYFUNCTION("""COMPUTED_VALUE"""),30) -> 30 | K34: =NOT(ISBLANK(H34)) -> TRUE
B35: =IFERROR(NOT(ISBLANK(D35)), FALSE) -> TRUE | C35: Maintenance (Lawn) | D35: 24 | E35: =IF($D$2="Summer", 80, 0) -> 80 | G35: =NOT(ISBLANK(D35)) -> TRUE | H35: =IFERROR(__xludf.DUMMYFUNCTION("""COMPUTED_VALUE"""),"Phone (Brittany)") -> Phone (Brittany) | I35: =IFERROR(__xludf.DUMMYFUNCTION("""COMPUTED_VALUE"""),16) -> 16 | J35: =IFERROR(__xludf.DUMMYFUNCTION("""COMPUTED_VALUE"""),50) -> 50 | K35: =NOT(ISBLANK(H35)) -> TRUE
B36: =IFERROR(NOT(ISBLANK(D36)), FALSE) -> FALSE | C36: Maintenance (Snow Removal) | E36: =IF($D$2="Winter", 110, 0) -> 0 | G36: =NOT(ISBLANK(D36)) -> FALSE | H36: =IFERROR(__xludf.DUMMYFUNCTION("""COMPUTED_VALUE"""),"Gym Membership (Nykosi)") -> Gym Membership (Nykosi) | I36: =IFERROR(__xludf.DUMMYFUNCTION("""COMPUTED_VALUE"""),24) -> 24 | J36: =IFERROR(__xludf.DUMMYFUNCTION("""COMPUTED_VALUE"""),22.23) -> 22.23 | K36: =NOT(ISBLANK(H36)) -> TRUE
B37: =IFERROR(NOT(ISBLANK(D37)), FALSE) -> TRUE | C37: Blink Security | D37: 1 | E37: 10.64 | G37: =NOT(ISBLANK(D37)) -> TRUE | H37: =IFERROR(__xludf.DUMMYFUNCTION("""COMPUTED_VALUE"""),"Gym Membership (Brittany)") -> Gym Membership (Brittany) | I37: =IFERROR(__xludf.DUMMYFUNCTION("""COMPUTED_VALUE"""),6) -> 6 | J37: =IFERROR(__xludf.DUMMYFUNCTION("""COMPUTED_VALUE"""),32.87) -> 32.87 | K37: =NOT(ISBLANK(H37)) -> TRUE
B38: =IFERROR(NOT(ISBLANK(D38)), FALSE) -> TRUE | C38: Avail Portal | D38: 1 | E38: 18 | G38: =NOT(ISBLANK(D38)) -> TRUE | H38: =IFERROR(__xludf.DUMMYFUNCTION("""COMPUTED_VALUE"""),"Gym Trainer (Brittany)") -> Gym Trainer (Brittany) | I38: =IFERROR(__xludf.DUMMYFUNCTION("""COMPUTED_VALUE"""),14) -> 14 | J38: =IFERROR(__xludf.DUMMYFUNCTION("""COMPUTED_VALUE"""),105.29) -> 105.29 | K38: =NOT(ISBLANK(H38)) -> TRUE
B39: =IFERROR(NOT(ISBLANK(D39)), FALSE) -> FALSE | G39: =NOT(ISBLANK(D39)) -> FALSE | H39: =IFERROR(__xludf.DUMMYFUNCTION("""COMPUTED_VALUE"""),"Gym Trainer (Brittany)") -> Gym Trainer (Brittany) | I39: =IFERROR(__xludf.DUMMYFUNCTION("""COMPUTED_VALUE"""),28) -> 28 | J39: =IFERROR(__xludf.DUMMYFUNCTION("""COMPUTED_VALUE"""),105.29) -> 105.29 | K39: =NOT(ISBLANK(H39)) -> TRUE
B40: =IFERROR(NOT(ISBLANK(D40)), FALSE) -> FALSE | C40: Bills | G40: =NOT(ISBLANK(D40)) -> FALSE | H40: =IFERROR(__xludf.DUMMYFUNCTION("""COMPUTED_VALUE"""),"Amazon Prime") -> Amazon Prime | I40: =IFERROR(__xludf.DUMMYFUNCTION("""COMPUTED_VALUE"""),14) -> 14 | J40: =IFERROR(__xludf.DUMMYFUNCTION("""COMPUTED_VALUE"""),14.99) -> 14.99 | K40: =NOT(ISBLANK(H40)) -> TRUE
B41: =IFERROR(NOT(ISBLANK(D41)), FALSE) -> TRUE | C41: Auto Insurance | D41: 4 | E41: 353.71 | G41: =NOT(ISBLANK(D41)) -> TRUE | H41: =IFERROR(__xludf.DUMMYFUNCTION("""COMPUTED_VALUE"""),"Microsoft 365") -> Microsoft 365 | I41: =IFERROR(__xludf.DUMMYFUNCTION("""COMPUTED_VALUE"""),17) -> 17 | J41: =IFERROR(__xludf.DUMMYFUNCTION("""COMPUTED_VALUE"""),14.14) -> 14.14 | K41: =NOT(ISBLANK(H41)) -> TRUE
B42: =IFERROR(NOT(ISBLANK(D42)), FALSE) -> FALSE | C42: Auto Taxes (Monthly) | G42: =NOT(ISBLANK(D42)) -> FALSE | H42: =IFERROR(__xludf.DUMMYFUNCTION("""COMPUTED_VALUE"""),"Netflix") -> Netflix | I42: =IFERROR(__xludf.DUMMYFUNCTION("""COMPUTED_VALUE"""),23) -> 23 | J42: =IFERROR(__xludf.DUMMYFUNCTION("""COMPUTED_VALUE"""),19.3) -> 19.3 | K42: =NOT(ISBLANK(H42)) -> TRUE
B43: =IFERROR(NOT(ISBLANK(D43)), FALSE) -> TRUE | C43: Heating/Natural Gas | D43: 15 | E43: 175 | G43: =NOT(ISBLANK(D43)) -> TRUE | H43: =IFERROR(__xludf.DUMMYFUNCTION("""COMPUTED_VALUE"""),"YNAB ") -> YNAB | I43: =IFERROR(__xludf.DUMMYFUNCTION("""COMPUTED_VALUE"""),9) -> 9 | J43: =IFERROR(__xludf.DUMMYFUNCTION("""COMPUTED_VALUE"""),14.99) -> 14.99 | K43: =NOT(ISBLANK(H43)) -> TRUE
B44: =IFERROR(NOT(ISBLANK(D44)), FALSE) -> TRUE | C44: Electricity | D44: 1 | E44: 192.43 | G44: =NOT(ISBLANK(D44)) -> TRUE | H44: =IFERROR(__xludf.DUMMYFUNCTION("""COMPUTED_VALUE"""),"OpenAI") -> OpenAI | I44: =IFERROR(__xludf.DUMMYFUNCTION("""COMPUTED_VALUE"""),16) -> 16 | J44: =IFERROR(__xludf.DUMMYFUNCTION("""COMPUTED_VALUE"""),20.2) -> 20.2 | K44: =NOT(ISBLANK(H44)) -> TRUE
B45: =IFERROR(NOT(ISBLANK(D45)), FALSE) -> TRUE | C45: Internet | D45: 27 | E45: 74.95 | G45: =NOT(ISBLANK(D45)) -> TRUE | K45: =NOT(ISBLANK(H45)) -> FALSE
B46: =IFERROR(NOT(ISBLANK(D46)), FALSE) -> TRUE | C46: Life Insurance | D46: 16 | E46: 82.37 | G46: =NOT(ISBLANK(D46)) -> TRUE | K46: =NOT(ISBLANK(H46)) -> FALSE
B47: =IFERROR(NOT(ISBLANK(D47)), FALSE) -> FALSE | G47: =NOT(ISBLANK(D47)) -> FALSE | K47: =NOT(ISBLANK(H47)) -> FALSE
B48: =IFERROR(NOT(ISBLANK(D48)), FALSE) -> FALSE | C48: Expenses (Needs) | G48: =NOT(ISBLANK(D48)) -> FALSE | K48: =NOT(ISBLANK(H48)) -> FALSE
B49: =IFERROR(NOT(ISBLANK(D49)), FALSE) -> TRUE | C49: Groceries + Toiletries | D49: 3 | E49: 250 | G49: =NOT(ISBLANK(D49)) -> TRUE | K49: =NOT(ISBLANK(H49)) -> FALSE
B50: =IFERROR(NOT(ISBLANK(D50)), FALSE) -> TRUE | C50: Groceries + Toiletries | D50: 10 | E50: 250 | G50: =NOT(ISBLANK(D50)) -> TRUE | K50: =NOT(ISBLANK(H50)) -> FALSE
B51: =IFERROR(NOT(ISBLANK(D51)), FALSE) -> TRUE | C51: Groceries + Toiletries | D51: 17 | E51: 250 | G51: =NOT(ISBLANK(D51)) -> TRUE | K51: =NOT(ISBLANK(H51)) -> FALSE
B52: =IFERROR(NOT(ISBLANK(D52)), FALSE) -> TRUE | C52: Groceries + Toiletries | D52: 24 | E52: 250 | G52: =NOT(ISBLANK(D52)) -> TRUE | K52: =NOT(ISBLANK(H52)) -> FALSE
B53: =IFERROR(NOT(ISBLANK(D53)), FALSE) -> TRUE | C53: Phone (Nykosi) | D53: 16 | E53: 30 | G53: =NOT(ISBLANK(D53)) -> TRUE | K53: =NOT(ISBLANK(H53)) -> FALSE
B54: =IFERROR(NOT(ISBLANK(D54)), FALSE) -> TRUE | C54: Phone (Brittany) | D54: 16 | E54: 50 | G54: =NOT(ISBLANK(D54)) -> TRUE | K54: =NOT(ISBLANK(H54)) -> FALSE
B55: =IFERROR(NOT(ISBLANK(D55)), FALSE) -> FALSE | G55: =NOT(ISBLANK(D55)) -> FALSE | K55: =NOT(ISBLANK(H55)) -> FALSE
B56: =IFERROR(NOT(ISBLANK(D56)), FALSE) -> FALSE | C56: Expenses (Wants) | G56: =NOT(ISBLANK(D56)) -> FALSE | K56: =NOT(ISBLANK(H56)) -> FALSE
B57: =IFERROR(NOT(ISBLANK(D57)), FALSE) -> TRUE | C57: Gym Membership (Nykosi) | D57: 24 | E57: 22.23 | G57: =NOT(ISBLANK(D57)) -> TRUE | K57: =NOT(ISBLANK(H57)) -> FALSE
B58: =IFERROR(NOT(ISBLANK(D58)), FALSE) -> TRUE | C58: Gym Membership (Brittany) | D58: 6 | E58: 32.87 | G58: =NOT(ISBLANK(D58)) -> TRUE | K58: =NOT(ISBLANK(H58)) -> FALSE
B59: =IFERROR(NOT(ISBLANK(D59)), FALSE) -> TRUE | C59: Gym Trainer (Brittany) | D59: 14 | E59: 105.29 | G59: =NOT(ISBLANK(D59)) -> TRUE | K59: =NOT(ISBLANK(H59)) -> FALSE
B60: =IFERROR(NOT(ISBLANK(D60)), FALSE) -> TRUE | C60: Gym Trainer (Brittany) | D60: 28 | E60: 105.29 | G60: =NOT(ISBLANK(D60)) -> TRUE | K60: =NOT(ISBLANK(H60)) -> FALSE
B61: =IFERROR(NOT(ISBLANK(D61)), FALSE) -> TRUE | C61: Amazon Prime | D61: 14 | E61: 14.99 | G61: =NOT(ISBLANK(D61)) -> TRUE | K61: =NOT(ISBLANK(H61)) -> FALSE
B62: =IFERROR(NOT(ISBLANK(D62)), FALSE) -> TRUE | C62: Microsoft 365 | D62: 17 | E62: 14.14 | G62: =NOT(ISBLANK(D62)) -> TRUE | K62: =NOT(ISBLANK(H62)) -> FALSE
B63: =IFERROR(NOT(ISBLANK(D63)), FALSE) -> TRUE | C63: Netflix | D63: 23 | E63: 19.3 | G63: =NOT(ISBLANK(D63)) -> TRUE | K63: =NOT(ISBLANK(H63)) -> FALSE
B64: =IFERROR(NOT(ISBLANK(D64)), FALSE) -> TRUE | C64: YNAB | D64: 9 | E64: 14.99 | G64: =NOT(ISBLANK(D64)) -> TRUE | K64: =NOT(ISBLANK(H64)) -> FALSE
B65: =IFERROR(NOT(ISBLANK(D65)), FALSE) -> TRUE | C65: OpenAI | D65: 16 | E65: 20.2 | G65: =NOT(ISBLANK(D65)) -> TRUE | K65: =NOT(ISBLANK(H65)) -> FALSE
B66: =IFERROR(NOT(ISBLANK(D66)), FALSE) -> FALSE | G66: =NOT(ISBLANK(D66)) -> FALSE | K66: =NOT(ISBLANK(H66)) -> FALSE
B67: =IFERROR(NOT(ISBLANK(D67)), FALSE) -> FALSE | G67: =NOT(ISBLANK(D67)) -> FALSE | K67: =NOT(ISBLANK(H67)) -> FALSE
B68: =IFERROR(NOT(ISBLANK(D68)), FALSE) -> FALSE | G68: =NOT(ISBLANK(D68)) -> FALSE | K68: =NOT(ISBLANK(H68)) -> FALSE
B69: =IFERROR(NOT(ISBLANK(D69)), FALSE) -> FALSE | C69: One-Time Expenses | G69: =NOT(ISBLANK(D69)) -> FALSE | K69: =NOT(ISBLANK(H69)) -> FALSE
B70: =IFERROR(NOT(ISBLANK(D70)), FALSE) -> FALSE | G70: =NOT(ISBLANK(D70)) -> FALSE | K70: =NOT(ISBLANK(H70)) -> FALSE
B71: =IFERROR(NOT(ISBLANK(D71)), FALSE) -> FALSE | G71: =NOT(ISBLANK(D71)) -> FALSE | K71: =NOT(ISBLANK(H71)) -> FALSE
B72: =IFERROR(NOT(ISBLANK(D72)), FALSE) -> FALSE | G72: =NOT(ISBLANK(D72)) -> FALSE | K72: =NOT(ISBLANK(H72)) -> FALSE
B73: =IFERROR(NOT(ISBLANK(D73)), FALSE) -> FALSE | G73: =NOT(ISBLANK(D73)) -> FALSE | K73: =NOT(ISBLANK(H73)) -> FALSE
B74: =IFERROR(NOT(ISBLANK(D74)), FALSE) -> FALSE | G74: =NOT(ISBLANK(D74)) -> FALSE | K74: =NOT(ISBLANK(H74)) -> FALSE
B75: =IFERROR(NOT(ISBLANK(D75)), FALSE) -> FALSE | C75: Cash After Expenses | E75: =$E$14-SUM($E$17:$E$74) -> 1844.47 | G75: =NOT(ISBLANK(D75)) -> FALSE | K75: =NOT(ISBLANK(H75)) -> FALSE
B76: =IFERROR(NOT(ISBLANK(D76)), FALSE) -> FALSE | G76: =NOT(ISBLANK(D76)) -> FALSE | K76: =NOT(ISBLANK(H76)) -> FALSE
B77: =IFERROR(NOT(ISBLANK(D77)), FALSE) -> FALSE | G77: =NOT(ISBLANK(D77)) -> FALSE | K77: =NOT(ISBLANK(H77)) -> FALSE
B78: =IFERROR(NOT(ISBLANK(D78)), FALSE) -> FALSE | C78: Savings | G78: =NOT(ISBLANK(D78)) -> FALSE | K78: =NOT(ISBLANK(H78)) -> FALSE
B79: =IFERROR(NOT(ISBLANK(D79)), FALSE) -> FALSE | C79: Education 529s | G79: =NOT(ISBLANK(D79)) -> FALSE | K79: =NOT(ISBLANK(H79)) -> FALSE
B80: =IFERROR(NOT(ISBLANK(D80)), FALSE) -> FALSE | C80: Emergency Fund | G80: =NOT(ISBLANK(D80)) -> FALSE | K80: =NOT(ISBLANK(H80)) -> FALSE
G81: =NOT(ISBLANK(D81)) -> FALSE | K81: =NOT(ISBLANK(H81)) -> FALSE
G82: =NOT(ISBLANK(D82)) -> FALSE | K82: =NOT(ISBLANK(H82)) -> FALSE
G83: =NOT(ISBLANK(D83)) -> FALSE | K83: =NOT(ISBLANK(H83)) -> FALSE
G84: =NOT(ISBLANK(D84)) -> FALSE | K84: =NOT(ISBLANK(H84)) -> FALSE
G85: =NOT(ISBLANK(D85)) -> FALSE | K85: =NOT(ISBLANK(H85)) -> FALSE
G86: =NOT(ISBLANK(D86)) -> FALSE | K86: =NOT(ISBLANK(H86)) -> FALSE
G87: =NOT(ISBLANK(D87)) -> FALSE | K87: =NOT(ISBLANK(H87)) -> FALSE
G88: =NOT(ISBLANK(D88)) -> FALSE | K88: =NOT(ISBLANK(H88)) -> FALSE
G89: =NOT(ISBLANK(D89)) -> FALSE | K89: =NOT(ISBLANK(H89)) -> FALSE
G90: =NOT(ISBLANK(D90)) -> FALSE | K90: =NOT(ISBLANK(H90)) -> FALSE
G91: =NOT(ISBLANK(D91)) -> FALSE | K91: =NOT(ISBLANK(H91)) -> FALSE
G92: =NOT(ISBLANK(D92)) -> FALSE | K92: =NOT(ISBLANK(H92)) -> FALSE
... G96: =NOT(ISBLANK(D96)) -> FALSE | K96: =NOT(ISBLANK(H96)) -> FALSE

Sheet DONOTUSE
A1: Category & Description Dropdowns
A2: Categories | B2: {=TRANSPOSE(_xlfn.UNIQUE(_xlfn._xlws.FILTER(SETUP!$C$6:$C$100, NOT(ISBLANK(SETUP!$C$6:$C$100))),FALSE,FALSE))} -> Income | C2: Property Expenses | D2: Fixed Expenses | E2: Variable Expenses | F2: Loan Payments | G2: Credit Card Payments | H2: Savings | I2: Investments
A3: {=_xlfn.UNIQUE(_xlfn._xlws.FILTER(SETUP!$C$6:$C$100, NOT(ISBLANK(SETUP!$C$6:$C$100))),FALSE,FALSE)} -> Income | B3: {=_xlfn._xlws.FILTER(SETUP!$D$6:$D$100, --(SETUP!$C$6:$C$100=B$2))} -> CVS Income | C3: {=_xlfn._xlws.FILTER(SETUP!$D$6:$D$100, --(SETUP!$C$6:$C$100=C$2))} -> Mortgage | D3: {=_xlfn._xlws.FILTER(SETUP!$D$6:$D$100, --(SETUP!$C$6:$C$100=D$2))} -> Auto Insurance | E3: {=_xlfn._xlws.FILTER(SETUP!$D$6:$D$100, --(SETUP!$C$6:$C$100=E$2))} -> Heating/Natural Gas | F3: {=_xlfn._xlws.FILTER(SETUP!$D$6:$D$100, --(SETUP!$C$6:$C$100=F$2))} -> CITIZENS HELOC | G3: {=_xlfn._xlws.FILTER(SETUP!$D$6:$D$100, --(SETUP!$C$6:$C$100=G$2))} -> BOA Customized Rewards | H3: {=_xlfn._xlws.FILTER(SETUP!$D$6:$D$100, --(SETUP!$C$6:$C$100=H$2))} -> 0 | I3: {=_xlfn._xlws.FILTER(SETUP!$D$6:$D$100, --(SETUP!$C$6:$C$100=I$2))} -> 0
A4: Property Expenses | B4: Apt 2 Rent | C4: Owner Contribution to Mortgage | D4: Auto Taxes (Monthly) | E4: Electricity | F4: UPSTART Debt Consolidation | G4: BOA Unlimited Rewards
A5: Fixed Expenses | B5: Apt 3 Rent | C5: Landlord Electricity | D5: Internet | E5: Groceries + Toiletries | F5: AQUA FINANCE Roofing Replacement | G5: CHASE Freedom
A6: Variable Expenses | B6: Uber Driver | C6: Water/Sewer (Monthly) | D6: Life Insurance | E6: Gym Trainer (Brittany) | F6: TD Auto Loan | G6: CITI Diamond Preferred
A7: Loan Payments | C7: Maintenance (Lawn) | D7: Phone (Nykosi) | F7: NELNET Student Loans | G7: CITIZENS Clear Value
A8: Credit Card Payments | C8: Maintenance (Lawn) | D8: Phone (Brittany) | F8: XXX Heating Systems
A9: Savings | C9: Maintenance (Snow Removal) | D9: Gym Membership (Nykosi)
A10: Investments | C10: Blink Security | D10: Gym Membership (Brittany)
C11: Avail Portal | D11: Amazon Prime
D12: Microsoft 365
D13: Netflix
D14: YNAB
D15: OpenAI

Sheet Budget
B2: Budget
B3: Category | C3: Description | D3: Due Date | E3: ="Amount "&" ("&'[1]Start Here'!$H$17&")" -> Amount ($) | F3: Include? | G3: Hide | H3: ="Amount for Cashflow "&" ("&'[1]Start Here'!$H$17&")" -> Amount for Cashflow ($)
B5: Loan Payments | C5: CITIZENS HELOC

Sheet Transactions
B2: Transactions
B3: Date | C3: Merchant | D3: Category | E3: Description | F3: ="Amount "&" ("&'[1]Start Here'!$H$17&")" -> Amount ($)

Sheet Budget_TEMPLATE
B2: ="Budget" -> Budget | G2: BUDGET VS ACTUAL CASHFLOW | L2: BUDGET STATUS | Q2: BUDGET SUMMARY | V2: BUDGET VS ACTUAL ALL CATEGORIES | AA2: WHERE DOES MY MONEY GO?
L3: LEFT TO BUDGET Total Budget Income less Total Budget Allocated | N3: ='[1]Start Here'!$H$17&TEXT(C130-SUM(M130,R130,W130,AB130,AG130),"#,##0") -> $0 | R3: Budget | S3: Actual | T3: Variance | AA3: BUDGET | AF3: ACTUAL
Q4: INCOME | R4: =B17 -> $0 | S4: =B20 -> $0 | T4: =IF(E130>=0,'[1]Start Here'!$H$25&TEXT(E130,"#,##0"),'[1]Start Here'!$H$25&TEXT(E130*-1,"#,##0")) -> 0
B6: BUDGET PERIOD | Q6: OUTGOINGS All Categories ex Income | R6: ='[1]Start Here'!$H$17&TEXT(SUM(M130,R130,W130,AB130,AG130),"#,##0") -> $0 | S6: ='[1]Start Here'!$H$17&TEXT(SUM(N130,S130,X130,AC130,AH130),"#,##0") -> $0 | T6: ='[1]Start Here'!$H$17&TEXT(SUM(N130,S130,X130,AC130,AH130)-SUM(M130,R130,W130,AB130,AG130),"#,##0") -> $0
B7: Start Date -> | C7: 45717
B8: End Date -> | C8: 45747 | L8: LEFT TO SPEND, SAVE, INVEST Total Actual Income less Total Actual Outgoings | N8: ='[1]Start Here'!$H$17&TEXT(D130-SUM(N130,S130,X130,AC130,AH130),"#,##0") -> $0 | Q8: NET Income less Outgoings | R8: ='[1]Start Here'!$H$17&TEXT(C130-SUM(M130,R130,W130,AB130,AG130),"#,##0") -> $0 | S8: ='[1]Start Here'!$H$17&TEXT(D130-SUM(N130,S130,X130,AC130,AH130),"#,##0") -> $0 | T8: ='[1]Start Here'!$H$17&TEXT((D130-SUM(N130,S130,X130,AC130,AH130))-(C130-SUM(M130,R130,W130,AB130,AG130)),"#,##0") -> $0
B9: ="Selected budget period is "&_xlfn.DAYS(C8,C7)&" days long" -> Selected budget period is 30 days long
Q11: % INCOME SAVED Total Savings / Total Income | R11: =AB130/C130 -> #DIV/0! | S11: =AC130/D130 -> #DIV/0! | T11: =S11-R11 -> #DIV/0!
B12: =TEXT(AU1072/AU1073,"#%")&" complete ("&IF(AU1071=1,AU1071&" day remaining)",AU1071&" days remaining)") -> #DIV/0! | G12: Starting Balance:
B15: INCOME | G15: PROPERY EXPENSES | L15: FIXED EXPENSES | Q15: VARIABLE EXPENSES | V15: LOAN REPAYMENTS | AA15: SAVINGS | AF15: INVESTMENTS
B17: ='[1]Start Here'!$H$17&TEXT(C130,"#,##0") -> $0 | G17: ='[1]Start Here'!$H$17&TEXT(H130,"#,##0") -> $0 | L17: ='[1]Start Here'!$H$17&TEXT(M130,"#,##0") -> $0 | Q17: ='[1]Start Here'!$H$17&TEXT(R130,"#,##0") -> $0 | V17: ='[1]Start Here'!$H$17&TEXT(W130,"#,##0") -> $0 | AA17: ='[1]Start Here'!$H$17&TEXT(AB130,"#,##0") -> $0 | AF17: ='[1]Start Here'!$H$17&TEXT(AG130,"#,##0") -> $0
C18: =IFERROR(D130/C130,"") | H18: =IFERROR(I130/H130,"") | M18: =IFERROR(N130/M130,"") | R18: =IFERROR(S130/R130,"") | W18: =IFERROR(X130/W130,"") | AB18: =IFERROR(AC130/AB130,"") | AG18: =IFERROR(AH130/AG130,"")
B19: TOTAL BUDGET | G19: TOTAL BUDGET | L19: TOTAL BUDGET | Q19: TOTAL BUDGET | V19: TOTAL BUDGET | AA19: TOTAL BUDGET | AF19: TOTAL BUDGET
B20: ='[1]Start Here'!$H$17&TEXT(D130,"#,##0") -> $0 | G20: ='[1]Start Here'!$H$17&TEXT(I130,"#,##0") -> $0 | L20: ='[1]Start Here'!$H$17&TEXT(N130,"#,##0") -> $0 | Q20: ='[1]Start Here'!$H$17&TEXT(S130,"#,##0") -> $0 | V20: ='[1]Start Here'!$H$17&TEXT(X130,"#,##0") -> $0 | AA20: ='[1]Start Here'!$H$17&TEXT(AC130,"#,##0") -> $0 | AF20: ='[1]Start Here'!$H$17&TEXT(AH130,"#,##0") -> $0
B22: TOTAL ACTUAL | G22: TOTAL ACTUAL | L22: TOTAL ACTUAL | Q22: TOTAL ACTUAL | V22: TOTAL ACTUAL | AA22: TOTAL ACTUAL | AF22: TOTAL ACTUAL
B23: =IF(D130-C130<0,'[1]Start Here'!$H$17&TEXT((D130-C130)*-1,"#,##0"),'[1]Start Here'!$H$17&TEXT((D130-C130),"#,##0")) -> $0 | G23: =IF(I130-H130<0,'[1]Start Here'!$H$17&TEXT((I130-H130)*-1,"#,##0"),'[1]Start Here'!$H$17&TEXT((I130-H130),"#,##0")) -> $0 | L23: =IF(N130-M130<0,'[1]Start Here'!$H$17&TEXT((N130-M130)*-1,"#,##0"),'[1]Start Here'!$H$17&TEXT((N130-M130),"#,##0")) -> $0 | Q23: =IF(S130-R130<0,'[1]Start Here'!$H$17&TEXT((S130-R130)*-1,"#,##0"),'[1]Start Here'!$H$17&TEXT((S130-R130),"#,##0")) -> $0 | V23: =IF(X130-W130<0,'[1]Start Here'!$H$17&TEXT((X130-W130)*-1,"#,##0"),'[1]Start Here'!$H$17&TEXT((X130-W130),"#,##0")) -> $0 | AA23: =IF(AC130-AB130<0,'[1]Start Here'!$H$17&TEXT((AC130-AB130)*-1,"#,##0"),'[1]Start Here'!$H$17&TEXT((AC130-AB130),"#,##0")) -> $0 | AF23: =IF(AH130-AG130<0,'[1]Start Here'!$H$17&TEXT((AH130-AG130)*-1,"#,##0"),'[1]Start Here'!$H$17&TEXT((AH130-AG130),"#,##0")) -> $0
B25: {=_xlfn.IFS( D130-C130<0,"UNDER BUDGET", D130-C130>0,"OVER BUDGET", D130-C130=0,"ON BUDGET ✅")} -> ON BUDGET ✅ | C25: ACTUAL VS BUDGET | G25: {=_xlfn.IFS( I130-H130<0,"UNDER BUDGET", I130-H130>0,"OVER BUDGET", I130-H130=0,"ON BUDGET ✅")} -> ON BUDGET ✅ | H25: ACTUAL VS BUDGET | L25: {=_xlfn.IFS( N130-M130<0,"UNDER BUDGET", N130-M130>0,"OVER BUDGET", N130-M130=0,"ON BUDGET ✅")} -> ON BUDGET ✅ | M25: ACTUAL VS BUDGET | Q25: {=_xlfn.IFS( S130-R130<0,"UNDER BUDGET", S130-R130>0,"OVER BUDGET", S130-R130=0,"ON BUDGET ✅")} -> ON BUDGET ✅ | R25: ACTUAL VS BUDGET | V25: {=_xlfn.IFS( X130-W130<0,"UNDER BUDGET", X130-W130>0,"OVER BUDGET", X130-W130=0,"ON BUDGET ✅")} -> ON BUDGET ✅ | W25: ACTUAL VS BUDGET | AA25: {=_xlfn.IFS( AC130-AB130<0,"UNDER BUDGET", AC130-AB130>0,"OVER BUDGET", AC130-AB130=0,"ON BUDGET ✅")} -> ON BUDGET ✅ | AB25: ACTUAL VS BUDGET | AF25: {=_xlfn.IFS( AH130-AG130<0,"UNDER BUDGET", AH130-AG130>0,"OVER BUDGET", AH130-AG130=0,"ON BUDGET ✅")} -> ON BUDGET ✅ | AG25: ACTUAL VS BUDGET
B28: Description | C28: ="Budget ("&'[1]Start Here'!$H$17&")" -> Budget ($) | D28: ="Actual ("&'[1]Start Here'!$H$17&")" -> Actual ($) | E28: ="Var. ("&'[1]Start Here'!$H$17&")" -> Var. ($) | G28: Description | H28: ="Budget ("&'[1]Start Here'!$H$17&")" -> Budget ($) | I28: ="Actual ("&'[1]Start Here'!$H$17&")" -> Actual ($) | J28: ="Var. ("&'[1]Start Here'!$H$17&")" -> Var. ($) | L28: Description | M28: ="Budget ("&'[1]Start Here'!$H$17&")" -> Budget ($) | N28: ="Actual ("&'[1]Start Here'!$H$17&")" -> Actual ($) | O28: ="Var. ("&'[1]Start Here'!$H$17&")" -> Var. ($) | Q28: Description | R28: ="Budget ("&'[1]Start Here'!$H$17&")" -> Budget ($) | S28: ="Actual ("&'[1]Start Here'!$H$17&")" -> Actual ($) | T28: ="Var. ("&'[1]Start Here'!$H$17&")" -> Var. ($) | V28: Description | W28: ="Budget ("&'[1]Start Here'!$H$17&")" -> Budget ($) | X28: ="Actual ("&'[1]Start Here'!$H$17&")" -> Actual ($) | Y28: ="Var. ("&'[1]Start Here'!$H$17&")" -> Var. ($) | AA28: Description | AB28: ="Budget ("&'[1]Start Here'!$H$17&")" -> Budget ($) | AC28: ="Actual ("&'[1]Start Here'!$H$17&")" -> Actual ($) | AD28: ="Var. ("&'[1]Start Here'!$H$17&")" -> Var. ($) | AF28: Description | AG28: ="Budget ("&'[1]Start Here'!$H$17&")" -> Budget ($) | AH28: ="Actual ("&'[1]Start Here'!$H$17&")" -> Actual ($) | AI28: ="Var. ("&'[1]Start Here'!$H$17&")" -> Var. ($)
D30: =IF(ISBLANK(C30),"",SUMIF($AN$5:$AN$1004,B30,$AO$5:$AO$1004)) | E30: =IF(ISBLANK(C30),"",D30-C30) | I30: =IF(ISBLANK(H30),"",SUMIF($AN$5:$AN$1004,G30,$AO$5:$AO$1004)) | J30: =IF(ISBLANK(H30),"",I30-H30) | N30: =IF(ISBLANK(M30),"",SUMIF($AN$5:$AN$1004,L30,$AO$5:$AO$1004)) | O30: =IF(ISBLANK(M30),"",N30-M30) | S30: =IF(ISBLANK(R30),"",SUMIF($AN$5:$AN$1004,Q30,$AO$5:$AO$1004)) | T30: =IF(ISBLANK(R30),"",S30-R30) | X30: =IF(ISBLANK(W30),"",SUMIF($AN$5:$AN$1004,V30,$AO$5:$AO$1004)) | Y30: =IF(ISBLANK(W30),"",X30-W30) | AC30: =IF(ISBLANK(AB30),"",SUMIF($AN$5:$AN$1004,AA30,$AO$5:$AO$1004)) | AD30: =IF(ISBLANK(AB30),"",AC30-AB30) | AH30: =IF(ISBLANK(AG30),"",SUMIF($AN$5:$AN$1004,AF30,$AO$5:$AO$1004)) | AI30: =IF(ISBLANK(AG30),"",AH30-AG30)
D31: =IF(ISBLANK(C31),"",SUMIF($AN$5:$AN$1004,B31,$AO$5:$AO$1004)) | E31: =IF(ISBLANK(C31),"",D31-C31) | I31: =IF(ISBLANK(H31),"",SUMIF($AN$5:$AN$1004,G31,$AO$5:$AO$1004)) | J31: =IF(ISBLANK(H31),"",I31-H31) | N31: =IF(ISBLANK(M31),"",SUMIF($AN$5:$AN$1004,L31,$AO$5:$AO$1004)) | O31: =IF(ISBLANK(M31),"",N31-M31) | S31: =IF(ISBLANK(R31),"",SUMIF($AN$5:$AN$1004,Q31,$AO$5:$AO$1004)) | T31: =IF(ISBLANK(R31),"",S31-R31) | X31: =IF(ISBLANK(W31),"",SUMIF($AN$5:$AN$1004,V31,$AO$5:$AO$1004)) | Y31: =IF(ISBLANK(W31),"",X31-W31) | AC31: =IF(ISBLANK(AB31),"",SUMIF($AN$5:$AN$1004,AA31,$AO$5:$AO$1004)) | AD31: =IF(ISBLANK(AB31),"",AC31-AB31) | AH31: =IF(ISBLANK(AG31),"",SUMIF($AN$5:$AN$1004,AF31,$AO$5:$AO$1004)) | AI31: =IF(ISBLANK(AG31),"",AH31-AG31)
D32: =IF(ISBLANK(C32),"",SUMIF($AN$5:$AN$1004,B32,$AO$5:$AO$1004)) | E32: =IF(ISBLANK(C32),"",D32-C32) | I32: =IF(ISBLANK(H32),"",SUMIF($AN$5:$AN$1004,G32,$AO$5:$AO$1004)) | J32: =IF(ISBLANK(H32),"",I32-H32) | N32: =IF(ISBLANK(M32),"",SUMIF($AN$5:$AN$1004,L32,$AO$5:$AO$1004)) | O32: =IF(ISBLANK(M32),"",N32-M32) | S32: =IF(ISBLANK(R32),"",SUMIF($AN$5:$AN$1004,Q32,$AO$5:$AO$1004)) | T32: =IF(ISBLANK(R32),"",S32-R32) | X32: =IF(ISBLANK(W32),"",SUMIF($AN$5:$AN$1004,V32,$AO$5:$AO$1004)) | Y32: =IF(ISBLANK(W32),"",X32-W32) | AC32: =IF(ISBLANK(AB32),"",SUMIF($AN$5:$AN$1004,AA32,$AO$5:$AO$1004)) | AD32: =IF(ISBLANK(AB32),"",AC32-AB32) | AH32: =IF(ISBLANK(AG32),"",SUMIF($AN$5:$AN$1004,AF32,$AO$5:$AO$1004)) | AI32: =IF(ISBLANK(AG32),"",AH32-AG32)
D33: =IF(ISBLANK(C33),"",SUMIF($AN$5:$AN$1004,B33,$AO$5:$AO$1004)) | E33: =IF(ISBLANK(C33),"",D33-C33) | I33: =IF(ISBLANK(H33),"",SUMIF($AN$5:$AN$1004,G33,$AO$5:$AO$1004)) | J33: =IF(ISBLANK(H33),"",I33-H33) | N33: =IF(ISBLANK(M33),"",SUMIF($AN$5:$AN$1004,L33,$AO$5:$AO$1004)) | O33: =IF(ISBLANK(M33),"",N33-M33) | S33: =IF(ISBLANK(R33),"",SUMIF($AN$5:$AN$1004,Q33,$AO$5:$AO$1004)) | T33: =IF(ISBLANK(R33),"",S33-R33) | X33: =IF(ISBLANK(W33),"",SUMIF($AN$5:$AN$1004,V33,$AO$5:$AO$1004)) | Y33: =IF(ISBLANK(W33),"",X33-W33) | AC33: =IF(ISBLANK(AB33),"",SUMIF($AN$5:$AN$1004,AA33,$AO$5:$AO$1004)) | AD33: =IF(ISBLANK(AB33),"",AC33-AB33) | AH33: =IF(ISBLANK(AG33),"",SUMIF($AN$5:$AN$1004,AF33,$AO$5:$AO$1004)) | AI33: =IF(ISBLANK(AG33),"",AH33-AG33)
D34: =IF(ISBLANK(C34),"",SUMIF($AN$5:$AN$1004,B34,$AO$5:$AO$1004)) | E34: =IF(ISBLANK(C34),"",D34-C34) | I34: =IF(ISBLANK(H34),"",SUMIF($AN$5:$AN$1004,G34,$AO$5:$AO$1004)) | J34: =IF(ISBLANK(H34),"",I34-H34) | N34: =IF(ISBLANK(M34),"",SUMIF($AN$5:$AN$1004,L34,$AO$5:$AO$1004)) | O34: =IF(ISBLANK(M34),"",N34-M34) | S34: =IF(ISBLANK(R34),"",SUMIF($AN$5:$AN$1004,Q34,$AO$5:$AO$1004)) | T34: =IF(ISBLANK(R34),"",S34-R34) | X34: =IF(ISBLANK(W34),"",SUMIF($AN$5:$AN$1004,V34,$AO$5:$AO$1004)) | Y34: =IF(ISBLANK(W34),"",X34-W34) | AC34: =IF(ISBLANK(AB34),"",SUMIF($AN$5:$AN$1004,AA34,$AO$5:$AO$1004)) | AD34: =IF(ISBLANK(AB34),"",AC34-AB34) | AH34: =IF(ISBLANK(AG34),"",SUMIF($AN$5:$AN$1004,AF34,$AO$5:$AO$1004)) | AI34: =IF(ISBLANK(AG34),"",AH34-AG34)
D35: =IF(ISBLANK(C35),"",SUMIF($AN$5:$AN$1004,B35,$AO$5:$AO$1004)) | E35: =IF(ISBLANK(C35),"",D35-C35) | I35: =IF(ISBLANK(H35),"",SUMIF($AN$5:$AN$1004,G35,$AO$5:$AO$1004)) | J35: =IF(ISBLANK(H35),"",I35-H35) | N35: =IF(ISBLANK(M35),"",SUMIF($AN$5:$AN$1004,L35,$AO$5:$AO$1004)) | O35: =IF(ISBLANK(M35),"",N35-M35) | S35: =IF(ISBLANK(R35),"",SUMIF($AN$5:$AN$1004,Q35,$AO$5:$AO$1004)) | T35: =IF(ISBLANK(R35),"",S35-R35) | X35: =IF(ISBLANK(W35),"",SUMIF($AN$5:$AN$1004,V35,$AO$5:$AO$1004)) | Y35: =IF(ISBLANK(W35),"",X35-W35) | AC35: =IF(ISBLANK(AB35),"",SUMIF($AN$5:$AN$1004,AA35,$AO$5:$AO$1004)) | AD35: =IF(ISBLANK(AB35),"",AC35-AB35) | AH35: =IF(ISBLANK(AG35),"",SUMIF($AN$5:$AN$1004,AF35,$AO$5:$AO$1004)) | AI35: =IF(ISBLANK(AG35),"",AH35-AG35)
D36: =IF(ISBLANK(C36),"",SUMIF($AN$5:$AN$1004,B36,$AO$5:$AO$1004)) | E36: =IF(ISBLANK(C36),"",D36-C36) | I36: =IF(ISBLANK(H36),"",SUMIF($AN$5:$AN$1004,G36,$AO$5:$AO$1004)) | J36: =IF(ISBLANK(H36),"",I36-H36) | N36: =IF(ISBLANK(M36),"",SUMIF($AN$5:$AN$1004,L36,$AO$5:$AO$1004)) | O36: =IF(ISBLANK(M36),"",N36-M36) | S36: =IF(ISBLANK(R36),"",SUMIF($AN$5:$AN$1004,Q36,$AO$5:$AO$1004)) | T36: =IF(ISBLANK(R36),"",S36-R36) | X36: =IF(ISBLANK(W36),"",SUMIF($AN$5:$AN$1004,V36,$AO$5:$AO$1004)) | Y36: =IF(ISBLANK(W36),"",X36-W36) | AC36: =IF(ISBLANK(AB36),"",SUMIF($AN$5:$AN$1004,AA36,$AO$5:$AO$1004)) | AD36: =IF(ISBLANK(AB36),"",AC36-AB36) | AH36: =IF(ISBLANK(AG36),"",SUMIF($AN$5:$AN$1004,AF36,$AO$5:$AO$1004)) | AI36: =IF(ISBLANK(AG36),"",AH36-AG36)
D37: =IF(ISBLANK(C37),"",SUMIF($AN$5:$AN$1004,B37,$AO$5:$AO$1004)) | E37: =IF(ISBLANK(C37),"",D37-C37) | I37: =IF(ISBLANK(H37),"",SUMIF($AN$5:$AN$1004,G37,$AO$5:$AO$1004)) | J37: =IF(ISBLANK(H37),"",I37-H37) | N37: =IF(ISBLANK(M37),"",SUMIF($AN$5:$AN$1004,L37,$AO$5:$AO$1004)) | O37: =IF(ISBLANK(M37),"",N37-M37) | S37: =IF(ISBLANK(R37),"",SUMIF($AN$5:$AN$1004,Q37,$AO$5:$AO$1004)) | T37: =IF(ISBLANK(R37),"",S37-R37) | X37: =IF(ISBLANK(W37),"",SUMIF($AN$5:$AN$1004,V37,$AO$5:$AO$1004)) | Y37: =IF(ISBLANK(W37),"",X37-W37) | AC37: =IF(ISBLANK(AB37),"",SUMIF($AN$5:$AN$1004,AA37,$AO$5:$AO$1004)) | AD37: =IF(ISBLANK(AB37),"",AC37-AB37) | AH37: =IF(ISBLANK(AG37),"",SUMIF($AN$5:$AN$1004,AF37,$AO$5:$AO$1004)) | AI37: =IF(ISBLANK(AG37),"",AH37-AG37)
D38: =IF(ISBLANK(C38),"",SUMIF($AN$5:$AN$1004,B38,$AO$5:$AO$1004)) | E38: =IF(ISBLANK(C38),"",D38-C38) | I38: =IF(ISBLANK(H38),"",SUMIF($AN$5:$AN$1004,G38,$AO$5:$AO$1004)) | J38: =IF(ISBLANK(H38),"",I38-H38) | N38: =IF(ISBLANK(M38),"",SUMIF($AN$5:$AN$1004,L38,$AO$5:$AO$1004)) | O38: =IF(ISBLANK(M38),"",N38-M38) | S38: =IF(ISBLANK(R38),"",SUMIF($AN$5:$AN$1004,Q38,$AO$5:$AO$1004)) | T38: =IF(ISBLANK(R38),"",S38-R38) | X38: =IF(ISBLANK(W38),"",SUMIF($AN$5:$AN$1004,V38,$AO$5:$AO$1004)) | Y38: =IF(ISBLANK(W38),"",X38-W38) | AC38: =IF(ISBLANK(AB38),"",SUMIF($AN$5:$AN$1004,AA38,$AO$5:$AO$1004)) | AD38: =IF(ISBLANK(AB38),"",AC38-AB38) | AH38: =IF(ISBLANK(AG38),"",SUMIF($AN$5:$AN$1004,AF38,$AO$5:$AO$1004)) | AI38: =IF(ISBLANK(AG38),"",AH38-AG38)
D39: =IF(ISBLANK(C39),"",SUMIF($AN$5:$AN$1004,B39,$AO$5:$AO$1004)) | E39: =IF(ISBLANK(C39),"",D39-C39) | I39: =IF(ISBLANK(H39),"",SUMIF($AN$5:$AN$1004,G39,$AO$5:$AO$1004)) | J39: =IF(ISBLANK(H39),"",I39-H39) | N39: =IF(ISBLANK(M39),"",SUMIF($AN$5:$AN$1004,L39,$AO$5:$AO$1004)) | O39: =IF(ISBLANK(M39),"",N39-M39) | S39: =IF(ISBLANK(R39),"",SUMIF($AN$5:$AN$1004,Q39,$AO$5:$AO$1004)) | T39: =IF(ISBLANK(R39),"",S39-R39) | X39: =IF(ISBLANK(W39),"",SUMIF($AN$5:$AN$1004,V39,$AO$5:$AO$1004)) | Y39: =IF(ISBLANK(W39),"",X39-W39) | AC39: =IF(ISBLANK(AB39),"",SUMIF($AN$5:$AN$1004,AA39,$AO$5:$AO$1004)) | AD39: =IF(ISBLANK(AB39),"",AC39-AB39) | AH39: =IF(ISBLANK(AG39),"",SUMIF($AN$5:$AN$1004,AF39,$AO$5:$AO$1004)) | AI39: =IF(ISBLANK(AG39),"",AH39-AG39)
D40: =IF(ISBLANK(C40),"",SUMIF($AN$5:$AN$1004,B40,$AO$5:$AO$1004)) | E40: =IF(ISBLANK(C40),"",D40-C40) | I40: =IF(ISBLANK(H40),"",SUMIF($AN$5:$AN$1004,G40,$AO$5:$AO$1004)) | J40: =IF(ISBLANK(H40),"",I40-H40) | N40: =IF(ISBLANK(M40),"",SUMIF($AN$5:$AN$1004,L40,$AO$5:$AO$1004)) | O40: =IF(ISBLANK(M40),"",N40-M40) | S40: =IF(ISBLANK(R40),"",SUMIF($AN$5:$AN$1004,Q40,$AO$5:$AO$1004)) | T40: =IF(ISBLANK(R40),"",S40-R40) | X40: =IF(ISBLANK(W40),"",SUMIF($AN$5:$AN$1004,V40,$AO$5:$AO$1004)) | Y40: =IF(ISBLANK(W40),"",X40-W40) | AC40: =IF(ISBLANK(AB40),"",SUMIF($AN$5:$AN$1004,AA40,$AO$5:$AO$1004)) | AD40: =IF(ISBLANK(AB40),"",AC40-AB40) | AH40: =IF(ISBLANK(AG40),"",SUMIF($AN$5:$AN$1004,AF40,$AO$5:$AO$1004)) | AI40: =IF(ISBLANK(AG40),"",AH40-AG40)
D41: =IF(ISBLANK(C41),"",SUMIF($AN$5:$AN$1004,B41,$AO$5:$AO$1004)) | E41: =IF(ISBLANK(C41),"",D41-C41) | I41: =IF(ISBLANK(H41),"",SUMIF($AN$5:$AN$1004,G41,$AO$5:$AO$1004)) | J41: =IF(ISBLANK(H41),"",I41-H41) | N41: =IF(ISBLANK(M41),"",SUMIF($AN$5:$AN$1004,L41,$AO$5:$AO$1004)) | O41: =IF(ISBLANK(M41),"",N41-M41) | S41: =IF(ISBLANK(R41),"",SUMIF($AN$5:$AN$1004,Q41,$AO$5:$AO$1004)) | T41: =IF(ISBLANK(R41),"",S41-R41) | X41: =IF(ISBLANK(W41),"",SUMIF($AN$5:$AN$1004,V41,$AO$5:$AO$1004)) | Y41: =IF(ISBLANK(W41),"",X41-W41) | AC41: =IF(ISBLANK(AB41),"",SUMIF($AN$5:$AN$1004,AA41,$AO$5:$AO$1004)) | AD41: =IF(ISBLANK(AB41),"",AC41-AB41) | AH41: =IF(ISBLANK(AG41),"",SUMIF($AN$5:$AN$1004,AF41,$AO$5:$AO$1004)) | AI41: =IF(ISBLANK(AG41),"",AH41-AG41)
... D129: =IF(ISBLANK(C129),"",SUMIF($AN$5:$AN$1004,B129,$AO$5:$AO$1004)) | E129: =IF(ISBLANK(C129),"",D129-C129) | I129: =IF(ISBLANK(H129),"",SUMIF($AN$5:$AN$1004,G129,$AO$5:$AO$1004)) | J129: =IF(ISBLANK(H129),"",I129-H129) | N129: =IF(ISBLANK(M129),"",SUMIF($AN$5:$AN$1004,L129,$AO$5:$AO$1004)) | O129: =IF(ISBLANK(M129),"",N129-M129) | S129: =IF(ISBLANK(R129),"",SUMIF($AN$5:$AN$1004,Q129,$AO$5:$AO$1004)) | T129: =IF(ISBLANK(R129),"",S129-R129) | X129: =IF(ISBLANK(W129),"",SUMIF($AN$5:$AN$1004,V129,$AO$5:$AO$1004)) | Y129: =IF(ISBLANK(W129),"",X129-W129) | AC129: =IF(ISBLANK(AB129),"",SUMIF($AN$5:$AN$1004,AA129,$AO$5:$AO$1004)) | AD129: =IF(ISBLANK(AB129),"",AC129-AB129) | AH129: =IF(ISBLANK(AG129),"",SUMIF($AN$5:$AN$1004,AF129,$AO$5:$AO$1004)) | AI129: =IF(ISBLANK(AG129),"",AH129-AG129)
B130: Total | C130: =SUM(C30:C129) -> 0 | D130: =SUM(D30:D129) -> 0 | E130: =SUM(E30:E129) -> 0 | G130: Total | H130: =SUM(H30:H129) -> 0 | I130: =SUM(I30:I129) -> 0 | J130: =IF(ISBLANK(H130),"",I130-H130) -> 0 | L130: Total | M130: =SUM(M30:M129) -> 0 | N130: =SUM(N30:N129) -> 0 | O130: =IF(ISBLANK(M130),"",N130-M130) -> 0 | Q130: Total | R130: =SUM(R30:R129) -> 0 | S130: =SUM(S30:S129) -> 0 | T130: =IF(ISBLANK(R130),"",S130-R130) -> 0 | V130: Total | W130: =SUM(W30:W129) -> 0 | X130: =SUM(X30:X129) -> 0 | Y130: =SUM(Y30:Y129) -> 0 | AA130: Total | AB130: =SUM(AB30:AB129) -> 0 | AC130: =SUM(AC30:AC129) -> 0 | AD130: =SUM(AD30:AD129) -> 0 | AF130: Total | AG130: =SUM(AG30:AG129) -> 0 | AH130: =SUM(AH30:AH129) -> 0 | AI130: =SUM(AI30:AI129) -> 0

Sheet 202507
B2: Season | C2: Summer
B4: =SUMIFS(D17:D90, C17:C90, "<=14") -> 922.03 | C4: Expenses: 1st to 15th
B5: =SUMIFS(D17:D90, C17:C90, ">=15") -> 4247.19 | C5: Expenses: 15th to 30th
B7: Description | C7: Expected Due Date | D7: Amount | G7: Description | H7: Expected Due Date | I7: Amount | J7: Adjusted Amount | K7: Adjusted Due Date
B8: CVS Income | C8: 15 | D8: 3500.73 | F8: =NOT(ISBLANK(C8)) -> TRUE | G8: {=_xlws.FILTER($B$8:$D$90, $F$8:$F$90)} -> #NAME? | J8: =IF(ISERROR(MATCH(G8, $B$8:$B$12, 0)), -1*I8,I8) -> 0 | K8: =DATE(2025, Cashflow!$D$2, $H8) -> 45930
B9: CVS Income | C9: 30 | D9: 3500.73 | F9: =NOT(ISBLANK(C9)) -> TRUE | J9: =IF(ISERROR(MATCH(G9, $B$8:$B$12, 0)), -1*I9,I9) -> 0 | K9: =DATE(2025, Cashflow!$D$2, $H9) -> 45930
B10: Apt 2 Rent | C10: 25 | F10: =NOT(ISBLANK(C10)) -> TRUE | J10: =IF(ISERROR(MATCH(G10, $B$8:$B$12, 0)), -1*I10,I10) -> 0 | K10: =DATE(2025, Cashflow!$D$2, $H10) -> 45930
B11: Apt 3 Rent | C11: 31 | F11: =NOT(ISBLANK(C11)) -> TRUE | J11: =IF(ISERROR(MATCH(G11, $B$8:$B$12, 0)), -1*I11,I11) -> 0 | K11: =DATE(2025, Cashflow!$D$2, $H11) -> 45930
B12: Uber Income | D12: 0 | F12: =NOT(ISBLANK(C12)) -> FALSE | J12: =IF(ISERROR(MATCH(G12, $B$8:$B$12, 0)), -1*I12,I12) -> 0 | K12: =DATE(2025, Cashflow!$D$2, $H12) -> 45930
F13: =NOT(ISBLANK(C13)) -> FALSE | J13: =IF(ISERROR(MATCH(G13, $B$8:$B$12, 0)), -1*I13,I13) -> 0 | K13: =DATE(2025, Cashflow!$D$2, $H13) -> 45930
B14: Total Income | D14: =SUM(D8:D12) -> 7001.46 | F14: =NOT(ISBLANK(C14)) -> FALSE | J14: =IF(ISERROR(MATCH(G14, $B$8:$B$12, 0)), -1*I14,I14) -> 0 | K14: =DATE(2025, Cashflow!$D$2, $H14) -> 45930
F15: =NOT(ISBLANK(C15)) -> FALSE | J15: =IF(ISERROR(MATCH(G15, $B$8:$B$12, 0)), -1*I15,I15) -> 0 | K15: =DATE(2025, Cashflow!$D$2, $H15) -> 45930
B16: Credit Cards | F16: =NOT(ISBLANK(C16)) -> FALSE | J16: =IF(ISERROR(MATCH(G16, $B$8:$B$12, 0)), -1*I16,I16) -> 0 | K16: =DATE(2025, Cashflow!$D$2, $H16) -> 45930
A17: FALSE | B17: BOA Customized Rewards | C17: 9 | D17: 35 | F17: =NOT(ISBLANK(C17)) -> TRUE | J17: =IF(ISERROR(MATCH(G17, $B$8:$B$12, 0)), -1*I17,I17) -> 0 | K17: =DATE(2025, Cashflow!$D$2, $H17) -> 45930
A18: FALSE | B18: BOA Unlimited Rewards | C18: 4 | D18: 25 | F18: =NOT(ISBLANK(C18)) -> TRUE | J18: =IF(ISERROR(MATCH(G18, $B$8:$B$12, 0)), -1*I18,I18) -> 0 | K18: =DATE(2025, Cashflow!$D$2, $H18) -> 45930
A19: FALSE | B19: CHASE Freedom | C19: 15 | D19: 440 | F19: =NOT(ISBLANK(C19)) -> TRUE | J19: =IF(ISERROR(MATCH(G19, $B$8:$B$12, 0)), -1*I19,I19) -> 0 | K19: =DATE(2025, Cashflow!$D$2, $H19) -> 45930
A20: FALSE | B20: CHASE Brittany | C20: 17 | D20: 125 | F20: =NOT(ISBLANK(C20)) -> TRUE | J20: =IF(ISERROR(MATCH(G20, $B$8:$B$12, 0)), -1*I20,I20) -> 0 | K20: =DATE(2025, Cashflow!$D$2, $H20) -> 45930
A21: FALSE | B21: CITI Diamond Preferred | C21: 15 | D21: 120 | F21: =NOT(ISBLANK(C21)) -> TRUE | J21: =IF(ISERROR(MATCH(G21, $B$8:$B$12, 0)), -1*I21,I21) -> 0 | K21: =DATE(2025, Cashflow!$D$2, $H21) -> 45930
A22: FALSE | B22: CITIZENS Clear Value | C22: 15 | D22: 70 | F22: =NOT(ISBLANK(C22)) -> TRUE | J22: =IF(ISERROR(MATCH(G22, $B$8:$B$12, 0)), -1*I22,I22) -> 0 | K22: =DATE(2025, Cashflow!$D$2, $H22) -> 45930
F23: =NOT(ISBLANK(C23)) -> FALSE | J23: =IF(ISERROR(MATCH(G23, $B$8:$B$12, 0)), -1*I23,I23) -> 0 | K23: =DATE(2025, Cashflow!$D$2, $H23) -> 45930
B24: Loan Payments | F24: =NOT(ISBLANK(C24)) -> FALSE | J24: =IF(ISERROR(MATCH(G24, $B$8:$B$12, 0)), -1*I24,I24) -> 0 | K24: =DATE(2025, Cashflow!$D$2, $H24) -> 45930
A25: FALSE | B25: CITIZENS Mortgage | C25: 1 | D25: 0 | F25: =NOT(ISBLANK(C25)) -> TRUE | J25: =IF(ISERROR(MATCH(G25, $B$8:$B$12, 0)), -1*I25,I25) -> 0 | K25: =DATE(2025, Cashflow!$D$2, $H25) -> 45930
A26: FALSE | B26: UPSTART Debt Consolidation | C26: 15 | D26: 181.13 | F26: =NOT(ISBLANK(C26)) -> TRUE | J26: =IF(ISERROR(MATCH(G26, $B$8:$B$12, 0)), -1*I26,I26) -> 0 | K26: =DATE(2025, Cashflow!$D$2, $H26) -> 45930
A27: FALSE | B27: LIGHTSTREAM Renovation | C27: 15 | D27: 525.13 | F27: =NOT(ISBLANK(C27)) -> TRUE | J27: =IF(ISERROR(MATCH(G27, $B$8:$B$12, 0)), -1*I27,I27) -> 0 | K27: =DATE(2025, Cashflow!$D$2, $H27) -> 45930
A28: FALSE | B28: AFFIRM Photography | C28: 21 | D28: 235.17 | F28: =NOT(ISBLANK(C28)) -> TRUE | J28: =IF(ISERROR(MATCH(G28, $B$8:$B$12, 0)), -1*I28,I28) -> 0 | K28: =DATE(2025, Cashflow!$D$2, $H28) -> 45930
A29: FALSE | B29: AQUA FINANCE Roofing Replacement | D29: 268.44 | F29: =NOT(ISBLANK(C29)) -> FALSE | J29: =IF(ISERROR(MATCH(G29, $B$8:$B$12, 0)), -1*I29,I29) -> 0 | K29: =DATE(2025, Cashflow!$D$2, $H29) -> 45930
A30: FALSE | B30: CONNEX Auto Loan | C30: 17 | D30: 878.54 | F30: =NOT(ISBLANK(C30)) -> TRUE | J30: =IF(ISERROR(MATCH(G30, $B$8:$B$12, 0)), -1*I30,I30) -> 0 | K30: =DATE(2025, Cashflow!$D$2, $H30) -> 45930
A31: FALSE | B31: NELNET Student Loans | F31: =NOT(ISBLANK(C31)) -> FALSE | J31: =IF(ISERROR(MATCH(G31, $B$8:$B$12, 0)), -1*I31,I31) -> 0 | K31: =DATE(2025, Cashflow!$D$2, $H31) -> 45930
F32: =NOT(ISBLANK(C32)) -> FALSE | J32: =IF(ISERROR(MATCH(G32, $B$8:$B$12, 0)), -1*I32,I32) -> 0 | K32: =DATE(2025, Cashflow!$D$2, $H32) -> 45930
B33: Propery Expenses | F33: =NOT(ISBLANK(C33)) -> FALSE | J33: =IF(ISERROR(MATCH(G33, $B$8:$B$12, 0)), -1*I33,I33) -> 0 | K33: =DATE(2025, Cashflow!$D$2, $H33) -> 45930
A34: FALSE | B34: Owner Contribution to Mortgage | C34: 1 | D34: 153.54 | F34: =NOT(ISBLANK(C34)) -> TRUE | J34: =IF(ISERROR(MATCH(G34, $B$8:$B$12, 0)), -1*I34,I34) -> 0 | K34: =DATE(2025, Cashflow!$D$2, $H34) -> 45930
A35: FALSE | B35: Landlord Electricity | C35: 5 | D35: 40 | F35: =NOT(ISBLANK(C35)) -> TRUE | J35: =IF(ISERROR(MATCH(G35, $B$8:$B$12, 0)), -1*I35,I35) -> 0 | K35: =DATE(2025, Cashflow!$D$2, $H35) -> 45930
A36: FALSE | B36: Water/Sewer (Monthly) | D36: 130 | F36: =NOT(ISBLANK(C36)) -> FALSE | J36: =IF(ISERROR(MATCH(G36, $B$8:$B$12, 0)), -1*I36,I36) -> 0 | K36: =DATE(2025, Cashflow!$D$2, $H36) -> 45930
A37: FALSE | B37: Maintenance (Lawn) | D37: =IF($C$2="Summer", 80, 0) -> 80 | F37: =NOT(ISBLANK(C37)) -> FALSE | J37: =IF(ISERROR(MATCH(G37, $B$8:$B$12, 0)), -1*I37,I37) -> 0 | K37: =DATE(2025, Cashflow!$D$2, $H37) -> 45930
A38: FALSE | B38: Maintenance (Snow Removal) | D38: =IF($C$2="Winter", 110, 0) -> 0 | F38: =NOT(ISBLANK(C38)) -> FALSE | J38: =IF(ISERROR(MATCH(G38, $B$8:$B$12, 0)), -1*I38,I38) -> 0 | K38: =DATE(2025, Cashflow!$D$2, $H38) -> 45930
A39: FALSE | B39: Blink Security | C39: 5 | D39: 10.64 | F39: =NOT(ISBLANK(C39)) -> TRUE | J39: =IF(ISERROR(MATCH(G39, $B$8:$B$12, 0)), -1*I39,I39) -> 0 | K39: =DATE(2025, Cashflow!$D$2, $H39) -> 45930
A40: FALSE | B40: Avail Portal | C40: 16 | D40: 18 | F40: =NOT(ISBLANK(C40)) -> TRUE | J40: =IF(ISERROR(MATCH(G40, $B$8:$B$12, 0)), -1*I40,I40) -> 0 | K40: =DATE(2025, Cashflow!$D$2, $H40) -> 45930
F41: =NOT(ISBLANK(C41)) -> FALSE | J41: =IF(ISERROR(MATCH(G41, $B$8:$B$12, 0)), -1*I41,I41) -> 0 | K41: =DATE(2025, Cashflow!$D$2, $H41) -> 45930
B42: Bills | F42: =NOT(ISBLANK(C42)) -> FALSE | J42: =IF(ISERROR(MATCH(G42, $B$8:$B$12, 0)), -1*I42,I42) -> 0 | K42: =DATE(2025, Cashflow!$D$2, $H42) -> 45930
A43: FALSE | B43: Auto Insurance | C43: 5 | D43: 95 | F43: =NOT(ISBLANK(C43)) -> TRUE | J43: =IF(ISERROR(MATCH(G43, $B$8:$B$12, 0)), -1*I43,I43) -> 0 | K43: =DATE(2025, Cashflow!$D$2, $H43) -> 45930
A44: FALSE | B44: Auto Taxes (Monthly) | C44: 1 | D44: 0 | F44: =NOT(ISBLANK(C44)) -> TRUE | J44: =IF(ISERROR(MATCH(G44, $B$8:$B$12, 0)), -1*I44,I44) -> 0 | K44: =DATE(2025, Cashflow!$D$2, $H44) -> 45930
A45: FALSE | B45: Heating/Natural Gas | C45: 23 | D45: 171 | F45: =NOT(ISBLANK(C45)) -> TRUE | J45: =IF(ISERROR(MATCH(G45, $B$8:$B$12, 0)), -1*I45,I45) -> 0 | K45: =DATE(2025, Cashflow!$D$2, $H45) -> 45930
A46: FALSE | B46: Electricity | C46: 22 | D46: 150 | F46: =NOT(ISBLANK(C46)) -> TRUE | J46: =IF(ISERROR(MATCH(G46, $B$8:$B$12, 0)), -1*I46,I46) -> 0 | K46: =DATE(2025, Cashflow!$D$2, $H46) -> 45930
A47: FALSE | B47: Internet | C47: 28 | D47: 74.95 | F47: =NOT(ISBLANK(C47)) -> TRUE | J47: =IF(ISERROR(MATCH(G47, $B$8:$B$12, 0)), -1*I47,I47) -> 0 | K47: =DATE(2025, Cashflow!$D$2, $H47) -> 45930
A48: FALSE | B48: Life Insurance | C48: 16 | D48: 82.37 | F48: =NOT(ISBLANK(C48)) -> TRUE | J48: =IF(ISERROR(MATCH(G48, $B$8:$B$12, 0)), -1*I48,I48) -> 0 | K48: =DATE(2025, Cashflow!$D$2, $H48) -> 45930
F49: =NOT(ISBLANK(C49)) -> FALSE | J49: =IF(ISERROR(MATCH(G49, $B$8:$B$12, 0)), -1*I49,I49) -> 0 | K49: =DATE(2025, Cashflow!$D$2, $H49) -> 45930
B50: Expenses (Needs) | F50: =NOT(ISBLANK(C50)) -> FALSE | J50: =IF(ISERROR(MATCH(G50, $B$8:$B$12, 0)), -1*I50,I50) -> 0 | K50: =DATE(2025, Cashflow!$D$2, $H50) -> 45930
A51: FALSE | B51: Groceries + Toiletries | C51: 4 | D51: 250 | F51: =NOT(ISBLANK(C51)) -> TRUE | J51: =IF(ISERROR(MATCH(G51, $B$8:$B$12, 0)), -1*I51,I51) -> 0 | K51: =DATE(2025, Cashflow!$D$2, $H51) -> 45930
A52: FALSE | B52: Groceries + Toiletries | C52: 11 | D52: 250 | F52: =NOT(ISBLANK(C52)) -> TRUE | J52: =IF(ISERROR(MATCH(G52, $B$8:$B$12, 0)), -1*I52,I52) -> 0 | K52: =DATE(2025, Cashflow!$D$2, $H52) -> 45930
A53: FALSE | B53: Groceries + Toiletries | C53: 18 | D53: 250 | F53: =NOT(ISBLANK(C53)) -> TRUE | J53: =IF(ISERROR(MATCH(G53, $B$8:$B$12, 0)), -1*I53,I53) -> 0 | K53: =DATE(2025, Cashflow!$D$2, $H53) -> 45930
A54: FALSE | B54: Groceries + Toiletries | C54: 24 | D54: 250 | F54: =NOT(ISBLANK(C54)) -> TRUE | J54: =IF(ISERROR(MATCH(G54, $B$8:$B$12, 0)), -1*I54,I54) -> 0 | K54: =DATE(2025, Cashflow!$D$2, $H54) -> 45930
A55: FALSE | B55: Phone (Nykosi) | C55: 16 | D55: 30 | F55: =NOT(ISBLANK(C55)) -> TRUE | J55: =IF(ISERROR(MATCH(G55, $B$8:$B$12, 0)), -1*I55,I55) -> 0 | K55: =DATE(2025, Cashflow!$D$2, $H55) -> 45930
A56: FALSE | B56: Phone (Brittany) | C56: 16 | D56: 50 | F56: =NOT(ISBLANK(C56)) -> TRUE | J56: =IF(ISERROR(MATCH(G56, $B$8:$B$12, 0)), -1*I56,I56) -> 0 | K56: =DATE(2025, Cashflow!$D$2, $H56) -> 45930
F57: =NOT(ISBLANK(C57)) -> FALSE | J57: =IF(ISERROR(MATCH(G57, $B$8:$B$12, 0)), -1*I57,I57) -> 0 | K57: =DATE(2025, Cashflow!$D$2, $H57) -> 45930
B58: Expenses (Wants) | F58: =NOT(ISBLANK(C58)) -> FALSE | J58: =IF(ISERROR(MATCH(G58, $B$8:$B$12, 0)), -1*I58,I58) -> 0 | K58: =DATE(2025, Cashflow!$D$2, $H58) -> 45930
A59: FALSE | B59: Gym Membership (Nykosi) | C59: 24 | D59: 22.23 | F59: =NOT(ISBLANK(C59)) -> TRUE | J59: =IF(ISERROR(MATCH(G59, $B$8:$B$12, 0)), -1*I59,I59) -> 0 | K59: =DATE(2025, Cashflow!$D$2, $H59) -> 45930
A60: FALSE | B60: Gym Membership (Brittany) | C60: 6 | D60: 32.87 | F60: =NOT(ISBLANK(C60)) -> TRUE | J60: =IF(ISERROR(MATCH(G60, $B$8:$B$12, 0)), -1*I60,I60) -> 0 | K60: =DATE(2025, Cashflow!$D$2, $H60) -> 45930
A61: FALSE | B61: Gym Trainer (Brittany) | C61: Bi-Weekly | D61: 210.58 | F61: =NOT(ISBLANK(C61)) -> TRUE | J61: =IF(ISERROR(MATCH(G61, $B$8:$B$12, 0)), -1*I61,I61) -> 0 | K61: =DATE(2025, Cashflow!$D$2, $H61) -> 45930
A62: FALSE | B62: Amazon Prime | C62: 14 | D62: 14.99 | F62: =NOT(ISBLANK(C62)) -> TRUE | J62: =IF(ISERROR(MATCH(G62, $B$8:$B$12, 0)), -1*I62,I62) -> 0 | K62: =DATE(2025, Cashflow!$D$2, $H62) -> 45930
A63: FALSE | B63: Drawboard PDF | C63: 29 | D63: 5.99 | F63: =NOT(ISBLANK(C63)) -> TRUE | J63: =IF(ISERROR(MATCH(G63, $B$8:$B$12, 0)), -1*I63,I63) -> 0 | K63: =DATE(2025, Cashflow!$D$2, $H63) -> 45930
A64: FALSE | B64: Mailchimp | C64: 25 | D64: 14.04 | F64: =NOT(ISBLANK(C64)) -> TRUE | J64: =IF(ISERROR(MATCH(G64, $B$8:$B$12, 0)), -1*I64,I64) -> 0 | K64: =DATE(2025, Cashflow!$D$2, $H64) -> 45930
A65: FALSE | B65: Microsoft 365 | C65: 17 | D65: 14.14 | F65: =NOT(ISBLANK(C65)) -> TRUE | J65: =IF(ISERROR(MATCH(G65, $B$8:$B$12, 0)), -1*I65,I65) -> 0 | K65: =DATE(2025, Cashflow!$D$2, $H65) -> 45930
A66: FALSE | B66: Netflix | C66: 23 | D66: 19.3 | F66: =NOT(ISBLANK(C66)) -> TRUE | J66: =IF(ISERROR(MATCH(G66, $B$8:$B$12, 0)), -1*I66,I66) -> 0 | K66: =DATE(2025, Cashflow!$D$2, $H66) -> 45930
A67: FALSE | B67: YNAB | C67: 9 | D67: 14.99 | F67: =NOT(ISBLANK(C67)) -> TRUE | J67: =IF(ISERROR(MATCH(G67, $B$8:$B$12, 0)), -1*I67,I67) -> 0 | K67: =DATE(2025, Cashflow!$D$2, $H67) -> 45930
A68: FALSE | B68: OpenAI | C68: 16 | D68: 20.2 | F68: =NOT(ISBLANK(C68)) -> TRUE | J68: =IF(ISERROR(MATCH(G68, $B$8:$B$12, 0)), -1*I68,I68) -> 0 | K68: =DATE(2025, Cashflow!$D$2, $H68) -> 45930
A69: FALSE | B69: SAH Stipend (1/2) | C69: 15 | D69: 250 | F69: =NOT(ISBLANK(C69)) -> TRUE | J69: =IF(ISERROR(MATCH(G69, $B$8:$B$12, 0)), -1*I69,I69) -> 0 | K69: =DATE(2025, Cashflow!$D$2, $H69) -> 45930
A70: FALSE | B70: SAH Stipend (2/2) | C70: 30 | D70: 250 | F70: =NOT(ISBLANK(C70)) -> TRUE | J70: =IF(ISERROR(MATCH(G70, $B$8:$B$12, 0)), -1*I70,I70) -> 0 | K70: =DATE(2025, Cashflow!$D$2, $H70) -> 45930
F71: =NOT(ISBLANK(C71)) -> FALSE | J71: =IF(ISERROR(MATCH(G71, $B$8:$B$12, 0)), -1*I71,I71) -> 0 | K71: =DATE(2025, Cashflow!$D$2, $H71) -> 45930
B72: One-Time Expenses | F72: =NOT(ISBLANK(C72)) -> FALSE | J72: =IF(ISERROR(MATCH(G72, $B$8:$B$12, 0)), -1*I72,I72) -> 0 | K72: =DATE(2025, Cashflow!$D$2, $H72) -> 45930
A73: FALSE | B73: Gym Membership (Nykosi) | C73: 24 | D73: 0 | F73: =NOT(ISBLANK(C73)) -> TRUE | J73: =IF(ISERROR(MATCH(G73, $B$8:$B$12, 0)), -1*I73,I73) -> 0 | K73: =DATE(2025, Cashflow!$D$2, $H73) -> 45930
A74: FALSE | B74: Gym Membership (Brittany) | C74: 6 | D74: 0 | F74: =NOT(ISBLANK(C74)) -> TRUE | J74: =IF(ISERROR(MATCH(G74, $B$8:$B$12, 0)), -1*I74,I74) -> 0 | K74: =DATE(2025, Cashflow!$D$2, $H74) -> 45930
F75: =NOT(ISBLANK(C75)) -> FALSE | J75: =IF(ISERROR(MATCH(G75, $B$8:$B$12, 0)), -1*I75,I75) -> 0 | K75: =DATE(2025, Cashflow!$D$2, $H75) -> 45930
B76: Cash After Expenses | D76: =$D$14-SUM($D$17:$D$75) -> 1143.22 | F76: =NOT(ISBLANK(C76)) -> FALSE | J76: =IF(ISERROR(MATCH(G76, $B$8:$B$12, 0)), -1*I76,I76) -> 0 | K76: =DATE(2025, Cashflow!$D$2, $H76) -> 45930
F77: =NOT(ISBLANK(C77)) -> FALSE | J77: =IF(ISERROR(MATCH(G77, $B$8:$B$12, 0)), -1*I77,I77) -> 0 | K77: =DATE(2025, Cashflow!$D$2, $H77) -> 45930
F78: =NOT(ISBLANK(C78)) -> FALSE | J78: =IF(ISERROR(MATCH(G78, $B$8:$B$12, 0)), -1*I78,I78) -> 0 | K78: =DATE(2025, Cashflow!$D$2, $H78) -> 45930
B79: Savings | F79: =NOT(ISBLANK(C79)) -> FALSE | J79: =IF(ISERROR(MATCH(G79, $B$8:$B$12, 0)), -1*I79,I79) -> 0 | K79: =DATE(2025, Cashflow!$D$2, $H79) -> 45930
B80: Education 529s | F80: =NOT(ISBLANK(C80)) -> FALSE | J80: =IF(ISERROR(MATCH(G80, $B$8:$B$12, 0)), -1*I80,I80) -> 0 | K80: =DATE(2025, Cashflow!$D$2, $H80) -> 45930
B81: Emergency Fund | F81: =NOT(ISBLANK(C81)) -> FALSE | J81: =IF(ISERROR(MATCH(G81, $B$8:$B$12, 0)), -1*I81,I81) -> 0 | K81: =DATE(2025, Cashflow!$D$2, $H81) -> 45930
F82: =NOT(ISBLANK(C82)) -> FALSE | J82: =IF(ISERROR(MATCH(G82, $B$8:$B$12, 0)), -1*I82,I82) -> 0 | K82: =DATE(2025, Cashflow!$D$2, $H82) -> 45930
F83: =NOT(ISBLANK(C83)) -> FALSE | J83: =IF(ISERROR(MATCH(G83, $B$8:$B$12, 0)), -1*I83,I83) -> 0 | K83: =DATE(2025, Cashflow!$D$2, $H83) -> 45930
F84: =NOT(ISBLANK(C84)) -> FALSE | J84: =IF(ISERROR(MATCH(G84, $B$8:$B$12, 0)), -1*I84,I84) -> 0 | K84: =DATE(2025, Cashflow!$D$2, $H84) -> 45930
F85: =NOT(ISBLANK(C85)) -> FALSE | J85: =IF(ISERROR(MATCH(G85, $B$8:$B$12, 0)), -1*I85,I85) -> 0 | K85: =DATE(2025, Cashflow!$D$2, $H85) -> 45930
F86: =NOT(ISBLANK(C86)) -> FALSE | J86: =IF(ISERROR(MATCH(G86, $B$8:$B$12, 0)), -1*I86,I86) -> 0 | K86: =DATE(2025, Cashflow!$D$2, $H86) -> 45930
F87: =NOT(ISBLANK(C87)) -> FALSE | J87: =IF(ISERROR(MATCH(G87, $B$8:$B$12, 0)), -1*I87,I87) -> 0 | K87: =DATE(2025, Cashflow!$D$2, $H87) -> 45930
F88: =NOT(ISBLANK(C88)) -> FALSE | J88: =IF(ISERROR(MATCH(G88, $B$8:$B$12, 0)), -1*I88,I88) -> 0 | K88: =DATE(2025, Cashflow!$D$2, $H88) -> 45930
F89: =NOT(ISBLANK(C89)) -> FALSE | J89: =IF(ISERROR(MATCH(G89, $B$8:$B$12, 0)), -1*I89,I89) -> 0 | K89: =DATE(2025, Cashflow!$D$2, $H89) -> 45930
F90: =NOT(ISBLANK(C90)) -> FALSE | J90: =IF(ISERROR(MATCH(G90, $B$8:$B$12, 0)), -1*I90,I90) -> 0 | K90: =DATE(2025, Cashflow!$D$2, $H90) -> 45930

Sheet 202508
B2: Season | C2: Summer
B4: =SUMIFS(D17:D94, C17:C94, "<=14") -> 1310.34 | C4: Expenses: 1st to 15th
B5: =SUMIFS(D17:D94, C17:C94, ">=15") -> 4864.44 | C5: Expenses: 15th to 30th
P6: =SUM(P7:P50) -> -350.71
B7: Description | C7: Expected Due Date | D7: Amount | G7: Description | H7: Expected Due Date | I7: Amount | J7: Adjusted Amount | K7: Adjusted Due Date | O7: New Britain Water Bill | P7: 0 | Q7: 795.49
B8: CVS Income | C8: 15 | D8: 3500.73 | F8: =NOT(ISBLANK(C8)) -> TRUE | G8: =IFERROR(__xludf.DUMMYFUNCTION("FILTER($B$8:$D$94, $F$8:$F$94)"),"CVS Income") -> CVS Income | H8: =IFERROR(__xludf.DUMMYFUNCTION("""COMPUTED_VALUE"""),15) -> 15 | I8: =IFERROR(__xludf.DUMMYFUNCTION("""COMPUTED_VALUE"""),3500.73) -> 3500.73 | J8: =IF(ISERROR(MATCH(G8, $B$8:$B$12, 0)), -1*I8,I8) -> 3500.73 | K8: =DATE(2025, Cashflow!$D$2, $H8) -> 45945 | O8: New Britain Auto Tax | P8: 773.71
B9: CVS Income | C9: 30 | D9: 3500.73 | F9: =NOT(ISBLANK(C9)) -> TRUE | G9: =IFERROR(__xludf.DUMMYFUNCTION("""COMPUTED_VALUE"""),"CVS Income") -> CVS Income | H9: =IFERROR(__xludf.DUMMYFUNCTION("""COMPUTED_VALUE"""),30) -> 30 | I9: =IFERROR(__xludf.DUMMYFUNCTION("""COMPUTED_VALUE"""),3500.73) -> 3500.73 | J9: =IF(ISERROR(MATCH(G9, $B$8:$B$12, 0)), -1*I9,I9) -> 3500.73 | K9: =DATE(2025, Cashflow!$D$2, $H9) -> 45960 | O9: Prism Q1 | P9: 682.5
B10: Apt 2 Rent | C10: 25 | F10: =NOT(ISBLANK(C10)) -> TRUE | G10: =IFERROR(__xludf.DUMMYFUNCTION("""COMPUTED_VALUE"""),"Apt 2 Rent") -> Apt 2 Rent | H10: =IFERROR(__xludf.DUMMYFUNCTION("""COMPUTED_VALUE"""),25) -> 25 | J10: =IF(ISERROR(MATCH(G10, $B$8:$B$12, 0)), -1*I10,I10) -> 0 | K10: =DATE(2025, Cashflow!$D$2, $H10) -> 45955 | O10: Connecticut Children
B11: Apt 3 Rent | C11: 31 | F11: =NOT(ISBLANK(C11)) -> TRUE | G11: =IFERROR(__xludf.DUMMYFUNCTION("""COMPUTED_VALUE"""),"Apt 3 Rent") -> Apt 3 Rent | H11: =IFERROR(__xludf.DUMMYFUNCTION("""COMPUTED_VALUE"""),31) -> 31 | J11: =IF(ISERROR(MATCH(G11, $B$8:$B$12, 0)), -1*I11,I11) -> 0 | K11: =DATE(2025, Cashflow!$D$2, $H11) -> 45961 | O11: Connecticut Children | P11: 2303.67
B12: Uber Income | D12: 0 | F12: =NOT(ISBLANK(C12)) -> FALSE | G12: =IFERROR(__xludf.DUMMYFUNCTION("""COMPUTED_VALUE"""),"BOA Customized Rewards") -> BOA Customized Rewards | H12: =IFERROR(__xludf.DUMMYFUNCTION("""COMPUTED_VALUE"""),9) -> 9 | I12: =IFERROR(__xludf.DUMMYFUNCTION("""COMPUTED_VALUE"""),61) -> 61 | J12: =IF(ISERROR(MATCH(G12, $B$8:$B$12, 0)), -1*I12,I12) -> -61 | K12: =DATE(2025, Cashflow!$D$2, $H12) -> 45939 | O12: Affirm | P12: 464.43
F13: =NOT(ISBLANK(C13)) -> FALSE | G13: =IFERROR(__xludf.DUMMYFUNCTION("""COMPUTED_VALUE"""),"BOA Unlimited Rewards") -> BOA Unlimited Rewards | H13: =IFERROR(__xludf.DUMMYFUNCTION("""COMPUTED_VALUE"""),4) -> 4 | I13: =IFERROR(__xludf.DUMMYFUNCTION("""COMPUTED_VALUE"""),35) -> 35 | J13: =IF(ISERROR(MATCH(G13, $B$8:$B$12, 0)), -1*I13,I13) -> -35 | K13: =DATE(2025, Cashflow!$D$2, $H13) -> 45934
B14: Total Income | D14: =SUM(D8:D12) -> 7001.46 | F14: =NOT(ISBLANK(C14)) -> FALSE | G14: =IFERROR(__xludf.DUMMYFUNCTION("""COMPUTED_VALUE"""),"CHASE Freedom") -> CHASE Freedom | H14: =IFERROR(__xludf.DUMMYFUNCTION("""COMPUTED_VALUE"""),15) -> 15 | I14: =IFERROR(__xludf.DUMMYFUNCTION("""COMPUTED_VALUE"""),440) -> 440 | J14: =IF(ISERROR(MATCH(G14, $B$8:$B$12, 0)), -1*I14,I14) -> -440 | K14: =DATE(2025, Cashflow!$D$2, $H14) -> 45945 | O14: Home Depot | P14: 576.78
F15: =NOT(ISBLANK(C15)) -> FALSE | G15: =IFERROR(__xludf.DUMMYFUNCTION("""COMPUTED_VALUE"""),"CHASE Brittany") -> CHASE Brittany | H15: =IFERROR(__xludf.DUMMYFUNCTION("""COMPUTED_VALUE"""),17) -> 17 | I15: =IFERROR(__xludf.DUMMYFUNCTION("""COMPUTED_VALUE"""),125) -> 125 | J15: =IF(ISERROR(MATCH(G15, $B$8:$B$12, 0)), -1*I15,I15) -> -125 | K15: =DATE(2025, Cashflow!$D$2, $H15) -> 45947
B16: Credit Cards | F16: =NOT(ISBLANK(C16)) -> FALSE | G16: =IFERROR(__xludf.DUMMYFUNCTION("""COMPUTED_VALUE"""),"CITI Diamond Preferred") -> CITI Diamond Preferred | H16: =IFERROR(__xludf.DUMMYFUNCTION("""COMPUTED_VALUE"""),15) -> 15 | I16: =IFERROR(__xludf.DUMMYFUNCTION("""COMPUTED_VALUE"""),120) -> 120 | J16: =IF(ISERROR(MATCH(G16, $B$8:$B$12, 0)), -1*I16,I16) -> -120 | K16: =DATE(2025, Cashflow!$D$2, $H16) -> 45945 | O16: Dividend Cash | P16: -571.45
A17: TRUE | B17: BOA Customized Rewards | C17: 9 | D17: 61 | F17: =NOT(ISBLANK(C17)) -> TRUE | G17: =IFERROR(__xludf.DUMMYFUNCTION("""COMPUTED_VALUE"""),"CITIZENS Clear Value") -> CITIZENS Clear Value | H17: =IFERROR(__xludf.DUMMYFUNCTION("""COMPUTED_VALUE"""),13) -> 13 | I17: =IFERROR(__xludf.DUMMYFUNCTION("""COMPUTED_VALUE"""),64) -> 64 | J17: =IF(ISERROR(MATCH(G17, $B$8:$B$12, 0)), -1*I17,I17) -> -64 | K17: =DATE(2025, Cashflow!$D$2, $H17) -> 45943 | O17: Sold Qualifying Stock | P17: -4580.35
A18: TRUE | B18: BOA Unlimited Rewards | C18: 4 | D18: 35 | F18: =NOT(ISBLANK(C18)) -> TRUE | G18: =IFERROR(__xludf.DUMMYFUNCTION("""COMPUTED_VALUE"""),"CITIZENS Mortgage") -> CITIZENS Mortgage | H18: =IFERROR(__xludf.DUMMYFUNCTION("""COMPUTED_VALUE"""),1) -> 1 | I18: =IFERROR(__xludf.DUMMYFUNCTION("""COMPUTED_VALUE"""),0) -> 0 | J18: =IF(ISERROR(MATCH(G18, $B$8:$B$12, 0)), -1*I18,I18) -> 0 | K18: =DATE(2025, Cashflow!$D$2, $H18) -> 45931
A19: FALSE | B19: CHASE Freedom | C19: 15 | D19: 440 | F19: =NOT(ISBLANK(C19)) -> TRUE | G19: =IFERROR(__xludf.DUMMYFUNCTION("""COMPUTED_VALUE"""),"UPSTART Debt Consolidation") -> UPSTART Debt Consolidation | H19: =IFERROR(__xludf.DUMMYFUNCTION("""COMPUTED_VALUE"""),15) -> 15 | I19: =IFERROR(__xludf.DUMMYFUNCTION("""COMPUTED_VALUE"""),181.13) -> 181.13 | J19: =IF(ISERROR(MATCH(G19, $B$8:$B$12, 0)), -1*I19,I19) -> -181.13 | K19: =DATE(2025, Cashflow!$D$2, $H19) -> 45945
A20: FALSE | B20: CHASE Brittany | C20: 17 | D20: 125 | F20: =NOT(ISBLANK(C20)) -> TRUE | G20: =IFERROR(__xludf.DUMMYFUNCTION("""COMPUTED_VALUE"""),"LIGHTSTREAM Renovation") -> LIGHTSTREAM Renovation | H20: =IFERROR(__xludf.DUMMYFUNCTION("""COMPUTED_VALUE"""),15) -> 15 | I20: =IFERROR(__xludf.DUMMYFUNCTION("""COMPUTED_VALUE"""),525.13) -> 525.13 | J20: =IF(ISERROR(MATCH(G20, $B$8:$B$12, 0)), -1*I20,I20) -> -525.13 | K20: =DATE(2025, Cashflow!$D$2, $H20) -> 45945
A21: FALSE | B21: CITI Diamond Preferred | C21: 15 | D21: 120 | F21: =NOT(ISBLANK(C21)) -> TRUE | G21: =IFERROR(__xludf.DUMMYFUNCTION("""COMPUTED_VALUE"""),"AFFIRM Photography") -> AFFIRM Photography | H21: =IFERROR(__xludf.DUMMYFUNCTION("""COMPUTED_VALUE"""),21) -> 21 | I21: =IFERROR(__xludf.DUMMYFUNCTION("""COMPUTED_VALUE"""),235.17) -> 235.17 | J21: =IF(ISERROR(MATCH(G21, $B$8:$B$12, 0)), -1*I21,I21) -> -235.17 | K21: =DATE(2025, Cashflow!$D$2, $H21) -> 45951
A22: TRUE | B22: CITIZENS Clear Value | C22: 13 | D22: 64 | F22: =NOT(ISBLANK(C22)) -> TRUE | G22: =IFERROR(__xludf.DUMMYFUNCTION("""COMPUTED_VALUE"""),"CONNEX Auto Loan") -> CONNEX Auto Loan | H22: =IFERROR(__xludf.DUMMYFUNCTION("""COMPUTED_VALUE"""),17) -> 17 | I22: =IFERROR(__xludf.DUMMYFUNCTION("""COMPUTED_VALUE"""),878.54) -> 878.54 | J22: =IF(ISERROR(MATCH(G22, $B$8:$B$12, 0)), -1*I22,I22) -> -878.54 | K22: =DATE(2025, Cashflow!$D$2, $H22) -> 45947
F23: =NOT(ISBLANK(C23)) -> FALSE | G23: =IFERROR(__xludf.DUMMYFUNCTION("""COMPUTED_VALUE"""),"Owner Contribution to Mortgage") -> Owner Contribution to Mortgage | H23: =IFERROR(__xludf.DUMMYFUNCTION("""COMPUTED_VALUE"""),1) -> 1 | I23: =IFERROR(__xludf.DUMMYFUNCTION("""COMPUTED_VALUE"""),146.54) -> 146.54 | J23: =IF(ISERROR(MATCH(G23, $B$8:$B$12, 0)), -1*I23,I23) -> -146.54 | K23: =DATE(2025, Cashflow!$D$2, $H23) -> 45931
B24: Loan Payments | F24: =NOT(ISBLANK(C24)) -> FALSE | G24: =IFERROR(__xludf.DUMMYFUNCTION("""COMPUTED_VALUE"""),"Landlord Electricity") -> Landlord Electricity | H24: =IFERROR(__xludf.DUMMYFUNCTION("""COMPUTED_VALUE"""),18) -> 18 | I24: =IFERROR(__xludf.DUMMYFUNCTION("""COMPUTED_VALUE"""),33.16) -> 33.16 | J24: =IF(ISERROR(MATCH(G24, $B$8:$B$12, 0)), -1*I24,I24) -> -33.16 | K24: =DATE(2025, Cashflow!$D$2, $H24) -> 45948
A25: TRUE | B25: CITIZENS Mortgage | C25: 1 | D25: 0 | F25: =NOT(ISBLANK(C25)) -> TRUE | G25: =IFERROR(__xludf.DUMMYFUNCTION("""COMPUTED_VALUE"""),"Maintenance (Lawn)") -> Maintenance (Lawn) | H25: =IFERROR(__xludf.DUMMYFUNCTION("""COMPUTED_VALUE"""),1) -> 1 | I25: =IFERROR(__xludf.DUMMYFUNCTION("""COMPUTED_VALUE"""),80) -> 80 | J25: =IF(ISERROR(MATCH(G25, $B$8:$B$12, 0)), -1*I25,I25) -> -80 | K25: =DATE(2025, Cashflow!$D$2, $H25) -> 45931
A26: FALSE | B26: UPSTART Debt Consolidation | C26: 15 | D26: 181.13 | F26: =NOT(ISBLANK(C26)) -> TRUE | G26: =IFERROR(__xludf.DUMMYFUNCTION("""COMPUTED_VALUE"""),"Maintenance (Lawn)") -> Maintenance (Lawn) | H26: =IFERROR(__xludf.DUMMYFUNCTION("""COMPUTED_VALUE"""),15) -> 15 | I26: =IFERROR(__xludf.DUMMYFUNCTION("""COMPUTED_VALUE"""),80) -> 80 | J26: =IF(ISERROR(MATCH(G26, $B$8:$B$12, 0)), -1*I26,I26) -> -80 | K26: =DATE(2025, Cashflow!$D$2, $H26) -> 45945
A27: FALSE | B27: LIGHTSTREAM Renovation | C27: 15 | D27: 525.13 | F27: =NOT(ISBLANK(C27)) -> TRUE | G27: =IFERROR(__xludf.DUMMYFUNCTION("""COMPUTED_VALUE"""),"Maintenance (Lawn)") -> Maintenance (Lawn) | H27: =IFERROR(__xludf.DUMMYFUNCTION("""COMPUTED_VALUE"""),29) -> 29 | I27: =IFERROR(__xludf.DUMMYFUNCTION("""COMPUTED_VALUE"""),80) -> 80 | J27: =IF(ISERROR(MATCH(G27, $B$8:$B$12, 0)), -1*I27,I27) -> -80 | K27: =DATE(2025, Cashflow!$D$2, $H27) -> 45959
A28: FALSE | B28: AFFIRM Photography | C28: 21 | D28: 235.17 | F28: =NOT(ISBLANK(C28)) -> TRUE | G28: =IFERROR(__xludf.DUMMYFUNCTION("""COMPUTED_VALUE"""),"Blink Security") -> Blink Security | H28: =IFERROR(__xludf.DUMMYFUNCTION("""COMPUTED_VALUE"""),5) -> 5 | I28: =IFERROR(__xludf.DUMMYFUNCTION("""COMPUTED_VALUE"""),10.64) -> 10.64 | J28: =IF(ISERROR(MATCH(G28, $B$8:$B$12, 0)), -1*I28,I28) -> -10.64 | K28: =DATE(2025, Cashflow!$D$2, $H28) -> 45935
A29: FALSE | B29: AQUA FINANCE Roofing Replacement | D29: 268.44 | F29: =NOT(ISBLANK(C29)) -> FALSE | G29: =IFERROR(__xludf.DUMMYFUNCTION("""COMPUTED_VALUE"""),"Avail Portal") -> Avail Portal | H29: =IFERROR(__xludf.DUMMYFUNCTION("""COMPUTED_VALUE"""),16) -> 16 | I29: =IFERROR(__xludf.DUMMYFUNCTION("""COMPUTED_VALUE"""),18) -> 18 | J29: =IF(ISERROR(MATCH(G29, $B$8:$B$12, 0)), -1*I29,I29) -> -18 | K29: =DATE(2025, Cashflow!$D$2, $H29) -> 45946
A30: FALSE | B30: CONNEX Auto Loan | C30: 17 | D30: 878.54 | F30: =NOT(ISBLANK(C30)) -> TRUE | G30: =IFERROR(__xludf.DUMMYFUNCTION("""COMPUTED_VALUE"""),"Auto Insurance") -> Auto Insurance | H30: =IFERROR(__xludf.DUMMYFUNCTION("""COMPUTED_VALUE"""),4) -> 4 | I30: =IFERROR(__xludf.DUMMYFUNCTION("""COMPUTED_VALUE"""),243.49) -> 243.49 | J30: =IF(ISERROR(MATCH(G30, $B$8:$B$12, 0)), -1*I30,I30) -> -243.49 | K30: =DATE(2025, Cashflow!$D$2, $H30) -> 45934
A31: FALSE | B31: NELNET Student Loans | F31: =NOT(ISBLANK(C31)) -> FALSE | G31: =IFERROR(__xludf.DUMMYFUNCTION("""COMPUTED_VALUE"""),"Auto Taxes (Monthly)") -> Auto Taxes (Monthly) | H31: =IFERROR(__xludf.DUMMYFUNCTION("""COMPUTED_VALUE"""),1) -> 1 | I31: =IFERROR(__xludf.DUMMYFUNCTION("""COMPUTED_VALUE"""),0) -> 0 | J31: =IF(ISERROR(MATCH(G31, $B$8:$B$12, 0)), -1*I31,I31) -> 0 | K31: =DATE(2025, Cashflow!$D$2, $H31) -> 45931
F32: =NOT(ISBLANK(C32)) -> FALSE | G32: =IFERROR(__xludf.DUMMYFUNCTION("""COMPUTED_VALUE"""),"Heating/Natural Gas") -> Heating/Natural Gas | H32: =IFERROR(__xludf.DUMMYFUNCTION("""COMPUTED_VALUE"""),23) -> 23 | I32: =IFERROR(__xludf.DUMMYFUNCTION("""COMPUTED_VALUE"""),260.73) -> 260.73 | J32: =IF(ISERROR(MATCH(G32, $B$8:$B$12, 0)), -1*I32,I32) -> -260.73 | K32: =DATE(2025, Cashflow!$D$2, $H32) -> 45953
B33: Propery Expenses | F33: =NOT(ISBLANK(C33)) -> FALSE | G33: =IFERROR(__xludf.DUMMYFUNCTION("""COMPUTED_VALUE"""),"Electricity") -> Electricity | H33: =IFERROR(__xludf.DUMMYFUNCTION("""COMPUTED_VALUE"""),18) -> 18 | I33: =IFERROR(__xludf.DUMMYFUNCTION("""COMPUTED_VALUE"""),199.07) -> 199.07 | J33: =IF(ISERROR(MATCH(G33, $B$8:$B$12, 0)), -1*I33,I33) -> -199.07 | K33: =DATE(2025, Cashflow!$D$2, $H33) -> 45948
A34: TRUE | B34: Owner Contribution to Mortgage | C34: 1 | D34: 146.54 | F34: =NOT(ISBLANK(C34)) -> TRUE | G34: =IFERROR(__xludf.DUMMYFUNCTION("""COMPUTED_VALUE"""),"Internet") -> Internet | H34: =IFERROR(__xludf.DUMMYFUNCTION("""COMPUTED_VALUE"""),28) -> 28 | I34: =IFERROR(__xludf.DUMMYFUNCTION("""COMPUTED_VALUE"""),74.95) -> 74.95 | J34: =IF(ISERROR(MATCH(G34, $B$8:$B$12, 0)), -1*I34,I34) -> -74.95 | K34: =DATE(2025, Cashflow!$D$2, $H34) -> 45958
A35: FALSE | B35: Landlord Electricity | C35: 18 | D35: 33.16 | F35: =NOT(ISBLANK(C35)) -> TRUE | G35: =IFERROR(__xludf.DUMMYFUNCTION("""COMPUTED_VALUE"""),"Life Insurance") -> Life Insurance | H35: =IFERROR(__xludf.DUMMYFUNCTION("""COMPUTED_VALUE"""),16) -> 16 | I35: =IFERROR(__xludf.DUMMYFUNCTION("""COMPUTED_VALUE"""),82.37) -> 82.37 | J35: =IF(ISERROR(MATCH(G35, $B$8:$B$12, 0)), -1*I35,I35) -> -82.37 | K35: =DATE(2025, Cashflow!$D$2, $H35) -> 45946
A36: FALSE | B36: Water/Sewer (Monthly) | D36: 130 | F36: =NOT(ISBLANK(C36)) -> FALSE | G36: =IFERROR(__xludf.DUMMYFUNCTION("""COMPUTED_VALUE"""),"Groceries + Toiletries") -> Groceries + Toiletries | H36: =IFERROR(__xludf.DUMMYFUNCTION("""COMPUTED_VALUE"""),1) -> 1 | I36: =IFERROR(__xludf.DUMMYFUNCTION("""COMPUTED_VALUE"""),252.58) -> 252.58 | J36: =IF(ISERROR(MATCH(G36, $B$8:$B$12, 0)), -1*I36,I36) -> -252.58 | K36: =DATE(2025, Cashflow!$D$2, $H36) -> 45931
A37: TRUE | B37: Maintenance (Lawn) | C37: 1 | D37: =IF($C$2="Summer", 80, 0) -> 80 | F37: =NOT(ISBLANK(C37)) -> TRUE | G37: =IFERROR(__xludf.DUMMYFUNCTION("""COMPUTED_VALUE"""),"Groceries + Toiletries") -> Groceries + Toiletries | H37: =IFERROR(__xludf.DUMMYFUNCTION("""COMPUTED_VALUE"""),8) -> 8 | I37: =IFERROR(__xludf.DUMMYFUNCTION("""COMPUTED_VALUE"""),248.95) -> 248.95 | J37: =IF(ISERROR(MATCH(G37, $B$8:$B$12, 0)), -1*I37,I37) -> -248.95 | K37: =DATE(2025, Cashflow!$D$2, $H37) -> 45938
A38: FALSE | B38: Maintenance (Lawn) | C38: 15 | D38: =IF($C$2="Summer", 80, 0) -> 80 | F38: =NOT(ISBLANK(C38)) -> TRUE | G38: =IFERROR(__xludf.DUMMYFUNCTION("""COMPUTED_VALUE"""),"Groceries + Toiletries") -> Groceries + Toiletries | H38: =IFERROR(__xludf.DUMMYFUNCTION("""COMPUTED_VALUE"""),15) -> 15 | I38: =IFERROR(__xludf.DUMMYFUNCTION("""COMPUTED_VALUE"""),250) -> 250 | J38: =IF(ISERROR(MATCH(G38, $B$8:$B$12, 0)), -1*I38,I38) -> -250 | K38: =DATE(2025, Cashflow!$D$2, $H38) -> 45945
A39: FALSE | B39: Maintenance (Lawn) | C39: 29 | D39: =IF($C$2="Summer", 80, 0) -> 80 | F39: =NOT(ISBLANK(C39)) -> TRUE | G39: =IFERROR(__xludf.DUMMYFUNCTION("""COMPUTED_VALUE"""),"Groceries + Toiletries") -> Groceries + Toiletries | H39: =IFERROR(__xludf.DUMMYFUNCTION("""COMPUTED_VALUE"""),22) -> 22 | I39: =IFERROR(__xludf.DUMMYFUNCTION("""COMPUTED_VALUE"""),250) -> 250 | J39: =IF(ISERROR(MATCH(G39, $B$8:$B$12, 0)), -1*I39,I39) -> -250 | K39: =DATE(2025, Cashflow!$D$2, $H39) -> 45952
A40: TRUE | B40: Maintenance (Snow Removal) | D40: =IF($C$2="Winter", 110, 0) -> 0 | F40: =NOT(ISBLANK(C40)) -> FALSE | G40: =IFERROR(__xludf.DUMMYFUNCTION("""COMPUTED_VALUE"""),"Groceries + Toiletries") -> Groceries + Toiletries | H40: =IFERROR(__xludf.DUMMYFUNCTION("""COMPUTED_VALUE"""),29) -> 29 | I40: =IFERROR(__xludf.DUMMYFUNCTION("""COMPUTED_VALUE"""),250) -> 250 | J40: =IF(ISERROR(MATCH(G40, $B$8:$B$12, 0)), -1*I40,I40) -> -250 | K40: =DATE(2025, Cashflow!$D$2, $H40) -> 45959
A41: TRUE | B41: Blink Security | C41: 5 | D41: 10.64 | F41: =NOT(ISBLANK(C41)) -> TRUE | G41: =IFERROR(__xludf.DUMMYFUNCTION("""COMPUTED_VALUE"""),"Phone (Nykosi)") -> Phone (Nykosi) | H41: =IFERROR(__xludf.DUMMYFUNCTION("""COMPUTED_VALUE"""),16) -> 16 | I41: =IFERROR(__xludf.DUMMYFUNCTION("""COMPUTED_VALUE"""),30) -> 30 | J41: =IF(ISERROR(MATCH(G41, $B$8:$B$12, 0)), -1*I41,I41) -> -30 | K41: =DATE(2025, Cashflow!$D$2, $H41) -> 45946
A42: FALSE | B42: Avail Portal | C42: 16 | D42: 18 | F42: =NOT(ISBLANK(C42)) -> TRUE | G42: =IFERROR(__xludf.DUMMYFUNCTION("""COMPUTED_VALUE"""),"Phone (Brittany)") -> Phone (Brittany) | H42: =IFERROR(__xludf.DUMMYFUNCTION("""COMPUTED_VALUE"""),16) -> 16 | I42: =IFERROR(__xludf.DUMMYFUNCTION("""COMPUTED_VALUE"""),50) -> 50 | J42: =IF(ISERROR(MATCH(G42, $B$8:$B$12, 0)), -1*I42,I42) -> -50 | K42: =DATE(2025, Cashflow!$D$2, $H42) -> 45946
F43: =NOT(ISBLANK(C43)) -> FALSE | G43: =IFERROR(__xludf.DUMMYFUNCTION("""COMPUTED_VALUE"""),"Gym Membership (Nykosi)") -> Gym Membership (Nykosi) | H43: =IFERROR(__xludf.DUMMYFUNCTION("""COMPUTED_VALUE"""),24) -> 24 | I43: =IFERROR(__xludf.DUMMYFUNCTION("""COMPUTED_VALUE"""),22.23) -> 22.23 | J43: =IF(ISERROR(MATCH(G43, $B$8:$B$12, 0)), -1*I43,I43) -> -22.23 | K43: =DATE(2025, Cashflow!$D$2, $H43) -> 45954
B44: Bills | F44: =NOT(ISBLANK(C44)) -> FALSE | G44: =IFERROR(__xludf.DUMMYFUNCTION("""COMPUTED_VALUE"""),"Gym Membership (Brittany)") -> Gym Membership (Brittany) | H44: =IFERROR(__xludf.DUMMYFUNCTION("""COMPUTED_VALUE"""),6) -> 6 | I44: =IFERROR(__xludf.DUMMYFUNCTION("""COMPUTED_VALUE"""),32.87) -> 32.87 | J44: =IF(ISERROR(MATCH(G44, $B$8:$B$12, 0)), -1*I44,I44) -> -32.87 | K44: =DATE(2025, Cashflow!$D$2, $H44) -> 45936
A45: TRUE | B45: Auto Insurance | C45: 4 | D45: 243.49 | F45: =NOT(ISBLANK(C45)) -> TRUE | G45: =IFERROR(__xludf.DUMMYFUNCTION("""COMPUTED_VALUE"""),"Gym Trainer (Brittany)") -> Gym Trainer (Brittany) | H45: =IFERROR(__xludf.DUMMYFUNCTION("""COMPUTED_VALUE"""),5) -> 5 | I45: =IFERROR(__xludf.DUMMYFUNCTION("""COMPUTED_VALUE"""),105.29) -> 105.29 | J45: =IF(ISERROR(MATCH(G45, $B$8:$B$12, 0)), -1*I45,I45) -> -105.29 | K45: =DATE(2025, Cashflow!$D$2, $H45) -> 45935
A46: FALSE | B46: Auto Taxes (Monthly) | C46: 1 | D46: 0 | F46: =NOT(ISBLANK(C46)) -> TRUE | G46: =IFERROR(__xludf.DUMMYFUNCTION("""COMPUTED_VALUE"""),"Gym Trainer (Brittany)") -> Gym Trainer (Brittany) | H46: =IFERROR(__xludf.DUMMYFUNCTION("""COMPUTED_VALUE"""),19) -> 19 | I46: =IFERROR(__xludf.DUMMYFUNCTION("""COMPUTED_VALUE"""),105.29) -> 105.29 | J46: =IF(ISERROR(MATCH(G46, $B$8:$B$12, 0)), -1*I46,I46) -> -105.29 | K46: =DATE(2025, Cashflow!$D$2, $H46) -> 45949
A47: FALSE | B47: Heating/Natural Gas | C47: 23 | D47: 260.73 | F47: =NOT(ISBLANK(C47)) -> TRUE | G47: =IFERROR(__xludf.DUMMYFUNCTION("""COMPUTED_VALUE"""),"Amazon Prime") -> Amazon Prime | H47: =IFERROR(__xludf.DUMMYFUNCTION("""COMPUTED_VALUE"""),14) -> 14 | I47: =IFERROR(__xludf.DUMMYFUNCTION("""COMPUTED_VALUE"""),14.99) -> 14.99 | J47: =IF(ISERROR(MATCH(G47, $B$8:$B$12, 0)), -1*I47,I47) -> -14.99 | K47: =DATE(2025, Cashflow!$D$2, $H47) -> 45944
A48: FALSE | B48: Electricity | C48: 18 | D48: 199.07 | F48: =NOT(ISBLANK(C48)) -> TRUE | G48: =IFERROR(__xludf.DUMMYFUNCTION("""COMPUTED_VALUE"""),"Drawboard PDF") -> Drawboard PDF | H48: =IFERROR(__xludf.DUMMYFUNCTION("""COMPUTED_VALUE"""),29) -> 29 | I48: =IFERROR(__xludf.DUMMYFUNCTION("""COMPUTED_VALUE"""),5.99) -> 5.99 | J48: =IF(ISERROR(MATCH(G48, $B$8:$B$12, 0)), -1*I48,I48) -> -5.99 | K48: =DATE(2025, Cashflow!$D$2, $H48) -> 45959
A49: FALSE | B49: Internet | C49: 28 | D49: 74.95 | F49: =NOT(ISBLANK(C49)) -> TRUE | G49: =IFERROR(__xludf.DUMMYFUNCTION("""COMPUTED_VALUE"""),"Mailchimp") -> Mailchimp | H49: =IFERROR(__xludf.DUMMYFUNCTION("""COMPUTED_VALUE"""),25) -> 25 | I49: =IFERROR(__xludf.DUMMYFUNCTION("""COMPUTED_VALUE"""),14.04) -> 14.04 | J49: =IF(ISERROR(MATCH(G49, $B$8:$B$12, 0)), -1*I49,I49) -> -14.04 | K49: =DATE(2025, Cashflow!$D$2, $H49) -> 45955
A50: FALSE | B50: Life Insurance | C50: 16 | D50: 82.37 | F50: =NOT(ISBLANK(C50)) -> TRUE | G50: =IFERROR(__xludf.DUMMYFUNCTION("""COMPUTED_VALUE"""),"Microsoft 365") -> Microsoft 365 | H50: =IFERROR(__xludf.DUMMYFUNCTION("""COMPUTED_VALUE"""),17) -> 17 | I50: =IFERROR(__xludf.DUMMYFUNCTION("""COMPUTED_VALUE"""),14.14) -> 14.14 | J50: =IF(ISERROR(MATCH(G50, $B$8:$B$12, 0)), -1*I50,I50) -> -14.14 | K50: =DATE(2025, Cashflow!$D$2, $H50) -> 45947
F51: =NOT(ISBLANK(C51)) -> FALSE | G51: =IFERROR(__xludf.DUMMYFUNCTION("""COMPUTED_VALUE"""),"Netflix") -> Netflix | H51: =IFERROR(__xludf.DUMMYFUNCTION("""COMPUTED_VALUE"""),23) -> 23 | I51: =IFERROR(__xludf.DUMMYFUNCTION("""COMPUTED_VALUE"""),19.3) -> 19.3 | J51: =IF(ISERROR(MATCH(G51, $B$8:$B$12, 0)), -1*I51,I51) -> -19.3 | K51: =DATE(2025, Cashflow!$D$2, $H51) -> 45953
B52: Expenses (Needs) | F52: =NOT(ISBLANK(C52)) -> FALSE | G52: =IFERROR(__xludf.DUMMYFUNCTION("""COMPUTED_VALUE"""),"YNAB ") -> YNAB | H52: =IFERROR(__xludf.DUMMYFUNCTION("""COMPUTED_VALUE"""),9) -> 9 | I52: =IFERROR(__xludf.DUMMYFUNCTION("""COMPUTED_VALUE"""),14.99) -> 14.99 | J52: =IF(ISERROR(MATCH(G52, $B$8:$B$12, 0)), -1*I52,I52) -> -14.99 | K52: =DATE(2025, Cashflow!$D$2, $H52) -> 45939
A53: TRUE | B53: Groceries + Toiletries | C53: 1 | D53: 252.58 | F53: =NOT(ISBLANK(C53)) -> TRUE | G53: =IFERROR(__xludf.DUMMYFUNCTION("""COMPUTED_VALUE"""),"OpenAI") -> OpenAI | H53: =IFERROR(__xludf.DUMMYFUNCTION("""COMPUTED_VALUE"""),16) -> 16 | I53: =IFERROR(__xludf.DUMMYFUNCTION("""COMPUTED_VALUE"""),20.2) -> 20.2 | J53: =IF(ISERROR(MATCH(G53, $B$8:$B$12, 0)), -1*I53,I53) -> -20.2 | K53: =DATE(2025, Cashflow!$D$2, $H53) -> 45946
A54: TRUE | B54: Groceries + Toiletries | C54: 8 | D54: 248.95 | F54: =NOT(ISBLANK(C54)) -> TRUE | G54: =IFERROR(__xludf.DUMMYFUNCTION("""COMPUTED_VALUE"""),"SAH Stipend (1/2)") -> SAH Stipend (1/2) | H54: =IFERROR(__xludf.DUMMYFUNCTION("""COMPUTED_VALUE"""),15) -> 15 | I54: =IFERROR(__xludf.DUMMYFUNCTION("""COMPUTED_VALUE"""),250) -> 250 | J54: =IF(ISERROR(MATCH(G54, $B$8:$B$12, 0)), -1*I54,I54) -> -250 | K54: =DATE(2025, Cashflow!$D$2, $H54) -> 45945
A55: FALSE | B55: Groceries + Toiletries | C55: 15 | D55: 250 | F55: =NOT(ISBLANK(C55)) -> TRUE | G55: =IFERROR(__xludf.DUMMYFUNCTION("""COMPUTED_VALUE"""),"SAH Stipend (2/2)") -> SAH Stipend (2/2) | H55: =IFERROR(__xludf.DUMMYFUNCTION("""COMPUTED_VALUE"""),30) -> 30 | I55: =IFERROR(__xludf.DUMMYFUNCTION("""COMPUTED_VALUE"""),250) -> 250 | J55: =IF(ISERROR(MATCH(G55, $B$8:$B$12, 0)), -1*I55,I55) -> -250 | K55: =DATE(2025, Cashflow!$D$2, $H55) -> 45960
A56: FALSE | B56: Groceries + Toiletries | C56: 22 | D56: 250 | F56: =NOT(ISBLANK(C56)) -> TRUE | G56: =IFERROR(__xludf.DUMMYFUNCTION("""COMPUTED_VALUE"""),"Gym Membership (Nykosi)") -> Gym Membership (Nykosi) | H56: =IFERROR(__xludf.DUMMYFUNCTION("""COMPUTED_VALUE"""),24) -> 24 | I56: =IFERROR(__xludf.DUMMYFUNCTION("""COMPUTED_VALUE"""),0) -> 0 | J56: =IF(ISERROR(MATCH(G56, $B$8:$B$12, 0)), -1*I56,I56) -> 0 | K56: =DATE(2025, Cashflow!$D$2, $H56) -> 45954
A57: FALSE | B57: Groceries + Toiletries | C57: 29 | D57: 250 | F57: =NOT(ISBLANK(C57)) -> TRUE | G57: =IFERROR(__xludf.DUMMYFUNCTION("""COMPUTED_VALUE"""),"Gym Membership (Brittany)") -> Gym Membership (Brittany) | H57: =IFERROR(__xludf.DUMMYFUNCTION("""COMPUTED_VALUE"""),6) -> 6 | I57: =IFERROR(__xludf.DUMMYFUNCTION("""COMPUTED_VALUE"""),0) -> 0 | J57: =IF(ISERROR(MATCH(G57, $B$8:$B$12, 0)), -1*I57,I57) -> 0 | K57: =DATE(2025, Cashflow!$D$2, $H57) -> 45936
A58: FALSE | B58: Phone (Nykosi) | C58: 16 | D58: 30 | F58: =NOT(ISBLANK(C58)) -> TRUE | J58: =IF(ISERROR(MATCH(G58, $B$8:$B$12, 0)), -1*I58,I58) -> 0 | K58: =DATE(2025, Cashflow!$D$2, $H58) -> 45930
A59: FALSE | B59: Phone (Brittany) | C59: 16 | D59: 50 | F59: =NOT(ISBLANK(C59)) -> TRUE | J59: =IF(ISERROR(MATCH(G59, $B$8:$B$12, 0)), -1*I59,I59) -> 0 | K59: =DATE(2025, Cashflow!$D$2, $H59) -> 45930
F60: =NOT(ISBLANK(C60)) -> FALSE | J60: =IF(ISERROR(MATCH(G60, $B$8:$B$12, 0)), -1*I60,I60) -> 0 | K60: =DATE(2025, Cashflow!$D$2, $H60) -> 45930
B61: Expenses (Wants) | F61: =NOT(ISBLANK(C61)) -> FALSE | J61: =IF(ISERROR(MATCH(G61, $B$8:$B$12, 0)), -1*I61,I61) -> 0 | K61: =DATE(2025, Cashflow!$D$2, $H61) -> 45930
A62: FALSE | B62: Gym Membership (Nykosi) | C62: 24 | D62: 22.23 | F62: =NOT(ISBLANK(C62)) -> TRUE | J62: =IF(ISERROR(MATCH(G62, $B$8:$B$12, 0)), -1*I62,I62) -> 0 | K62: =DATE(2025, Cashflow!$D$2, $H62) -> 45930
A63: TRUE | B63: Gym Membership (Brittany) | C63: 6 | D63: 32.87 | F63: =NOT(ISBLANK(C63)) -> TRUE | J63: =IF(ISERROR(MATCH(G63, $B$8:$B$12, 0)), -1*I63,I63) -> 0 | K63: =DATE(2025, Cashflow!$D$2, $H63) -> 45930
A64: TRUE | B64: Gym Trainer (Brittany) | C64: 5 | D64: 105.29 | F64: =NOT(ISBLANK(C64)) -> TRUE | J64: =IF(ISERROR(MATCH(G64, $B$8:$B$12, 0)), -1*I64,I64) -> 0 | K64: =DATE(2025, Cashflow!$D$2, $H64) -> 45930
A65: FALSE | B65: Gym Trainer (Brittany) | C65: 19 | D65: 105.29 | F65: =NOT(ISBLANK(C65)) -> TRUE | J65: =IF(ISERROR(MATCH(G65, $B$8:$B$12, 0)), -1*I65,I65) -> 0 | K65: =DATE(2025, Cashflow!$D$2, $H65) -> 45930
A66: FALSE | B66: Amazon Prime | C66: 14 | D66: 14.99 | F66: =NOT(ISBLANK(C66)) -> TRUE | J66: =IF(ISERROR(MATCH(G66, $B$8:$B$12, 0)), -1*I66,I66) -> 0 | K66: =DATE(2025, Cashflow!$D$2, $H66) -> 45930
A67: FALSE | B67: Drawboard PDF | C67: 29 | D67: 5.99 | F67: =NOT(ISBLANK(C67)) -> TRUE | J67: =IF(ISERROR(MATCH(G67, $B$8:$B$12, 0)), -1*I67,I67) -> 0 | K67: =DATE(2025, Cashflow!$D$2, $H67) -> 45930
A68: FALSE | B68: Mailchimp | C68: 25 | D68: 14.04 | F68: =NOT(ISBLANK(C68)) -> TRUE | J68: =IF(ISERROR(MATCH(G68, $B$8:$B$12, 0)), -1*I68,I68) -> 0 | K68: =DATE(2025, Cashflow!$D$2, $H68) -> 45930
A69: FALSE | B69: Microsoft 365 | C69: 17 | D69: 14.14 | F69: =NOT(ISBLANK(C69)) -> TRUE | J69: =IF(ISERROR(MATCH(G69, $B$8:$B$12, 0)), -1*I69,I69) -> 0 | K69: =DATE(2025, Cashflow!$D$2, $H69) -> 45930
A70: FALSE | B70: Netflix | C70: 23 | D70: 19.3 | F70: =NOT(ISBLANK(C70)) -> TRUE | J70: =IF(ISERROR(MATCH(G70, $B$8:$B$12, 0)), -1*I70,I70) -> 0 | K70: =DATE(2025, Cashflow!$D$2, $H70) -> 45930
A71: FALSE | B71: YNAB | C71: 9 | D71: 14.99 | F71: =NOT(ISBLANK(C71)) -> TRUE | J71: =IF(ISERROR(MATCH(G71, $B$8:$B$12, 0)), -1*I71,I71) -> 0 | K71: =DATE(2025, Cashflow!$D$2, $H71) -> 45930
A72: FALSE | B72: OpenAI | C72: 16 | D72: 20.2 | F72: =NOT(ISBLANK(C72)) -> TRUE | J72: =IF(ISERROR(MATCH(G72, $B$8:$B$12, 0)), -1*I72,I72) -> 0 | K72: =DATE(2025, Cashflow!$D$2, $H72) -> 45930
A73: FALSE | B73: SAH Stipend (1/2) | C73: 15 | D73: 250 | F73: =NOT(ISBLANK(C73)) -> TRUE | J73: =IF(ISERROR(MATCH(G73, $B$8:$B$12, 0)), -1*I73,I73) -> 0 | K73: =DATE(2025, Cashflow!$D$2, $H73) -> 45930
A74: FALSE | B74: SAH Stipend (2/2) | C74: 30 | D74: 250 | F74: =NOT(ISBLANK(C74)) -> TRUE | J74: =IF(ISERROR(MATCH(G74, $B$8:$B$12, 0)), -1*I74,I74) -> 0 | K74: =DATE(2025, Cashflow!$D$2, $H74) -> 45930
F75: =NOT(ISBLANK(C75)) -> FALSE | J75: =IF(ISERROR(MATCH(G75, $B$8:$B$12, 0)), -1*I75,I75) -> 0 | K75: =DATE(2025, Cashflow!$D$2, $H75) -> 45930
B76: One-Time Expenses | F76: =NOT(ISBLANK(C76)) -> FALSE | J76: =IF(ISERROR(MATCH(G76, $B$8:$B$12, 0)), -1*I76,I76) -> 0 | K76: =DATE(2025, Cashflow!$D$2, $H76) -> 45930
A77: FALSE | B77: Gym Membership (Nykosi) | C77: 24 | D77: 0 | F77: =NOT(ISBLANK(C77)) -> TRUE | J77: =IF(ISERROR(MATCH(G77, $B$8:$B$12, 0)), -1*I77,I77) -> 0 | K77: =DATE(2025, Cashflow!$D$2, $H77) -> 45930
A78: FALSE | B78: Gym Membership (Brittany) | C78: 6 | D78: 0 | F78: =NOT(ISBLANK(C78)) -> TRUE | J78: =IF(ISERROR(MATCH(G78, $B$8:$B$12, 0)), -1*I78,I78) -> 0 | K78: =DATE(2025, Cashflow!$D$2, $H78) -> 45930
F79: =NOT(ISBLANK(C79)) -> FALSE | J79: =IF(ISERROR(MATCH(G79, $B$8:$B$12, 0)), -1*I79,I79) -> 0 | K79: =DATE(2025, Cashflow!$D$2, $H79) -> 45930
B80: Cash After Expenses | D80: =$D$14-SUM($D$17:$D$79) -> 428.24 | F80: =NOT(ISBLANK(C80)) -> FALSE | J80: =IF(ISERROR(MATCH(G80, $B$8:$B$12, 0)), -1*I80,I80) -> 0 | K80: =DATE(2025, Cashflow!$D$2, $H80) -> 45930
F81: =NOT(ISBLANK(C81)) -> FALSE | J81: =IF(ISERROR(MATCH(G81, $B$8:$B$12, 0)), -1*I81,I81) -> 0 | K81: =DATE(2025, Cashflow!$D$2, $H81) -> 45930
F82: =NOT(ISBLANK(C82)) -> FALSE | J82: =IF(ISERROR(MATCH(G82, $B$8:$B$12, 0)), -1*I82,I82) -> 0 | K82: =DATE(2025, Cashflow!$D$2, $H82) -> 45930
B83: Savings | F83: =NOT(ISBLANK(C83)) -> FALSE | J83: =IF(ISERROR(MATCH(G83, $B$8:$B$12, 0)), -1*I83,I83) -> 0 | K83: =DATE(2025, Cashflow!$D$2, $H83) -> 45930
B84: Education 529s | F84: =NOT(ISBLANK(C84)) -> FALSE | J84: =IF(ISERROR(MATCH(G84, $B$8:$B$12, 0)), -1*I84,I84) -> 0 | K84: =DATE(2025, Cashflow!$D$2, $H84) -> 45930
B85: Emergency Fund | F85: =NOT(ISBLANK(C85)) -> FALSE | J85: =IF(ISERROR(MATCH(G85, $B$8:$B$12, 0)), -1*I85,I85) -> 0 | K85: =DATE(2025, Cashflow!$D$2, $H85) -> 45930
F86: =NOT(ISBLANK(C86)) -> FALSE | J86: =IF(ISERROR(MATCH(G86, $B$8:$B$12, 0)), -1*I86,I86) -> 0 | K86: =DATE(2025, Cashflow!$D$2, $H86) -> 45930
F87: =NOT(ISBLANK(C87)) -> FALSE | J87: =IF(ISERROR(MATCH(G87, $B$8:$B$12, 0)), -1*I87,I87) -> 0 | K87: =DATE(2025, Cashflow!$D$2, $H87) -> 45930
F88: =NOT(ISBLANK(C88)) -> FALSE | J88: =IF(ISERROR(MATCH(G88, $B$8:$B$12, 0)), -1*I88,I88) -> 0 | K88: =DATE(2025, Cashflow!$D$2, $H88) -> 45930
F89: =NOT(ISBLANK(C89)) -> FALSE | J89: =IF(ISERROR(MATCH(G89, $B$8:$B$12, 0)), -1*I89,I89) -> 0 | K89: =DATE(2025, Cashflow!$D$2, $H89) -> 45930
F90: =NOT(ISBLANK(C90)) -> FALSE | J90: =IF(ISERROR(MATCH(G90, $B$8:$B$12, 0)), -1*I90,I90) -> 0 | K90: =DATE(2025, Cashflow!$D$2, $H90) -> 45930
F91: =NOT(ISBLANK(C91)) -> FALSE | J91: =IF(ISERROR(MATCH(G91, $B$8:$B$12, 0)), -1*I91,I91) -> 0 | K91: =DATE(2025, Cashflow!$D$2, $H91) -> 45930
F92: =NOT(ISBLANK(C92)) -> FALSE | J92: =IF(ISERROR(MATCH(G92, $B$8:$B$12, 0)), -1*I92,I92) -> 0 | K92: =DATE(2025, Cashflow!$D$2, $H92) -> 45930
F93: =NOT(ISBLANK(C93)) -> FALSE | J93: =IF(ISERROR(MATCH(G93, $B$8:$B$12, 0)), -1*I93,I93) -> 0 | K93: =DATE(2025, Cashflow!$D$2, $H93) -> 45930
F94: =NOT(ISBLANK(C94)) -> FALSE | J94: =IF(ISERROR(MATCH(G94, $B$8:$B$12, 0)), -1*I94,I94) -> 0 | K94: =DATE(2025, Cashflow!$D$2, $H94) -> 45930

Sheet 202509
B2: Season | C2: Summer
B4: =SUMIFS(D17:D91, C17:C91, "<=14") -> 1812.24 | C4: Expenses: 1st to 15th
B5: =SUMIFS(D17:D91, C17:C91, ">=15") -> 2369.98 | C5: Expenses: 15th to 30th
B7: Description | C7: Expected Due Date | D7: Amount
A8: =IFERROR(NOT(ISBLANK(C8)), FALSE) -> TRUE | B8: CVS Income | C8: 15 | D8: 3250.73
A9: =IFERROR(NOT(ISBLANK(C9)), FALSE) -> TRUE | B9: CVS Income | C9: 30 | D9: 3250.73
A10: =IFERROR(NOT(ISBLANK(C10)), FALSE) -> FALSE | B10: Apt 2 Rent
A11: =IFERROR(NOT(ISBLANK(C11)), FALSE) -> FALSE | B11: Apt 3 Rent
A12: =IFERROR(NOT(ISBLANK(C12)), FALSE) -> FALSE | B12: Uber Income
A13: =IFERROR(NOT(ISBLANK(C13)), FALSE) -> FALSE
A14: =IFERROR(NOT(ISBLANK(C14)), FALSE) -> FALSE | B14: Total Income | D14: =SUM(D8:D12) -> 6501.46
A15: =IFERROR(NOT(ISBLANK(C15)), FALSE) -> FALSE
A16: =IFERROR(NOT(ISBLANK(C16)), FALSE) -> FALSE | B16: Credit Cards
A17: =IFERROR(NOT(ISBLANK(C17)), FALSE) -> TRUE | B17: BOA Customized Rewards | C17: 9
B18: BOA Unlimited Rewards | C18: 4
B19: CHASE Freedom | C19: 15
B20: CHASE Brittany | C20: 17
B21: CITI Diamond Preferred | C21: 15 | D21: 120
A22: =IFERROR(NOT(ISBLANK(C22)), FALSE) -> TRUE | B22: CITIZENS Clear Value | C22: 13 | D22: 64
A23: =IFERROR(NOT(ISBLANK(C23)), FALSE) -> FALSE
A24: =IFERROR(NOT(ISBLANK(C24)), FALSE) -> FALSE | B24: Loan Payments
A25: =IFERROR(NOT(ISBLANK(C25)), FALSE) -> TRUE | B25: CITIZENS HELOC | C25: 1 | D25: 407
B26: UPSTART Debt Consolidation | C26: 15 | D26: 181.13
A27: =IFERROR(NOT(ISBLANK(C27)), FALSE) -> TRUE | B27: LIGHTSTREAM Renovation | C27: 15
B28: AFFIRM Photography | C28: 21 | D28: 235.17
B29: AQUA FINANCE Roofing Replacement | D29: 268.44
A30: =IFERROR(NOT(ISBLANK(C30)), FALSE) -> TRUE | B30: TD Auto Loan | C30: 17 | D30: 595 | F30: ~$3000 Underwater on loan (ie, need to pay this as a downpayment)
A31: =IFERROR(NOT(ISBLANK(C31)), FALSE) -> FALSE | B31: NELNET Student Loans
A32: =IFERROR(NOT(ISBLANK(C32)), FALSE) -> FALSE
A33: =IFERROR(NOT(ISBLANK(C33)), FALSE) -> FALSE | B33: Propery Expenses
A34: =IFERROR(NOT(ISBLANK(C34)), FALSE) -> TRUE | B34: Owner Contribution to Mortgage | C34: 1 | D34: 146.54
A35: =IFERROR(NOT(ISBLANK(C35)), FALSE) -> TRUE | B35: Landlord Electricity | C35: 18 | D35: 33.16
A36: =IFERROR(NOT(ISBLANK(C36)), FALSE) -> FALSE | B36: Water/Sewer (Monthly) | D36: 130
A37: =IFERROR(NOT(ISBLANK(C37)), FALSE) -> TRUE | B37: Maintenance (Lawn) | C37: 10 | D37: =IF($C$2="Summer", 80, 0) -> 80
A38: =IFERROR(NOT(ISBLANK(C38)), FALSE) -> TRUE | B38: Maintenance (Lawn) | C38: 24 | D38: =IF($C$2="Summer", 80, 0) -> 80
A39: =IFERROR(NOT(ISBLANK(C39)), FALSE) -> FALSE | B39: Maintenance (Snow Removal) | D39: =IF($C$2="Winter", 110, 0) -> 0
A40: =IFERROR(NOT(ISBLANK(C40)), FALSE) -> TRUE | B40: Blink Security | C40: 5 | D40: 10.64
A41: =IFERROR(NOT(ISBLANK(C41)), FALSE) -> TRUE | B41: Avail Portal | C41: 16 | D41: 18
A42: =IFERROR(NOT(ISBLANK(C42)), FALSE) -> FALSE
A43: =IFERROR(NOT(ISBLANK(C43)), FALSE) -> FALSE | B43: Bills
A44: =IFERROR(NOT(ISBLANK(C44)), FALSE) -> TRUE | B44: Auto Insurance | C44: 4 | D44: 243.49
A45: =IFERROR(NOT(ISBLANK(C45)), FALSE) -> FALSE | B45: Auto Taxes (Monthly)
A46: =IFERROR(NOT(ISBLANK(C46)), FALSE) -> TRUE | B46: Heating/Natural Gas | C46: 15 | D46: 175
A47: =IFERROR(NOT(ISBLANK(C47)), FALSE) -> TRUE | B47: Electricity | C47: 1 | D47: 192.43
A48: =IFERROR(NOT(ISBLANK(C48)), FALSE) -> TRUE | B48: Internet | C48: 27 | D48: 74.95
A49: =IFERROR(NOT(ISBLANK(C49)), FALSE) -> TRUE | B49: Life Insurance | C49: 16 | D49: 82.37
A50: =IFERROR(NOT(ISBLANK(C50)), FALSE) -> FALSE
A51: =IFERROR(NOT(ISBLANK(C51)), FALSE) -> FALSE | B51: Expenses (Needs)
A52: =IFERROR(NOT(ISBLANK(C52)), FALSE) -> TRUE | B52: Groceries + Toiletries | C52: 5 | D52: 250
A53: =IFERROR(NOT(ISBLANK(C53)), FALSE) -> TRUE | B53: Groceries + Toiletries | C53: 12 | D53: 250
A54: =IFERROR(NOT(ISBLANK(C54)), FALSE) -> TRUE | B54: Groceries + Toiletries | C54: 19 | D54: 250
A55: =IFERROR(NOT(ISBLANK(C55)), FALSE) -> TRUE | B55: Groceries + Toiletries | C55: 26 | D55: 250
A56: =IFERROR(NOT(ISBLANK(C56)), FALSE) -> TRUE | B56: Phone (Nykosi) | C56: 16 | D56: 30
A57: =IFERROR(NOT(ISBLANK(C57)), FALSE) -> TRUE | B57: Phone (Brittany) | C57: 16 | D57: 50
A58: =IFERROR(NOT(ISBLANK(C58)), FALSE) -> FALSE
A59: =IFERROR(NOT(ISBLANK(C59)), FALSE) -> FALSE | B59: Expenses (Wants)
A60: =IFERROR(NOT(ISBLANK(C60)), FALSE) -> TRUE | B60: Gym Membership (Nykosi) | C60: 24 | D60: 22.23
A61: =IFERROR(NOT(ISBLANK(C61)), FALSE) -> TRUE | B61: Gym Membership (Brittany) | C61: 6 | D61: 32.87
A62: =IFERROR(NOT(ISBLANK(C62)), FALSE) -> TRUE | B62: Gym Trainer (Brittany) | C62: 2 | D62: 105.29
A63: =IFERROR(NOT(ISBLANK(C63)), FALSE) -> TRUE | B63: Gym Trainer (Brittany) | C63: 16 | D63: 105.29
A64: =IFERROR(NOT(ISBLANK(C64)), FALSE) -> TRUE | B64: Amazon Prime | C64: 14 | D64: 14.99
A65: =IFERROR(NOT(ISBLANK(C65)), FALSE) -> TRUE | B65: Mailchimp | C65: 25 | D65: 14.04
A66: =IFERROR(NOT(ISBLANK(C66)), FALSE) -> TRUE | B66: Microsoft 365 | C66: 17 | D66: 14.14
A67: =IFERROR(NOT(ISBLANK(C67)), FALSE) -> TRUE | B67: Netflix | C67: 23 | D67: 19.3
A68: =IFERROR(NOT(ISBLANK(C68)), FALSE) -> TRUE | B68: YNAB | C68: 9 | D68: 14.99
A69: =IFERROR(NOT(ISBLANK(C69)), FALSE) -> TRUE | B69: OpenAI | C69: 16 | D69: 20.2
A70: =IFERROR(NOT(ISBLANK(C70)), FALSE) -> FALSE
A71: =IFERROR(NOT(ISBLANK(C71)), FALSE) -> FALSE
A72: =IFERROR(NOT(ISBLANK(C72)), FALSE) -> FALSE
A73: =IFERROR(NOT(ISBLANK(C73)), FALSE) -> FALSE | B73: One-Time Expenses
A74: =IFERROR(NOT(ISBLANK(C74)), FALSE) -> FALSE
A75: =IFERROR(NOT(ISBLANK(C75)), FALSE) -> FALSE
A76: =IFERROR(NOT(ISBLANK(C76)), FALSE) -> FALSE
A77: =IFERROR(NOT(ISBLANK(C77)), FALSE) -> FALSE | B77: Cash After Expenses | D77: =$D$14-SUM($D$17:$D$76) -> 1920.8
A78: =IFERROR(NOT(ISBLANK(C78)), FALSE) -> FALSE
A79: =IFERROR(NOT(ISBLANK(C79)), FALSE) -> FALSE
A80: =IFERROR(NOT(ISBLANK(C80)), FALSE) -> FALSE | B80: Savings
A81: =IFERROR(NOT(ISBLANK(C81)), FALSE) -> FALSE | B81: Education 529s
A82: =IFERROR(NOT(ISBLANK(C82)), FALSE) -> FALSE | B82: Emergency Fund

Sheet 202510
C2: Season | D2: Summer
C4: =SUMIFS(E17:E89, D17:D89, "<=14") -> 1986.06 | D4: Expenses: 1st to 15th
C5: =SUMIFS(E17:E89, D17:D89, ">=15") -> 2165.56 | D5: Expenses: 15th to 30th
C7: Description | D7: Expected Due Date | E7: Amount | G7: Date Input? | H7: Description | I7: Expected Due Date | J7: Amount | K7: Pull into CASHFLOW
B8: =IFERROR(NOT(ISBLANK(D8)), FALSE) -> TRUE | C8: CVS Income | D8: 15 | E8: 3205.07 | G8: =NOT(ISBLANK(D8)) -> TRUE | H8: =IFERROR(__xludf.DUMMYFUNCTION("FILTER($C$8:$E$96, $G8:$G$96)"),"CVS Income") -> CVS Income | I8: =IFERROR(__xludf.DUMMYFUNCTION("""COMPUTED_VALUE"""),15) -> 15 | J8: =IFERROR(__xludf.DUMMYFUNCTION("""COMPUTED_VALUE"""),3205.07) -> 3205.07 | K8: =NOT(ISBLANK(H8)) -> TRUE
B9: =IFERROR(NOT(ISBLANK(D9)), FALSE) -> TRUE | C9: CVS Income | D9: 30 | E9: 3205.07 | G9: =NOT(ISBLANK(D9)) -> TRUE | H9: =IFERROR(__xludf.DUMMYFUNCTION("""COMPUTED_VALUE"""),"CVS Income") -> CVS Income | I9: =IFERROR(__xludf.DUMMYFUNCTION("""COMPUTED_VALUE"""),30) -> 30 | J9: =IFERROR(__xludf.DUMMYFUNCTION("""COMPUTED_VALUE"""),3205.07) -> 3205.07 | K9: =NOT(ISBLANK(H9)) -> TRUE
B10: =IFERROR(NOT(ISBLANK(D10)), FALSE) -> FALSE | C10: Apt 2 Rent | G10: =NOT(ISBLANK(D10)) -> FALSE | H10: =IFERROR(__xludf.DUMMYFUNCTION("""COMPUTED_VALUE"""),"BOA Customized Rewards") -> BOA Customized Rewards | I10: =IFERROR(__xludf.DUMMYFUNCTION("""COMPUTED_VALUE"""),9) -> 9 | K10: =NOT(ISBLANK(H10)) -> TRUE
B11: =IFERROR(NOT(ISBLANK(D11)), FALSE) -> FALSE | C11: Apt 3 Rent | G11: =NOT(ISBLANK(D11)) -> FALSE | H11: =IFERROR(__xludf.DUMMYFUNCTION("""COMPUTED_VALUE"""),"BOA Unlimited Rewards") -> BOA Unlimited Rewards | I11: =IFERROR(__xludf.DUMMYFUNCTION("""COMPUTED_VALUE"""),4) -> 4 | J11: =IFERROR(__xludf.DUMMYFUNCTION("""COMPUTED_VALUE"""),151) -> 151 | K11: =NOT(ISBLANK(H11)) -> TRUE
B12: =IFERROR(NOT(ISBLANK(D12)), FALSE) -> FALSE | C12: Uber Income | G12: =NOT(ISBLANK(D12)) -> FALSE | H12: =IFERROR(__xludf.DUMMYFUNCTION("""COMPUTED_VALUE"""),"CHASE Freedom") -> CHASE Freedom | I12: =IFERROR(__xludf.DUMMYFUNCTION("""COMPUTED_VALUE"""),15) -> 15 | K12: =NOT(ISBLANK(H12)) -> TRUE
B13: =IFERROR(NOT(ISBLANK(D13)), FALSE) -> FALSE | G13: =NOT(ISBLANK(D13)) -> FALSE | H13: =IFERROR(__xludf.DUMMYFUNCTION("""COMPUTED_VALUE"""),"CITI Diamond Preferred") -> CITI Diamond Preferred | I13: =IFERROR(__xludf.DUMMYFUNCTION("""COMPUTED_VALUE"""),15) -> 15 | J13: =IFERROR(__xludf.DUMMYFUNCTION("""COMPUTED_VALUE"""),120) -> 120 | K13: =NOT(ISBLANK(H13)) -> TRUE
B14: =IFERROR(NOT(ISBLANK(D14)), FALSE) -> FALSE | C14: Total Income | E14: =SUM(E8:E12) -> 6410.14 | G14: =NOT(ISBLANK(D14)) -> FALSE | H14: =IFERROR(__xludf.DUMMYFUNCTION("""COMPUTED_VALUE"""),"CITIZENS Clear Value") -> CITIZENS Clear Value | I14: =IFERROR(__xludf.DUMMYFUNCTION("""COMPUTED_VALUE"""),13) -> 13 | J14: =IFERROR(__xludf.DUMMYFUNCTION("""COMPUTED_VALUE"""),64) -> 64 | K14: =NOT(ISBLANK(H14)) -> TRUE
B15: =IFERROR(NOT(ISBLANK(D15)), FALSE) -> FALSE | G15: =NOT(ISBLANK(D15)) -> FALSE | H15: =IFERROR(__xludf.DUMMYFUNCTION("""COMPUTED_VALUE"""),"CITIZENS HELOC") -> CITIZENS HELOC | I15: =IFERROR(__xludf.DUMMYFUNCTION("""COMPUTED_VALUE"""),15) -> 15 | J15: =IFERROR(__xludf.DUMMYFUNCTION("""COMPUTED_VALUE"""),95.95) -> 95.95 | K15: =NOT(ISBLANK(H15)) -> TRUE
B16: =IFERROR(NOT(ISBLANK(D16)), FALSE) -> FALSE | C16: Credit Cards | G16: =NOT(ISBLANK(D16)) -> FALSE | H16: =IFERROR(__xludf.DUMMYFUNCTION("""COMPUTED_VALUE"""),"UPSTART Debt Consolidation") -> UPSTART Debt Consolidation | I16: =IFERROR(__xludf.DUMMYFUNCTION("""COMPUTED_VALUE"""),15) -> 15 | J16: =IFERROR(__xludf.DUMMYFUNCTION("""COMPUTED_VALUE"""),181.13) -> 181.13 | K16: =NOT(ISBLANK(H16)) -> TRUE
B17: =IFERROR(NOT(ISBLANK(D17)), FALSE) -> TRUE | C17: BOA Customized Rewards | D17: 9 | G17: =NOT(ISBLANK(D17)) -> TRUE | H17: =IFERROR(__xludf.DUMMYFUNCTION("""COMPUTED_VALUE"""),"AQUA FINANCE Roofing Replacement") -> AQUA FINANCE Roofing Replacement | I17: =IFERROR(__xludf.DUMMYFUNCTION("""COMPUTED_VALUE"""),6) -> 6 | J17: =IFERROR(__xludf.DUMMYFUNCTION("""COMPUTED_VALUE"""),268.44) -> 268.44 | K17: =NOT(ISBLANK(H17)) -> TRUE
C18: BOA Unlimited Rewards | D18: 4 | E18: 151 | G18: =NOT(ISBLANK(D18)) -> TRUE | H18: =IFERROR(__xludf.DUMMYFUNCTION("""COMPUTED_VALUE"""),"TD Auto Loan") -> TD Auto Loan | I18: =IFERROR(__xludf.DUMMYFUNCTION("""COMPUTED_VALUE"""),17) -> 17 | J18: =IFERROR(__xludf.DUMMYFUNCTION("""COMPUTED_VALUE"""),595) -> 595 | K18: =NOT(ISBLANK(H18)) -> TRUE
C19: CHASE Freedom | D19: 15 | G19: =NOT(ISBLANK(D19)) -> TRUE | H19: =IFERROR(__xludf.DUMMYFUNCTION("""COMPUTED_VALUE"""),"Owner Contribution to Mortgage") -> Owner Contribution to Mortgage | I19: =IFERROR(__xludf.DUMMYFUNCTION("""COMPUTED_VALUE"""),1) -> 1 | J19: =IFERROR(__xludf.DUMMYFUNCTION("""COMPUTED_VALUE"""),146.54) -> 146.54 | K19: =NOT(ISBLANK(H19)) -> TRUE
C20: CITI Diamond Preferred | D20: 15 | E20: 120 | G20: =NOT(ISBLANK(D20)) -> TRUE | H20: =IFERROR(__xludf.DUMMYFUNCTION("""COMPUTED_VALUE"""),"Landlord Electricity") -> Landlord Electricity | I20: =IFERROR(__xludf.DUMMYFUNCTION("""COMPUTED_VALUE"""),1) -> 1 | J20: =IFERROR(__xludf.DUMMYFUNCTION("""COMPUTED_VALUE"""),33.16) -> 33.16 | K20: =NOT(ISBLANK(H20)) -> TRUE
B21: =IFERROR(NOT(ISBLANK(D21)), FALSE) -> TRUE | C21: CITIZENS Clear Value | D21: 13 | E21: 64 | G21: =NOT(ISBLANK(D21)) -> TRUE | H21: =IFERROR(__xludf.DUMMYFUNCTION("""COMPUTED_VALUE"""),"Maintenance (Lawn)") -> Maintenance (Lawn) | I21: =IFERROR(__xludf.DUMMYFUNCTION("""COMPUTED_VALUE"""),10) -> 10 | J21: =IFERROR(__xludf.DUMMYFUNCTION("""COMPUTED_VALUE"""),80) -> 80 | K21: =NOT(ISBLANK(H21)) -> TRUE
B22: =IFERROR(NOT(ISBLANK(D22)), FALSE) -> FALSE | G22: =NOT(ISBLANK(D22)) -> FALSE | H22: =IFERROR(__xludf.DUMMYFUNCTION("""COMPUTED_VALUE"""),"Maintenance (Lawn)") -> Maintenance (Lawn) | I22: =IFERROR(__xludf.DUMMYFUNCTION("""COMPUTED_VALUE"""),24) -> 24 | J22: =IFERROR(__xludf.DUMMYFUNCTION("""COMPUTED_VALUE"""),80) -> 80 | K22: =NOT(ISBLANK(H22)) -> TRUE
B23: =IFERROR(NOT(ISBLANK(D23)), FALSE) -> FALSE | C23: Loan Payments | G23: =NOT(ISBLANK(D23)) -> FALSE | H23: =IFERROR(__xludf.DUMMYFUNCTION("""COMPUTED_VALUE"""),"Blink Security") -> Blink Security | I23: =IFERROR(__xludf.DUMMYFUNCTION("""COMPUTED_VALUE"""),1) -> 1 | J23: =IFERROR(__xludf.DUMMYFUNCTION("""COMPUTED_VALUE"""),10.64) -> 10.64 | K23: =NOT(ISBLANK(H23)) -> TRUE
B24: =IFERROR(NOT(ISBLANK(D24)), FALSE) -> TRUE | C24: CITIZENS HELOC | D24: 15 | E24: 95.95 | G24: =NOT(ISBLANK(D24)) -> TRUE | H24: =IFERROR(__xludf.DUMMYFUNCTION("""COMPUTED_VALUE"""),"Avail Portal") -> Avail Portal | I24: =IFERROR(__xludf.DUMMYFUNCTION("""COMPUTED_VALUE"""),1) -> 1 | J24: =IFERROR(__xludf.DUMMYFUNCTION("""COMPUTED_VALUE"""),18) -> 18 | K24: =NOT(ISBLANK(H24)) -> TRUE
C25: UPSTART Debt Consolidation | D25: 15 | E25: 181.13 | G25: =NOT(ISBLANK(D25)) -> TRUE | H25: =IFERROR(__xludf.DUMMYFUNCTION("""COMPUTED_VALUE"""),"Auto Insurance") -> Auto Insurance | I25: =IFERROR(__xludf.DUMMYFUNCTION("""COMPUTED_VALUE"""),4) -> 4 | J25: =IFERROR(__xludf.DUMMYFUNCTION("""COMPUTED_VALUE"""),353.71) -> 353.71 | K25: =NOT(ISBLANK(H25)) -> TRUE
C26: AQUA FINANCE Roofing Replacement | D26: 6 | E26: 268.44 | G26: =NOT(ISBLANK(D26)) -> TRUE | H26: =IFERROR(__xludf.DUMMYFUNCTION("""COMPUTED_VALUE"""),"Heating/Natural Gas") -> Heating/Natural Gas | I26: =IFERROR(__xludf.DUMMYFUNCTION("""COMPUTED_VALUE"""),15) -> 15 | J26: =IFERROR(__xludf.DUMMYFUNCTION("""COMPUTED_VALUE"""),175) -> 175 | K26: =NOT(ISBLANK(H26)) -> TRUE
B27: =IFERROR(NOT(ISBLANK(D27)), FALSE) -> TRUE | C27: TD Auto Loan | D27: 17 | E27: 595 | G27: =NOT(ISBLANK(D27)) -> TRUE | H27: =IFERROR(__xludf.DUMMYFUNCTION("""COMPUTED_VALUE"""),"Electricity") -> Electricity | I27: =IFERROR(__xludf.DUMMYFUNCTION("""COMPUTED_VALUE"""),1) -> 1 | J27: =IFERROR(__xludf.DUMMYFUNCTION("""COMPUTED_VALUE"""),192.43) -> 192.43 | K27: =NOT(ISBLANK(H27)) -> TRUE
B28: =IFERROR(NOT(ISBLANK(D28)), FALSE) -> FALSE | C28: NELNET Student Loans | G28: =NOT(ISBLANK(D28)) -> FALSE | H28: =IFERROR(__xludf.DUMMYFUNCTION("""COMPUTED_VALUE"""),"Internet") -> Internet | I28: =IFERROR(__xludf.DUMMYFUNCTION("""COMPUTED_VALUE"""),27) -> 27 | J28: =IFERROR(__xludf.DUMMYFUNCTION("""COMPUTED_VALUE"""),74.95) -> 74.95 | K28: =NOT(ISBLANK(H28)) -> TRUE
B29: =IFERROR(NOT(ISBLANK(D29)), FALSE) -> FALSE | G29: =NOT(ISBLANK(D29)) -> FALSE | H29: =IFERROR(__xludf.DUMMYFUNCTION("""COMPUTED_VALUE"""),"Life Insurance") -> Life Insurance | I29: =IFERROR(__xludf.DUMMYFUNCTION("""COMPUTED_VALUE"""),16) -> 16 | J29: =IFERROR(__xludf.DUMMYFUNCTION("""COMPUTED_VALUE"""),82.37) -> 82.37 | K29: =NOT(ISBLANK(H29)) -> TRUE
B30: =IFERROR(NOT(ISBLANK(D30)), FALSE) -> FALSE | C30: Propery Expenses | G30: =NOT(ISBLANK(D30)) -> FALSE | H30: =IFERROR(__xludf.DUMMYFUNCTION("""COMPUTED_VALUE"""),"Groceries + Toiletries") -> Groceries + Toiletries | I30: =IFERROR(__xludf.DUMMYFUNCTION("""COMPUTED_VALUE"""),3) -> 3 | J30: =IFERROR(__xludf.DUMMYFUNCTION("""COMPUTED_VALUE"""),250) -> 250 | K30: =NOT(ISBLANK(H30)) -> TRUE
B31: =IFERROR(NOT(ISBLANK(D31)), FALSE) -> TRUE | C31: Owner Contribution to Mortgage | D31: 1 | E31: 146.54 | G31: =NOT(ISBLANK(D31)) -> TRUE | H31: =IFERROR(__xludf.DUMMYFUNCTION("""COMPUTED_VALUE"""),"Groceries + Toiletries") -> Groceries + Toiletries | I31: =IFERROR(__xludf.DUMMYFUNCTION("""COMPUTED_VALUE"""),10) -> 10 | J31: =IFERROR(__xludf.DUMMYFUNCTION("""COMPUTED_VALUE"""),250) -> 250 | K31: =NOT(ISBLANK(H31)) -> TRUE
B32: =IFERROR(NOT(ISBLANK(D32)), FALSE) -> TRUE | C32: Landlord Electricity | D32: 1 | E32: 33.16 | G32: =NOT(ISBLANK(D32)) -> TRUE | H32: =IFERROR(__xludf.DUMMYFUNCTION("""COMPUTED_VALUE"""),"Groceries + Toiletries") -> Groceries + Toiletries | I32: =IFERROR(__xludf.DUMMYFUNCTION("""COMPUTED_VALUE"""),17) -> 17 | J32: =IFERROR(__xludf.DUMMYFUNCTION("""COMPUTED_VALUE"""),250) -> 250 | K32: =NOT(ISBLANK(H32)) -> TRUE
B33: =IFERROR(NOT(ISBLANK(D33)), FALSE) -> FALSE | C33: Water/Sewer (Monthly) | E33: 130 | G33: =NOT(ISBLANK(D33)) -> FALSE | H33: =IFERROR(__xludf.DUMMYFUNCTION("""COMPUTED_VALUE"""),"Groceries + Toiletries") -> Groceries + Toiletries | I33: =IFERROR(__xludf.DUMMYFUNCTION("""COMPUTED_VALUE"""),24) -> 24 | J33: =IFERROR(__xludf.DUMMYFUNCTION("""COMPUTED_VALUE"""),250) -> 250 | K33: =NOT(ISBLANK(H33)) -> TRUE
B34: =IFERROR(NOT(ISBLANK(D34)), FALSE) -> TRUE | C34: Maintenance (Lawn) | D34: 10 | E34: =IF($D$2="Summer", 80, 0) -> 80 | G34: =NOT(ISBLANK(D34)) -> TRUE | H34: =IFERROR(__xludf.DUMMYFUNCTION("""COMPUTED_VALUE"""),"Phone (Nykosi)") -> Phone (Nykosi) | I34: =IFERROR(__xludf.DUMMYFUNCTION("""COMPUTED_VALUE"""),16) -> 16 | J34: =IFERROR(__xludf.DUMMYFUNCTION("""COMPUTED_VALUE"""),30) -> 30 | K34: =NOT(ISBLANK(H34)) -> TRUE
B35: =IFERROR(NOT(ISBLANK(D35)), FALSE) -> TRUE | C35: Maintenance (Lawn) | D35: 24 | E35: =IF($D$2="Summer", 80, 0) -> 80 | G35: =NOT(ISBLANK(D35)) -> TRUE | H35: =IFERROR(__xludf.DUMMYFUNCTION("""COMPUTED_VALUE"""),"Phone (Brittany)") -> Phone (Brittany) | I35: =IFERROR(__xludf.DUMMYFUNCTION("""COMPUTED_VALUE"""),16) -> 16 | J35: =IFERROR(__xludf.DUMMYFUNCTION("""COMPUTED_VALUE"""),50) -> 50 | K35: =NOT(ISBLANK(H35)) -> TRUE
B36: =IFERROR(NOT(ISBLANK(D36)), FALSE) -> FALSE | C36: Maintenance (Snow Removal) | E36: =IF($D$2="Winter", 110, 0) -> 0 | G36: =NOT(ISBLANK(D36)) -> FALSE | H36: =IFERROR(__xludf.DUMMYFUNCTION("""COMPUTED_VALUE"""),"Gym Membership (Nykosi)") -> Gym Membership (Nykosi) | I36: =IFERROR(__xludf.DUMMYFUNCTION("""COMPUTED_VALUE"""),24) -> 24 | J36: =IFERROR(__xludf.DUMMYFUNCTION("""COMPUTED_VALUE"""),22.23) -> 22.23 | K36: =NOT(ISBLANK(H36)) -> TRUE
B37: =IFERROR(NOT(ISBLANK(D37)), FALSE) -> TRUE | C37: Blink Security | D37: 1 | E37: 10.64 | G37: =NOT(ISBLANK(D37)) -> TRUE | H37: =IFERROR(__xludf.DUMMYFUNCTION("""COMPUTED_VALUE"""),"Gym Membership (Brittany)") -> Gym Membership (Brittany) | I37: =IFERROR(__xludf.DUMMYFUNCTION("""COMPUTED_VALUE"""),6) -> 6 | J37: =IFERROR(__xludf.DUMMYFUNCTION("""COMPUTED_VALUE"""),32.87) -> 32.87 | K37: =NOT(ISBLANK(H37)) -> TRUE
B38: =IFERROR(NOT(ISBLANK(D38)), FALSE) -> TRUE | C38: Avail Portal | D38: 1 | E38: 18 | G38: =NOT(ISBLANK(D38)) -> TRUE | H38: =IFERROR(__xludf.DUMMYFUNCTION("""COMPUTED_VALUE"""),"Gym Trainer (Brittany)") -> Gym Trainer (Brittany) | I38: =IFERROR(__xludf.DUMMYFUNCTION("""COMPUTED_VALUE"""),14) -> 14 | J38: =IFERROR(__xludf.DUMMYFUNCTION("""COMPUTED_VALUE"""),105.29) -> 105.29 | K38: =NOT(ISBLANK(H38)) -> TRUE
B39: =IFERROR(NOT(ISBLANK(D39)), FALSE) -> FALSE | G39: =NOT(ISBLANK(D39)) -> FALSE | H39: =IFERROR(__xludf.DUMMYFUNCTION("""COMPUTED_VALUE"""),"Gym Trainer (Brittany)") -> Gym Trainer (Brittany) | I39: =IFERROR(__xludf.DUMMYFUNCTION("""COMPUTED_VALUE"""),28) -> 28 | J39: =IFERROR(__xludf.DUMMYFUNCTION("""COMPUTED_VALUE"""),105.29) -> 105.29 | K39: =NOT(ISBLANK(H39)) -> TRUE
B40: =IFERROR(NOT(ISBLANK(D40)), FALSE) -> FALSE | C40: Bills | G40: =NOT(ISBLANK(D40)) -> FALSE | H40: =IFERROR(__xludf.DUMMYFUNCTION("""COMPUTED_VALUE"""),"Amazon Prime") -> Amazon Prime | I40: =IFERROR(__xludf.DUMMYFUNCTION("""COMPUTED_VALUE"""),14) -> 14 | J40: =IFERROR(__xludf.DUMMYFUNCTION("""COMPUTED_VALUE"""),14.99) -> 14.99 | K40: =NOT(ISBLANK(H40)) -> TRUE
B41: =IFERROR(NOT(ISBLANK(D41)), FALSE) -> TRUE | C41: Auto Insurance | D41: 4 | E41: 353.71 | G41: =NOT(ISBLANK(D41)) -> TRUE | H41: =IFERROR(__xludf.DUMMYFUNCTION("""COMPUTED_VALUE"""),"Microsoft 365") -> Microsoft 365 | I41: =IFERROR(__xludf.DUMMYFUNCTION("""COMPUTED_VALUE"""),17) -> 17 | J41: =IFERROR(__xludf.DUMMYFUNCTION("""COMPUTED_VALUE"""),14.14) -> 14.14 | K41: =NOT(ISBLANK(H41)) -> TRUE
B42: =IFERROR(NOT(ISBLANK(D42)), FALSE) -> FALSE | C42: Auto Taxes (Monthly) | G42: =NOT(ISBLANK(D42)) -> FALSE | H42: =IFERROR(__xludf.DUMMYFUNCTION("""COMPUTED_VALUE"""),"Netflix") -> Netflix | I42: =IFERROR(__xludf.DUMMYFUNCTION("""COMPUTED_VALUE"""),23) -> 23 | J42: =IFERROR(__xludf.DUMMYFUNCTION("""COMPUTED_VALUE"""),19.3) -> 19.3 | K42: =NOT(ISBLANK(H42)) -> TRUE
B43: =IFERROR(NOT(ISBLANK(D43)), FALSE) -> TRUE | C43: Heating/Natural Gas | D43: 15 | E43: 175 | G43: =NOT(ISBLANK(D43)) -> TRUE | H43: =IFERROR(__xludf.DUMMYFUNCTION("""COMPUTED_VALUE"""),"YNAB ") -> YNAB | I43: =IFERROR(__xludf.DUMMYFUNCTION("""COMPUTED_VALUE"""),9) -> 9 | J43: =IFERROR(__xludf.DUMMYFUNCTION("""COMPUTED_VALUE"""),14.99) -> 14.99 | K43: =NOT(ISBLANK(H43)) -> TRUE
B44: =IFERROR(NOT(ISBLANK(D44)), FALSE) -> TRUE | C44: Electricity | D44: 1 | E44: 192.43 | G44: =NOT(ISBLANK(D44)) -> TRUE | H44: =IFERROR(__xludf.DUMMYFUNCTION("""COMPUTED_VALUE"""),"OpenAI") -> OpenAI | I44: =IFERROR(__xludf.DUMMYFUNCTION("""COMPUTED_VALUE"""),16) -> 16 | J44: =IFERROR(__xludf.DUMMYFUNCTION("""COMPUTED_VALUE"""),20.2) -> 20.2 | K44: =NOT(ISBLANK(H44)) -> TRUE
B45: =IFERROR(NOT(ISBLANK(D45)), FALSE) -> TRUE | C45: Internet | D45: 27 | E45: 74.95 | G45: =NOT(ISBLANK(D45)) -> TRUE | K45: =NOT(ISBLANK(H45)) -> FALSE
B46: =IFERROR(NOT(ISBLANK(D46)), FALSE) -> TRUE | C46: Life Insurance | D46: 16 | E46: 82.37 | G46: =NOT(ISBLANK(D46)) -> TRUE | K46: =NOT(ISBLANK(H46)) -> FALSE
B47: =IFERROR(NOT(ISBLANK(D47)), FALSE) -> FALSE | G47: =NOT(ISBLANK(D47)) -> FALSE | K47: =NOT(ISBLANK(H47)) -> FALSE
B48: =IFERROR(NOT(ISBLANK(D48)), FALSE) -> FALSE | C48: Expenses (Needs) | G48: =NOT(ISBLANK(D48)) -> FALSE | K48: =NOT(ISBLANK(H48)) -> FALSE
B49: =IFERROR(NOT(ISBLANK(D49)), FALSE) -> TRUE | C49: Groceries + Toiletries | D49: 3 | E49: 250 | G49: =NOT(ISBLANK(D49)) -> TRUE | K49: =NOT(ISBLANK(H49)) -> FALSE
B50: =IFERROR(NOT(ISBLANK(D50)), FALSE) -> TRUE | C50: Groceries + Toiletries | D50: 10 | E50: 250 | G50: =NOT(ISBLANK(D50)) -> TRUE | K50: =NOT(ISBLANK(H50)) -> FALSE
B51: =IFERROR(NOT(ISBLANK(D51)), FALSE) -> TRUE | C51: Groceries + Toiletries | D51: 17 | E51: 250 | G51: =NOT(ISBLANK(D51)) -> TRUE | K51: =NOT(ISBLANK(H51)) -> FALSE
B52: =IFERROR(NOT(ISBLANK(D52)), FALSE) -> TRUE | C52: Groceries + Toiletries | D52: 24 | E52: 250 | G52: =NOT(ISBLANK(D52)) -> TRUE | K52: =NOT(ISBLANK(H52)) -> FALSE
B53: =IFERROR(NOT(ISBLANK(D53)), FALSE) -> TRUE | C53: Phone (Nykosi) | D53: 16 | E53: 30 | G53: =NOT(ISBLANK(D53)) -> TRUE | K53: =NOT(ISBLANK(H53)) -> FALSE
B54: =IFERROR(NOT(ISBLANK(D54)), FALSE) -> TRUE | C54: Phone (Brittany) | D54: 16 | E54: 50 | G54: =NOT(ISBLANK(D54)) -> TRUE | K54: =NOT(ISBLANK(H54)) -> FALSE
B55: =IFERROR(NOT(ISBLANK(D55)), FALSE) -> FALSE | G55: =NOT(ISBLANK(D55)) -> FALSE | K55: =NOT(ISBLANK(H55)) -> FALSE
B56: =IFERROR(NOT(ISBLANK(D56)), FALSE) -> FALSE | C56: Expenses (Wants) | G56: =NOT(ISBLANK(D56)) -> FALSE | K56: =NOT(ISBLANK(H56)) -> FALSE
B57: =IFERROR(NOT(ISBLANK(D57)), FALSE) -> TRUE | C57: Gym Membership (Nykosi) | D57: 24 | E57: 22.23 | G57: =NOT(ISBLANK(D57)) -> TRUE | K57: =NOT(ISBLANK(H57)) -> FALSE
B58: =IFERROR(NOT(ISBLANK(D58)), FALSE) -> TRUE | C58: Gym Membership (Brittany) | D58: 6 | E58: 32.87 | G58: =NOT(ISBLANK(D58)) -> TRUE | K58: =NOT(ISBLANK(H58)) -> FALSE
B59: =IFERROR(NOT(ISBLANK(D59)), FALSE) -> TRUE | C59: Gym Trainer (Brittany) | D59: 14 | E59: 105.29 | G59: =NOT(ISBLANK(D59)) -> TRUE | K59: =NOT(ISBLANK(H59)) -> FALSE
B60: =IFERROR(NOT(ISBLANK(D60)), FALSE) -> TRUE | C60: Gym Trainer (Brittany) | D60: 28 | E60: 105.29 | G60: =NOT(ISBLANK(D60)) -> TRUE | K60: =NOT(ISBLANK(H60)) -> FALSE
B61: =IFERROR(NOT(ISBLANK(D61)), FALSE) -> TRUE | C61: Amazon Prime | D61: 14 | E61: 14.99 | G61: =NOT(ISBLANK(D61)) -> TRUE | K61: =NOT(ISBLANK(H61)) -> FALSE
B62: =IFERROR(NOT(ISBLANK(D62)), FALSE) -> TRUE | C62: Microsoft 365 | D62: 17 | E62: 14.14 | G62: =NOT(ISBLANK(D62)) -> TRUE | K62: =NOT(ISBLANK(H62)) -> FALSE
B63: =IFERROR(NOT(ISBLANK(D63)), FALSE) -> TRUE | C63: Netflix | D63: 23 | E63: 19.3 | G63: =NOT(ISBLANK(D63)) -> TRUE | K63: =NOT(ISBLANK(H63)) -> FALSE
B64: =IFERROR(NOT(ISBLANK(D64)), FALSE) -> TRUE | C64: YNAB | D64: 9 | E64: 14.99 | G64: =NOT(ISBLANK(D64)) -> TRUE | K64: =NOT(ISBLANK(H64)) -> FALSE
B65: =IFERROR(NOT(ISBLANK(D65)), FALSE) -> TRUE | C65: OpenAI | D65: 16 | E65: 20.2 | G65: =NOT(ISBLANK(D65)) -> TRUE | K65: =NOT(ISBLANK(H65)) -> FALSE
B66: =IFERROR(NOT(ISBLANK(D66)), FALSE) -> FALSE | G66: =NOT(ISBLANK(D66)) -> FALSE | K66: =NOT(ISBLANK(H66)) -> FALSE
B67: =IFERROR(NOT(ISBLANK(D67)), FALSE) -> FALSE | G67: =NOT(ISBLANK(D67)) -> FALSE | K67: =NOT(ISBLANK(H67)) -> FALSE
B68: =IFERROR(NOT(ISBLANK(D68)), FALSE) -> FALSE | G68: =NOT(ISBLANK(D68)) -> FALSE | K68: =NOT(ISBLANK(H68)) -> FALSE
B69: =IFERROR(NOT(ISBLANK(D69)), FALSE) -> FALSE | C69: One-Time Expenses | G69: =NOT(ISBLANK(D69)) -> FALSE | K69: =NOT(ISBLANK(H69)) -> FALSE
B70: =IFERROR(NOT(ISBLANK(D70)), FALSE) -> FALSE | G70: =NOT(ISBLANK(D70)) -> FALSE | K70: =NOT(ISBLANK(H70)) -> FALSE
B71: =IFERROR(NOT(ISBLANK(D71)), FALSE) -> FALSE | G71: =NOT(ISBLANK(D71)) -> FALSE | K71: =NOT(ISBLANK(H71)) -> FALSE
B72: =IFERROR(NOT(ISBLANK(D72)), FALSE) -> FALSE | G72: =NOT(ISBLANK(D72)) -> FALSE | K72: =NOT(ISBLANK(H72)) -> FALSE
B73: =IFERROR(NOT(ISBLANK(D73)), FALSE) -> FALSE | G73: =NOT(ISBLANK(D73)) -> FALSE | K73: =NOT(ISBLANK(H73)) -> FALSE
B74: =IFERROR(NOT(ISBLANK(D74)), FALSE) -> FALSE | G74: =NOT(ISBLANK(D74)) -> FALSE | K74: =NOT(ISBLANK(H74)) -> FALSE
B75: =IFERROR(NOT(ISBLANK(D75)), FALSE) -> FALSE | C75: Cash After Expenses | E75: =$E$14-SUM($E$17:$E$74) -> 2128.52 | G75: =NOT(ISBLANK(D75)) -> FALSE | K75: =NOT(ISBLANK(H75)) -> FALSE
B76: =IFERROR(NOT(ISBLANK(D76)), FALSE) -> FALSE | G76: =NOT(ISBLANK(D76)) -> FALSE | K76: =NOT(ISBLANK(H76)) -> FALSE
B77: =IFERROR(NOT(ISBLANK(D77)), FALSE) -> FALSE | G77: =NOT(ISBLANK(D77)) -> FALSE | K77: =NOT(ISBLANK(H77)) -> FALSE
B78: =IFERROR(NOT(ISBLANK(D78)), FALSE) -> FALSE | C78: Savings | G78: =NOT(ISBLANK(D78)) -> FALSE | K78: =NOT(ISBLANK(H78)) -> FALSE
B79: =IFERROR(NOT(ISBLANK(D79)), FALSE) -> FALSE | C79: Education 529s | G79: =NOT(ISBLANK(D79)) -> FALSE | K79: =NOT(ISBLANK(H79)) -> FALSE
B80: =IFERROR(NOT(ISBLANK(D80)), FALSE) -> FALSE | C80: Emergency Fund | G80: =NOT(ISBLANK(D80)) -> FALSE | K80: =NOT(ISBLANK(H80)) -> FALSE
G81: =NOT(ISBLANK(D81)) -> FALSE | K81: =NOT(ISBLANK(H81)) -> FALSE
G82: =NOT(ISBLANK(D82)) -> FALSE | K82: =NOT(ISBLANK(H82)) -> FALSE
G83: =NOT(ISBLANK(D83)) -> FALSE | K83: =NOT(ISBLANK(H83)) -> FALSE
G84: =NOT(ISBLANK(D84)) -> FALSE | K84: =NOT(ISBLANK(H84)) -> FALSE
G85: =NOT(ISBLANK(D85)) -> FALSE | K85: =NOT(ISBLANK(H85)) -> FALSE
G86: =NOT(ISBLANK(D86)) -> FALSE | K86: =NOT(ISBLANK(H86)) -> FALSE
G87: =NOT(ISBLANK(D87)) -> FALSE | K87: =NOT(ISBLANK(H87)) -> FALSE
G88: =NOT(ISBLANK(D88)) -> FALSE | K88: =NOT(ISBLANK(H88)) -> FALSE
G89: =NOT(ISBLANK(D89)) -> FALSE | K89: =NOT(ISBLANK(H89)) -> FALSE
G90: =NOT(ISBLANK(D90)) -> FALSE | K90: =NOT(ISBLANK(H90)) -> FALSE
G91: =NOT(ISBLANK(D91)) -> FALSE | K91: =NOT(ISBLANK(H91)) -> FALSE
G92: =NOT(ISBLANK(D92)) -> FALSE | K92: =NOT(ISBLANK(H92)) -> FALSE
... G96: =NOT(ISBLANK(D96)) -> FALSE | K96: =NOT(ISBLANK(H96)) -> FALSE

Sheet Cashflow
C2: Month | D2: 10
C3: Year | D3: 2025
C4: Sheet Name | D4: =D3&TEXT(D2, "00") -> 202510
C5: Starting Bank Balance | D5: 984.73 | K5: Currently In MONTHLY RECURRING transfers
K6: Auto Insurance | L6: 4 | M6: 353.71
K7: Heating/Natural Gas | L7: 15 | M7: 175
K8: CITI Diamond Preferred | L8: 15 | M8: 120
K9: UPSTART Debt Consolidation | L9: 15 | M9: 181.13
K10: Life Insurance | L10: 15 | M10: 82.37
K11: Electricity | L11: 18 | M11: 102.03
K12: TD Auto Loan | L12: 21 | M12: 595.68
K13: Internet | L13: 27 | M13: 74.95
K14: Currently In OTHER transfers
K15: Owner Contribution to Mortgage | L15: 1 | M15: 146.54
K16: Blink Security | L16: 5 | M16: 10.64
K17: Avail Portal | L17: 16 | M17: 18
K18: Landlord Electricity | L18: 18 | M18: 33.16
K19: CITIZENS HELOC | L19: 15 | M19: 95.95
B23: Paid? | C23: Description | D23: Expected Due Date | E23: Amount | F23: Adjusted Amount | G23: Adjusted Due Date | H23: Cummulative | K23: Debt Payoff Tracker
B24: TRUE | C24: Owner Contribution to Mortgage | D24: 1 | E24: 146.54 | F24: =IF($B24=TRUE, 0, IF(ISERROR(MATCH(C24, INDIRECT("'"&$D$4&"'!$B$8:$B$12"), 0)), -1*E24,E24)) -> 0 | G24: =DATE(2025, $D$2, $D24) -> 45931 | H24: =$D$5+F24 -> 984.73 | K24: Debt Payment | L24: Debt Balance | M24: Interest Rate
B25: TRUE | C25: Auto Insurance | D25: 1 | E25: 353.71 | F25: =IF($B25=TRUE, 0, IF(ISERROR(MATCH(C25, INDIRECT("'"&$D$4&"'!$B$8:$B$12"), 0)), -1*E25,E25)) -> 0 | G25: =DATE(2025, $D$2, $D25) -> 45931 | H25: =H24+F25 -> 984.73 | K25: BOA Customized Rewards | L25: 7700 | M25: 0.2124
B26: TRUE | C26: Groceries + Toiletries | D26: 3 | E26: 230.63 | F26: =IF($B26=TRUE, 0, IF(ISERROR(MATCH(C26, INDIRECT("'"&$D$4&"'!$B$8:$B$12"), 0)), -1*E26,E26)) -> 0 | G26: =DATE(2025, $D$2, $D26) -> 45933 | H26: =H25+F26 -> 984.73 | J26: FALSE | K26: 1000 | L26: =L25-K26 -> 6700
B27: TRUE | C27: BOA Unlimited Rewards | D27: 4 | E27: 0 | F27: =IF($B27=TRUE, 0, IF(ISERROR(MATCH(C27, INDIRECT("'"&$D$4&"'!$B$8:$B$12"), 0)), -1*E27,E27)) -> 0 | G27: =DATE(2025, $D$2, $D27) -> 45934 | H27: =H26+F27 -> 984.73 | J27: FALSE | K27: 1000 | L27: =L26-K27 -> 5700
B28: TRUE | C28: Blink Security | D28: 1 | E28: 10.64 | F28: =IF($B28=TRUE, 0, IF(ISERROR(MATCH(C28, INDIRECT("'"&$D$4&"'!$B$8:$B$12"), 0)), -1*E28,E28)) -> 0 | G28: =DATE(2025, $D$2, $D28) -> 45931 | H28: =H27+F28 -> 984.73 | J28: FALSE | K28: 1000 | L28: =L27-K28 -> 4700
B29: TRUE | C29: Gym Membership (Brittany) | D29: 6 | E29: 32.87 | F29: =IF($B29=TRUE, 0, IF(ISERROR(MATCH(C29, INDIRECT("'"&$D$4&"'!$B$8:$B$12"), 0)), -1*E29,E29)) -> 0 | G29: =DATE(2025, $D$2, $D29) -> 45936 | H29: =H28+F29 -> 984.73 | J29: FALSE | K29: 1000 | L29: =L28-K29 -> 3700
B30: TRUE | C30: BOA Customized Rewards | D30: 9 | F30: =IF($B30=TRUE, 0, IF(ISERROR(MATCH(C30, INDIRECT("'"&$D$4&"'!$B$8:$B$12"), 0)), -1*E30,E30)) -> 0 | G30: =DATE(2025, $D$2, $D30) -> 45939 | H30: =H29+F30 -> 984.73 | J30: FALSE | K30: 1000 | L30: =L29-K30 -> 2700
B31: TRUE | C31: YNAB | D31: 9 | E31: 14.99 | F31: =IF($B31=TRUE, 0, IF(ISERROR(MATCH(C31, INDIRECT("'"&$D$4&"'!$B$8:$B$12"), 0)), -1*E31,E31)) -> 0 | G31: =DATE(2025, $D$2, $D31) -> 45939 | H31: =H30+F31 -> 984.73 | K31: CITIZENS Clear Value | L31: 6246.15 | M31: 0 | N31: 0% APR ends MAR 2026
B32: TRUE | C32: Maintenance (Lawn) | D32: 10 | E32: 80 | F32: =IF($B32=TRUE, 0, IF(ISERROR(MATCH(C32, INDIRECT("'"&$D$4&"'!$B$8:$B$12"), 0)), -1*E32,E32)) -> 0 | G32: =DATE(2025, $D$2, $D32) -> 45940 | H32: =H31+F32 -> 984.73 | J32: FALSE | K32: 1000 | L32: =L31-K32 -> 5246.15
B33: TRUE | C33: Groceries + Toiletries | D33: 10 | E33: 267.65 | F33: =IF($B33=TRUE, 0, IF(ISERROR(MATCH(C33, INDIRECT("'"&$D$4&"'!$B$8:$B$12"), 0)), -1*E33,E33)) -> 0 | G33: =DATE(2025, $D$2, $D33) -> 45940 | H33: =H32+F33 -> 984.73 | J33: FALSE | K33: 1000 | L33: =L32-K33 -> 4246.15
B34: TRUE | C34: AQUA FINANCE Roofing Replacement | D34: 11 | E34: =268.44 -> 268.44 | F34: =IF($B34=TRUE, 0, IF(ISERROR(MATCH(C34, INDIRECT("'"&$D$4&"'!$B$8:$B$12"), 0)), -1*E34,E34)) -> 0 | G34: =DATE(2025, $D$2, $D34) -> 45941 | H34: =H33+F34 -> 984.73 | J34: FALSE | K34: 1000 | L34: =L33-K34 -> 3246.15
B35: TRUE | C35: CITIZENS Clear Value | D35: 13 | E35: 62 | F35: =IF($B35=TRUE, 0, IF(ISERROR(MATCH(C35, INDIRECT("'"&$D$4&"'!$B$8:$B$12"), 0)), -1*E35,E35)) -> 0 | G35: =DATE(2025, $D$2, $D35) -> 45943 | H35: =H34+F35 -> 984.73 | J35: FALSE | K35: 1000 | L35: =L34-K35 -> 2246.15
B36: TRUE | C36: Gym Trainer (Brittany) | D36: 14 | E36: 105.29 | F36: =IF($B36=TRUE, 0, IF(ISERROR(MATCH(C36, INDIRECT("'"&$D$4&"'!$B$8:$B$12"), 0)), -1*E36,E36)) -> 0 | G36: =DATE(2025, $D$2, $D36) -> 45944 | H36: =H35+F36 -> 984.73 | J36: FALSE | K36: 1000 | L36: =L35-K36 -> 1246.15
B37: TRUE | C37: Amazon Prime | D37: 14 | E37: 14.99 | F37: =IF($B37=TRUE, 0, IF(ISERROR(MATCH(C37, INDIRECT("'"&$D$4&"'!$B$8:$B$12"), 0)), -1*E37,E37)) -> 0 | G37: =DATE(2025, $D$2, $D37) -> 45944 | H37: =H36+F37 -> 984.73 | K37: 1000 | L37: =L36-K37 -> 246.15
B38: TRUE | C38: CVS Income | D38: 15 | E38: -3205.07 | F38: =IF($B38=TRUE, 0, IF(ISERROR(MATCH(C38, INDIRECT("'"&$D$4&"'!$B$8:$B$12"), 0)), -1*E38,E38)) -> 0 | G38: =DATE(2025, $D$2, $D38) -> 45945 | H38: =H37+F38 -> 984.73 | K38: =L37 -> 246.15 | L38: =L37-K38 -> 0
B39: TRUE | C39: CITI Diamond Preferred | D39: 15 | E39: 120 | F39: =IF($B39=TRUE, 0, IF(ISERROR(MATCH(C39, INDIRECT("'"&$D$4&"'!$B$8:$B$12"), 0)), -1*E39,E39)) -> 0 | G39: =DATE(2025, $D$2, $D39) -> 45945 | H39: =H38+F39 -> 984.73 | K39: CITI Diamond Preferred | L39: 11685.1 | M39: 0 | N39: 0% APR ends SEP 2026
B40: TRUE | C40: UPSTART Debt Consolidation | D40: 15 | E40: 181.13 | F40: =IF($B40=TRUE, 0, IF(ISERROR(MATCH(C40, INDIRECT("'"&$D$4&"'!$B$8:$B$12"), 0)), -1*E40,E40)) -> 0 | G40: =DATE(2025, $D$2, $D40) -> 45945 | H40: =H39+F40 -> 984.73 | J40: FALSE | K40: 1000 | L40: =L39-K40 -> 10685.1
B41: TRUE | C41: Heating/Natural Gas | D41: 15 | E41: 175 | F41: =IF($B41=TRUE, 0, IF(ISERROR(MATCH(C41, INDIRECT("'"&$D$4&"'!$B$8:$B$12"), 0)), -1*E41,E41)) -> 0 | G41: =DATE(2025, $D$2, $D41) -> 45945 | H41: =H40+F41 -> 984.73 | J41: FALSE | K41: 1000 | L41: =L40-K41 -> 9685.1
B42: TRUE | C42: Electricity | D42: 15 | E42: 102.03 | F42: =IF($B42=TRUE, 0, IF(ISERROR(MATCH(C42, INDIRECT("'"&$D$4&"'!$B$8:$B$12"), 0)), -1*E42,E42)) -> 0 | G42: =DATE(2025, $D$2, $D42) -> 45945 | H42: =H41+F42 -> 984.73 | J42: FALSE | K42: 1000 | L42: =L41-K42 -> 8685.1
B43: FALSE | C43: Landlord Electricity | D43: 15 | E43: 33.16 | F43: =IF($B43=TRUE, 0, IF(ISERROR(MATCH(C43, INDIRECT("'"&$D$4&"'!$B$8:$B$12"), 0)), -1*E43,E43)) -> -33.16 | G43: =DATE(2025, $D$2, $D43) -> 45945 | H43: =H42+F43 -> 951.57 | J43: FALSE | K43: 1000 | L43: =L42-K43 -> 7685.1
B44: TRUE | C44: CITIZENS HELOC | D44: 1 | E44: 380 | F44: =IF($B44=TRUE, 0, IF(ISERROR(MATCH(C44, INDIRECT("'"&$D$4&"'!$B$8:$B$12"), 0)), -1*E44,E44)) -> 0 | G44: =DATE(2025, $D$2, $D44) -> 45931 | H44: =H43+F44 -> 951.57 | J44: FALSE | K44: 1000 | L44: =L43-K44 -> 6685.1
B45: TRUE | C45: Internet | D45: 15 | E45: 74.95 | F45: =IF($B45=TRUE, 0, IF(ISERROR(MATCH(C45, INDIRECT("'"&$D$4&"'!$B$8:$B$12"), 0)), -1*E45,E45)) -> 0 | G45: =DATE(2025, $D$2, $D45) -> 45945 | H45: =H44+F45 -> 951.57 | J45: FALSE | K45: 1000 | L45: =L44-K45 -> 5685.1
B46: TRUE | C46: Mom Loan | D46: 15 | E46: 500 | F46: =IF($B46=TRUE, 0, IF(ISERROR(MATCH(C46, INDIRECT("'"&$D$4&"'!$B$8:$B$12"), 0)), -1*E46,E46)) -> 0 | G46: =DATE(2025, $D$2, $D46) -> 45945 | H46: =H45+F46 -> 951.57 | K46: UPSTART Debt Consolidation | L46: 3877.83 | M46: 0.1888
B47: TRUE | C47: Avail Portal | D47: 15 | E47: 18 | F47: =IF($B47=TRUE, 0, IF(ISERROR(MATCH(C47, INDIRECT("'"&$D$4&"'!$B$8:$B$12"), 0)), -1*E47,E47)) -> 0 | G47: =DATE(2025, $D$2, $D47) -> 45945 | H47: =H46+F47 -> 951.57 | J47: FALSE | K47: 1000 | L47: =L46-K47 -> 2877.83
B48: TRUE | C48: Life Insurance | D48: 15 | E48: 82.37 | F48: =IF($B48=TRUE, 0, IF(ISERROR(MATCH(C48, INDIRECT("'"&$D$4&"'!$B$8:$B$12"), 0)), -1*E48,E48)) -> 0 | G48: =DATE(2025, $D$2, $D48) -> 45945 | H48: =H47+F48 -> 951.57 | J48: FALSE | K48: 1000 | L48: =L47-K48 -> 1877.83
B49: TRUE | C49: TD Auto Loan | D49: 15 | E49: 595 | F49: =IF($B49=TRUE, 0, IF(ISERROR(MATCH(C49, INDIRECT("'"&$D$4&"'!$B$8:$B$12"), 0)), -1*E49,E49)) -> 0 | G49: =DATE(2025, $D$2, $D49) -> 45945 | H49: =H48+F49 -> 951.57 | J49: FALSE | K49: 1000 | L49: =L48-K49 -> 877.83
B50: FALSE | C50: Phone (Nykosi) | D50: 16 | E50: 30 | F50: =IF($B50=TRUE, 0, IF(ISERROR(MATCH(C50, INDIRECT("'"&$D$4&"'!$B$8:$B$12"), 0)), -1*E50,E50)) -> -30 | G50: =DATE(2025, $D$2, $D50) -> 45946 | H50: =H49+F50 -> 921.57 | J50: FALSE | K50: 877.83 | L50: =L49-K50 -> 0
B51: FALSE | C51: Phone (Brittany) | D51: 16 | E51: 50 | F51: =IF($B51=TRUE, 0, IF(ISERROR(MATCH(C51, INDIRECT("'"&$D$4&"'!$B$8:$B$12"), 0)), -1*E51,E51)) -> -50 | G51: =DATE(2025, $D$2, $D51) -> 45946 | H51: =H50+F51 -> 871.57
B52: FALSE | C52: OpenAI | D52: 16 | E52: 20.2 | F52: =IF($B52=TRUE, 0, IF(ISERROR(MATCH(C52, INDIRECT("'"&$D$4&"'!$B$8:$B$12"), 0)), -1*E52,E52)) -> -20.2 | G52: =DATE(2025, $D$2, $D52) -> 45946 | H52: =H51+F52 -> 851.37
B53: TRUE | C53: Microsoft 365 | D53: 17 | E53: 14.14 | F53: =IF($B53=TRUE, 0, IF(ISERROR(MATCH(C53, INDIRECT("'"&$D$4&"'!$B$8:$B$12"), 0)), -1*E53,E53)) -> 0 | G53: =DATE(2025, $D$2, $D53) -> 45947 | H53: =H52+F53 -> 851.37
B54: FALSE | C54: Groceries + Toiletries | D54: 17 | E54: 250 | F54: =IF($B54=TRUE, 0, IF(ISERROR(MATCH(C54, INDIRECT("'"&$D$4&"'!$B$8:$B$12"), 0)), -1*E54,E54)) -> -250 | G54: =DATE(2025, $D$2, $D54) -> 45947 | H54: =H53+F54 -> 601.37
B55: FALSE | C55: Netflix | D55: 23 | E55: 19.3 | F55: =IF($B55=TRUE, 0, IF(ISERROR(MATCH(C55, INDIRECT("'"&$D$4&"'!$B$8:$B$12"), 0)), -1*E55,E55)) -> -19.3 | G55: =DATE(2025, $D$2, $D55) -> 45953 | H55: =H54+F55 -> 582.07
B56: FALSE | C56: Maintenance (Lawn) | D56: 24 | E56: 80 | F56: =IF($B56=TRUE, 0, IF(ISERROR(MATCH(C56, INDIRECT("'"&$D$4&"'!$B$8:$B$12"), 0)), -1*E56,E56)) -> -80 | G56: =DATE(2025, $D$2, $D56) -> 45954 | H56: =H55+F56 -> 502.07
B57: FALSE | C57: Gym Membership (Nykosi) | D57: 24 | E57: 22.23 | F57: =IF($B57=TRUE, 0, IF(ISERROR(MATCH(C57, INDIRECT("'"&$D$4&"'!$B$8:$B$12"), 0)), -1*E57,E57)) -> -22.23 | G57: =DATE(2025, $D$2, $D57) -> 45954 | H57: =H56+F57 -> 479.84
B58: FALSE | C58: Groceries + Toiletries | D58: 24 | E58: 250 | F58: =IF($B58=TRUE, 0, IF(ISERROR(MATCH(C58, INDIRECT("'"&$D$4&"'!$B$8:$B$12"), 0)), -1*E58,E58)) -> -250 | G58: =DATE(2025, $D$2, $D58) -> 45954 | H58: =H57+F58 -> 229.84
B59: FALSE | C59: Gym Trainer (Brittany) | D59: 28 | E59: 105.29 | F59: =IF($B59=TRUE, 0, IF(ISERROR(MATCH(C59, INDIRECT("'"&$D$4&"'!$B$8:$B$12"), 0)), -1*E59,E59)) -> -105.29 | G59: =DATE(2025, $D$2, $D59) -> 45958 | H59: =H58+F59 -> 124.55
B60: FALSE | C60: CVS Income | D60: 31 | E60: -3205.07 | F60: =IF($B60=TRUE, 0, IF(ISERROR(MATCH(C60, INDIRECT("'"&$D$4&"'!$B$8:$B$12"), 0)), -1*E60,E60)) -> 3205.07 | G60: =DATE(2025, $D$2, $D60) -> 45961 | H60: =H59+F60 -> 3329.62
B61: FALSE | C61: NB Water Bill | D61: 31 | E61: 795.49 | F61: =IF($B61=TRUE, 0, IF(ISERROR(MATCH(C61, INDIRECT("'"&$D$4&"'!$B$8:$B$12"), 0)), -1*E61,E61)) -> -795.49 | G61: =DATE(2025, $D$2, $D61) -> 45961 | H61: =H60+F61 -> 2534.13
B62: FALSE | C62: Wife Fall Clothes | D62: 31 | E62: 500 | F62: =IF($B62=TRUE, 0, IF(ISERROR(MATCH(C62, INDIRECT("'"&$D$4&"'!$B$8:$B$12"), 0)), -1*E62,E62)) -> -500 | G62: =DATE(2025, $D$2, $D62) -> 45961 | H62: =H61+F62 -> 2034.13
... B64: FALSE | C64: Jeremiah Fall Clothes | D64: 31 | E64: 200 | F64: =IF($B64=TRUE, 0, IF(ISERROR(MATCH(C64, INDIRECT("'"&$D$4&"'!$B$8:$B$12"), 0)), -1*E64,E64)) -> -200 | G64: =DATE(2025, $D$2, $D64) -> 45961 | H64: =H63+F64 -> 1534.13

Sheet Cashflow NOV
C2: Month | D2: 11
C3: Year | D3: 2025
C4: Sheet Name | D4: =D3&TEXT(D2, "00") -> 202511
C5: Starting Bank Balance | D5: 1534.13 | K5: Currently In MONTHLY RECURRING transfers
K6: Auto Insurance | L6: 4 | M6: 353.71
K7: Heating/Natural Gas | L7: 15 | M7: 175
K8: CITI Diamond Preferred | L8: 15 | M8: 120
K9: UPSTART Debt Consolidation | L9: 15 | M9: 181.13
K10: Life Insurance | L10: 15 | M10: 82.37
K11: Electricity | L11: 18 | M11: 102.03
K12: TD Auto Loan | L12: 21 | M12: 595.68
K13: Internet | L13: 27 | M13: 74.95
K14: Currently In OTHER transfers
K15: Owner Contribution to Mortgage | L15: 1 | M15: 146.54
K16: Blink Security | L16: 5 | M16: 10.64
K17: Avail Portal | L17: 16 | M17: 18
K18: Landlord Electricity | L18: 18 | M18: 33.16
K19: CITIZENS HELOC | L19: 15 | M19: 95.95
B23: Paid? | C23: Description | D23: Expected Due Date | E23: Amount | F23: Adjusted Amount | G23: Adjusted Due Date | H23: Cummulative | K23: Debt Payoff Tracker
B24: FALSE | C24: Owner Contribution to Mortgage | D24: 1 | E24: 146.54 | F24: =IF($B24=TRUE, 0, IF(ISERROR(MATCH(C24, INDIRECT("'"&$D$4&"'!$B$8:$B$12"), 0)), -1*E24,E24)) -> -146.54 | G24: =DATE(2025, $D$2, $D24) -> 45962 | H24: =$D$5+F24 -> 1387.59 | K24: Debt Payment | L24: Debt Balance | M24: Interest Rate
B25: FALSE | C25: Blink Security | D25: 1 | E25: 10.64 | F25: =IF($B25=TRUE, 0, IF(ISERROR(MATCH(C25, INDIRECT("'"&$D$4&"'!$B$8:$B$12"), 0)), -1*E25,E25)) -> -10.64 | G25: =DATE(2025, $D$2, $D25) -> 45962 | H25: =H24+F25 -> 1376.95 | K25: BOA Customized Rewards | L25: 7700 | M25: 0.2124
B26: FALSE | C26: Landlord Electricity | D26: 1 | E26: 33.16 | F26: =IF($B26=TRUE, 0, IF(ISERROR(MATCH(C26, INDIRECT("'"&$D$4&"'!$B$8:$B$12"), 0)), -1*E26,E26)) -> -33.16 | G26: =DATE(2025, $D$2, $D26) -> 45962 | H26: =H25+F26 -> 1343.79 | J26: FALSE | K26: 1000 | L26: =L25-K26 -> 6700
B27: FALSE | C27: Avail Portal | D27: 1 | E27: 18 | F27: =IF($B27=TRUE, 0, IF(ISERROR(MATCH(C27, INDIRECT("'"&$D$4&"'!$B$8:$B$12"), 0)), -1*E27,E27)) -> -18 | G27: =DATE(2025, $D$2, $D27) -> 45962 | H27: =H26+F27 -> 1325.79 | J27: FALSE | K27: 1000 | L27: =L26-K27 -> 5700
B28: FALSE | C28: Auto Insurance | D28: 1 | E28: 353.71 | F28: =IF($B28=TRUE, 0, IF(ISERROR(MATCH(C28, INDIRECT("'"&$D$4&"'!$B$8:$B$12"), 0)), -1*E28,E28)) -> -353.71 | G28: =DATE(2025, $D$2, $D28) -> 45962 | H28: =H27+F28 -> 972.08 | J28: FALSE | K28: 1000 | L28: =L27-K28 -> 4700
B29: FALSE | C29: AQUA FINANCE Roofing Replacement | D29: 1 | E29: =268.44 -> 268.44 | F29: =IF($B29=TRUE, 0, IF(ISERROR(MATCH(C29, INDIRECT("'"&$D$4&"'!$B$8:$B$12"), 0)), -1*E29,E29)) -> -268.44 | G29: =DATE(2025, $D$2, $D29) -> 45962 | H29: =H28+F29 -> 703.64 | J29: FALSE | K29: 1000 | L29: =L28-K29 -> 3700
B30: FALSE | C30: BOA Unlimited Rewards | D30: 4 | E30: 0 | F30: =IF($B30=TRUE, 0, IF(ISERROR(MATCH(C30, INDIRECT("'"&$D$4&"'!$B$8:$B$12"), 0)), -1*E30,E30)) -> 0 | G30: =DATE(2025, $D$2, $D30) -> 45965 | H30: =H29+F30 -> 703.64 | J30: FALSE | K30: 1000 | L30: =L29-K30 -> 2700
B31: FALSE | C31: Gym Membership (Brittany) | D31: 6 | E31: 32.87 | F31: =IF($B31=TRUE, 0, IF(ISERROR(MATCH(C31, INDIRECT("'"&$D$4&"'!$B$8:$B$12"), 0)), -1*E31,E31)) -> -32.87 | G31: =DATE(2025, $D$2, $D31) -> 45967 | H31: =H30+F31 -> 670.77 | K31: CITIZENS Clear Value | L31: 6246.15 | M31: 0 | N31: 0% APR ends MAR 2026
B32: FALSE | C32: Groceries + Toiletries | D32: 7 | E32: 250 | F32: =IF($B32=TRUE, 0, IF(ISERROR(MATCH(C32, INDIRECT("'"&$D$4&"'!$B$8:$B$12"), 0)), -1*E32,E32)) -> -250 | G32: =DATE(2025, $D$2, $D32) -> 45968 | H32: =H31+F32 -> 420.77 | J32: FALSE | K32: 1000 | L32: =L31-K32 -> 5246.15
B33: FALSE | C33: Maintenance (Lawn) | D33: 10 | E33: 80 | F33: =IF($B33=TRUE, 0, IF(ISERROR(MATCH(C33, INDIRECT("'"&$D$4&"'!$B$8:$B$12"), 0)), -1*E33,E33)) -> -80 | G33: =DATE(2025, $D$2, $D33) -> 45971 | H33: =H32+F33 -> 340.77 | J33: FALSE | K33: 1000 | L33: =L32-K33 -> 4246.15
B34: FALSE | C34: CITIZENS Clear Value | D34: 13 | E34: 62 | F34: =IF($B34=TRUE, 0, IF(ISERROR(MATCH(C34, INDIRECT("'"&$D$4&"'!$B$8:$B$12"), 0)), -1*E34,E34)) -> -62 | G34: =DATE(2025, $D$2, $D34) -> 45974 | H34: =H33+F34 -> 278.77 | J34: FALSE | K34: 1000 | L34: =L33-K34 -> 3246.15
B35: FALSE | C35: CVS Income | D35: 14 | E35: -3205.07 | F35: =IF($B35=TRUE, 0, IF(ISERROR(MATCH(C35, INDIRECT("'"&$D$4&"'!$B$8:$B$12"), 0)), -1*E35,E35)) -> 3205.07 | G35: =DATE(2025, $D$2, $D35) -> 45975 | H35: =H34+F35 -> 3483.84 | J35: FALSE | K35: 1000 | L35: =L34-K35 -> 2246.15
B36: FALSE | C36: Groceries + Toiletries | D36: 14 | E36: 0 | F36: =IF($B36=TRUE, 0, IF(ISERROR(MATCH(C36, INDIRECT("'"&$D$4&"'!$B$8:$B$12"), 0)), -1*E36,E36)) -> 0 | G36: =DATE(2025, $D$2, $D36) -> 45975 | H36: =H35+F36 -> 3483.84 | J36: FALSE | K36: 1000 | L36: =L35-K36 -> 1246.15
B37: FALSE | C37: Gym Trainer (Brittany) | D37: 14 | E37: 105.29 | F37: =IF($B37=TRUE, 0, IF(ISERROR(MATCH(C37, INDIRECT("'"&$D$4&"'!$B$8:$B$12"), 0)), -1*E37,E37)) -> -105.29 | G37: =DATE(2025, $D$2, $D37) -> 45975 | H37: =H36+F37 -> 3378.55 | K37: 1000 | L37: =L36-K37 -> 246.15
B38: FALSE | C38: Amazon Prime | D38: 14 | E38: 14.99 | F38: =IF($B38=TRUE, 0, IF(ISERROR(MATCH(C38, INDIRECT("'"&$D$4&"'!$B$8:$B$12"), 0)), -1*E38,E38)) -> -14.99 | G38: =DATE(2025, $D$2, $D38) -> 45975 | H38: =H37+F38 -> 3363.56 | K38: =L37 -> 246.15 | L38: =L37-K38 -> 0
B39: FALSE | C39: CITI Diamond Preferred | D39: 14 | E39: 120 | F39: =IF($B39=TRUE, 0, IF(ISERROR(MATCH(C39, INDIRECT("'"&$D$4&"'!$B$8:$B$12"), 0)), -1*E39,E39)) -> -120 | G39: =DATE(2025, $D$2, $D39) -> 45975 | H39: =H38+F39 -> 3243.56 | K39: CITI Diamond Preferred | L39: 11685.1 | M39: 0 | N39: 0% APR ends SEP 2026
B40: FALSE | C40: UPSTART Debt Consolidation | D40: 14 | E40: 181.13 | F40: =IF($B40=TRUE, 0, IF(ISERROR(MATCH(C40, INDIRECT("'"&$D$4&"'!$B$8:$B$12"), 0)), -1*E40,E40)) -> -181.13 | G40: =DATE(2025, $D$2, $D40) -> 45975 | H40: =H39+F40 -> 3062.43 | J40: FALSE | K40: 1000 | L40: =L39-K40 -> 10685.1
B41: FALSE | C41: Heating/Natural Gas | D41: 14 | E41: 175 | F41: =IF($B41=TRUE, 0, IF(ISERROR(MATCH(C41, INDIRECT("'"&$D$4&"'!$B$8:$B$12"), 0)), -1*E41,E41)) -> -175 | G41: =DATE(2025, $D$2, $D41) -> 45975 | H41: =H40+F41 -> 2887.43 | J41: FALSE | K41: 1000 | L41: =L40-K41 -> 9685.1
B42: FALSE | C42: Electricity | D42: 14 | E42: 102.03 | F42: =IF($B42=TRUE, 0, IF(ISERROR(MATCH(C42, INDIRECT("'"&$D$4&"'!$B$8:$B$12"), 0)), -1*E42,E42)) -> -102.03 | G42: =DATE(2025, $D$2, $D42) -> 45975 | H42: =H41+F42 -> 2785.4 | J42: FALSE | K42: 1000 | L42: =L41-K42 -> 8685.1
B43: FALSE | C43: CITIZENS HELOC | D43: 14 | E43: 95.95 | F43: =IF($B43=TRUE, 0, IF(ISERROR(MATCH(C43, INDIRECT("'"&$D$4&"'!$B$8:$B$12"), 0)), -1*E43,E43)) -> -95.95 | G43: =DATE(2025, $D$2, $D43) -> 45975 | H43: =H42+F43 -> 2689.45 | J43: FALSE | K43: 1000 | L43: =L42-K43 -> 7685.1
B44: FALSE | C44: Internet | D44: 14 | E44: 74.95 | F44: =IF($B44=TRUE, 0, IF(ISERROR(MATCH(C44, INDIRECT("'"&$D$4&"'!$B$8:$B$12"), 0)), -1*E44,E44)) -> -74.95 | G44: =DATE(2025, $D$2, $D44) -> 45975 | H44: =H43+F44 -> 2614.5 | J44: FALSE | K44: 1000 | L44: =L43-K44 -> 6685.1
B45: FALSE | C45: Life Insurance | D45: 14 | E45: 82.37 | F45: =IF($B45=TRUE, 0, IF(ISERROR(MATCH(C45, INDIRECT("'"&$D$4&"'!$B$8:$B$12"), 0)), -1*E45,E45)) -> -82.37 | G45: =DATE(2025, $D$2, $D45) -> 45975 | H45: =H44+F45 -> 2532.13 | J45: FALSE | K45: 1000 | L45: =L44-K45 -> 5685.1
B46: FALSE | C46: Microsoft 365 | D46: 14 | E46: 14.14 | F46: =IF($B46=TRUE, 0, IF(ISERROR(MATCH(C46, INDIRECT("'"&$D$4&"'!$B$8:$B$12"), 0)), -1*E46,E46)) -> -14.14 | G46: =DATE(2025, $D$2, $D46) -> 45975 | H46: =H45+F46 -> 2517.99 | K46: UPSTART Debt Consolidation | L46: 3877.83 | M46: 0.1888
B47: FALSE | C47: TD Auto Loan | D47: 14 | E47: 595.68 | F47: =IF($B47=TRUE, 0, IF(ISERROR(MATCH(C47, INDIRECT("'"&$D$4&"'!$B$8:$B$12"), 0)), -1*E47,E47)) -> -595.68 | G47: =DATE(2025, $D$2, $D47) -> 45975 | H47: =H46+F47 -> 1922.31 | J47: FALSE | K47: 1000 | L47: =L46-K47 -> 2877.83
B48: FALSE | C48: Wife Hair | D48: 15 | E48: 400 | F48: =IF($B48=TRUE, 0, IF(ISERROR(MATCH(C48, INDIRECT("'"&$D$4&"'!$B$8:$B$12"), 0)), -1*E48,E48)) -> -400 | G48: =DATE(2025, $D$2, $D48) -> 45976 | H48: =H47+F48 -> 1522.31 | J48: FALSE | K48: 1000 | L48: =L47-K48 -> 1877.83
B49: FALSE | C49: Wife Repayment | D49: 15 | E49: 500 | F49: =IF($B49=TRUE, 0, IF(ISERROR(MATCH(C49, INDIRECT("'"&$D$4&"'!$B$8:$B$12"), 0)), -1*E49,E49)) -> -500 | G49: =DATE(2025, $D$2, $D49) -> 45976 | H49: =H48+F49 -> 1022.31 | J49: FALSE | K49: 1000 | L49: =L48-K49 -> 877.83
B50: FALSE | C50: Wife Fall Clothes | D50: 15 | E50: 500 | F50: =IF($B50=TRUE, 0, IF(ISERROR(MATCH(C50, INDIRECT("'"&$D$4&"'!$B$8:$B$12"), 0)), -1*E50,E50)) -> -500 | G50: =DATE(2025, $D$2, $D50) -> 45976 | H50: =H49+F50 -> 522.31 | J50: FALSE | K50: 877.83 | L50: =L49-K50 -> 0
B51: FALSE | C51: Phone (Nykosi) | D51: 16 | E51: 30 | F51: =IF($B51=TRUE, 0, IF(ISERROR(MATCH(C51, INDIRECT("'"&$D$4&"'!$B$8:$B$12"), 0)), -1*E51,E51)) -> -30 | G51: =DATE(2025, $D$2, $D51) -> 45977 | H51: =H50+F51 -> 492.31
B52: FALSE | C52: Phone (Brittany) | D52: 16 | E52: 50 | F52: =IF($B52=TRUE, 0, IF(ISERROR(MATCH(C52, INDIRECT("'"&$D$4&"'!$B$8:$B$12"), 0)), -1*E52,E52)) -> -50 | G52: =DATE(2025, $D$2, $D52) -> 45977 | H52: =H51+F52 -> 442.31
B53: FALSE | C53: OpenAI | D53: 16 | E53: 20.2 | F53: =IF($B53=TRUE, 0, IF(ISERROR(MATCH(C53, INDIRECT("'"&$D$4&"'!$B$8:$B$12"), 0)), -1*E53,E53)) -> -20.2 | G53: =DATE(2025, $D$2, $D53) -> 45977 | H53: =H52+F53 -> 422.11
B54: FALSE | C54: Groceries + Toiletries | D54: 21 | E54: 250 | F54: =IF($B54=TRUE, 0, IF(ISERROR(MATCH(C54, INDIRECT("'"&$D$4&"'!$B$8:$B$12"), 0)), -1*E54,E54)) -> -250 | G54: =DATE(2025, $D$2, $D54) -> 45982 | H54: =H53+F54 -> 172.11
B55: FALSE | C55: Netflix | D55: 23 | E55: 19.3 | F55: =IF($B55=TRUE, 0, IF(ISERROR(MATCH(C55, INDIRECT("'"&$D$4&"'!$B$8:$B$12"), 0)), -1*E55,E55)) -> -19.3 | G55: =DATE(2025, $D$2, $D55) -> 45984 | H55: =H54+F55 -> 152.81
B56: FALSE | C56: Mom Loan (Repayment) | D56: 24 | E56: -500 | F56: =IF($B56=TRUE, 0, IF(ISERROR(MATCH(C56, INDIRECT("'"&$D$4&"'!$B$8:$B$12"), 0)), -1*E56,E56)) -> 500 | G56: =DATE(2025, $D$2, $D56) -> 45985 | H56: =H55+F56 -> 652.81
B57: FALSE | C57: Maintenance (Lawn) | D57: 24 | E57: 80 | F57: =IF($B57=TRUE, 0, IF(ISERROR(MATCH(C57, INDIRECT("'"&$D$4&"'!$B$8:$B$12"), 0)), -1*E57,E57)) -> -80 | G57: =DATE(2025, $D$2, $D57) -> 45985 | H57: =H56+F57 -> 572.81
B58: FALSE | C58: Gym Membership (Nykosi) | D58: 24 | E58: 22.23 | F58: =IF($B58=TRUE, 0, IF(ISERROR(MATCH(C58, INDIRECT("'"&$D$4&"'!$B$8:$B$12"), 0)), -1*E58,E58)) -> -22.23 | G58: =DATE(2025, $D$2, $D58) -> 45985 | H58: =H57+F58 -> 550.58
B59: FALSE | C59: Groceries + Toiletries | D59: 28 | E59: 250 | F59: =IF($B59=TRUE, 0, IF(ISERROR(MATCH(C59, INDIRECT("'"&$D$4&"'!$B$8:$B$12"), 0)), -1*E59,E59)) -> -250 | G59: =DATE(2025, $D$2, $D59) -> 45989 | H59: =H58+F59 -> 300.58
B60: FALSE | C60: Gym Trainer (Brittany) | D60: 28 | E60: 105.29 | F60: =IF($B60=TRUE, 0, IF(ISERROR(MATCH(C60, INDIRECT("'"&$D$4&"'!$B$8:$B$12"), 0)), -1*E60,E60)) -> -105.29 | G60: =DATE(2025, $D$2, $D60) -> 45989 | H60: =H59+F60 -> 195.29
B61: FALSE | C61: CVS Income | D61: 31 | E61: -3205.07 | F61: =IF($B61=TRUE, 0, IF(ISERROR(MATCH(C61, INDIRECT("'"&$D$4&"'!$B$8:$B$12"), 0)), -1*E61,E61)) -> 3205.07 | G61: =DATE(2025, $D$2, $D61) -> 45992 | H61: =H60+F61 -> 3400.36
B62: FALSE | C62: UPSTART Debt Consolidation | D62: 31 | E62: 1000 | F62: =IF($B62=TRUE, 0, IF(ISERROR(MATCH(C62, INDIRECT("'"&$D$4&"'!$B$8:$B$12"), 0)), -1*E62,E62)) -> -1000 | G62: =DATE(2025, $D$2, $D62) -> 45992 | H62: =H61+F62 -> 2400.36

Sheet Cashflow DEC
C2: Month | D2: 12
C3: Year | D3: 2025
C4: Sheet Name | D4: =D3&TEXT(D2, "00") -> 202512
C5: Starting Bank Balance | D5: 2201.09 | K5: Currently In MONTHLY RECURRING transfers
K6: Auto Insurance | L6: 4 | M6: 353.71
K7: Heating/Natural Gas | L7: 15 | M7: 175
K8: CITI Diamond Preferred | L8: 15 | M8: 120
K9: UPSTART Debt Consolidation | L9: 15 | M9: 181.13
K10: Life Insurance | L10: 15 | M10: 82.37
K11: Electricity | L11: 18 | M11: 102.03
K12: TD Auto Loan | L12: 21 | M12: 595.68
K13: Internet | L13: 27 | M13: 74.95
K14: Currently In OTHER transfers
K15: Owner Contribution to Mortgage | L15: 1 | M15: 146.54
K16: Blink Security | L16: 5 | M16: 10.64
K17: Avail Portal | L17: 16 | M17: 18
K18: Landlord Electricity | L18: 18 | M18: 33.16
K19: CITIZENS HELOC | L19: 15 | M19: 95.95
B23: Paid? | C23: Description | D23: Expected Due Date | E23: Amount | F23: Adjusted Amount | G23: Adjusted Due Date | H23: Cummulative | K23: Debt Payoff Tracker
B24: FALSE | C24: Owner Contribution to Mortgage | D24: 1 | E24: 146.54 | F24: =IF($B24=TRUE, 0, IF(ISERROR(MATCH(C24, INDIRECT("'"&$D$4&"'!$B$8:$B$12"), 0)), -1*E24,E24)) -> -146.54 | G24: =DATE(2025, $D$2, $D24) -> 45992 | H24: =$D$5+F24 -> 2054.55 | K24: Debt Payment | L24: Debt Balance | M24: Interest Rate
B25: FALSE | C25: Blink Security | D25: 1 | E25: 10.64 | F25: =IF($B25=TRUE, 0, IF(ISERROR(MATCH(C25, INDIRECT("'"&$D$4&"'!$B$8:$B$12"), 0)), -1*E25,E25)) -> -10.64 | G25: =DATE(2025, $D$2, $D25) -> 45992 | H25: =H24+F25 -> 2043.91 | K25: BOA Customized Rewards | L25: 7700 | M25: 0.2124
B26: FALSE | C26: Landlord Electricity | D26: 1 | E26: 36.85 | F26: =IF($B26=TRUE, 0, IF(ISERROR(MATCH(C26, INDIRECT("'"&$D$4&"'!$B$8:$B$12"), 0)), -1*E26,E26)) -> -36.85 | G26: =DATE(2025, $D$2, $D26) -> 45992 | H26: =H25+F26 -> 2007.06 | J26: FALSE | K26: 1000 | L26: =L25-K26 -> 6700
B27: FALSE | C27: Avail Portal | D27: 1 | E27: 18 | F27: =IF($B27=TRUE, 0, IF(ISERROR(MATCH(C27, INDIRECT("'"&$D$4&"'!$B$8:$B$12"), 0)), -1*E27,E27)) -> -18 | G27: =DATE(2025, $D$2, $D27) -> 45992 | H27: =H26+F27 -> 1989.06 | J27: FALSE | K27: 1000 | L27: =L26-K27 -> 5700
B28: TRUE | C28: Auto Insurance | D28: 1 | E28: 353.71 | F28: =IF($B28=TRUE, 0, IF(ISERROR(MATCH(C28, INDIRECT("'"&$D$4&"'!$B$8:$B$12"), 0)), -1*E28,E28)) -> 0 | G28: =DATE(2025, $D$2, $D28) -> 45992 | H28: =H27+F28 -> 1989.06 | J28: FALSE | K28: 1000 | L28: =L27-K28 -> 4700
B29: FALSE | C29: AQUA FINANCE Roofing Replacement | D29: 1 | E29: 264.88 | F29: =IF($B29=TRUE, 0, IF(ISERROR(MATCH(C29, INDIRECT("'"&$D$4&"'!$B$8:$B$12"), 0)), -1*E29,E29)) -> -264.88 | G29: =DATE(2025, $D$2, $D29) -> 45992 | H29: =H28+F29 -> 1724.18 | J29: FALSE | K29: 1000 | L29: =L28-K29 -> 3700
B30: FALSE | C30: BOA Unlimited Rewards | D30: 4 | E30: 0 | F30: =IF($B30=TRUE, 0, IF(ISERROR(MATCH(C30, INDIRECT("'"&$D$4&"'!$B$8:$B$12"), 0)), -1*E30,E30)) -> 0 | G30: =DATE(2025, $D$2, $D30) -> 45995 | H30: =H29+F30 -> 1724.18 | J30: FALSE | K30: 1000 | L30: =L29-K30 -> 2700
B31: FALSE | C31: Gym Membership (Brittany) | D31: 6 | E31: 32.87 | F31: =IF($B31=TRUE, 0, IF(ISERROR(MATCH(C31, INDIRECT("'"&$D$4&"'!$B$8:$B$12"), 0)), -1*E31,E31)) -> -32.87 | G31: =DATE(2025, $D$2, $D31) -> 45997 | H31: =H30+F31 -> 1691.31 | K31: CITIZENS Clear Value | L31: 6246.15 | M31: 0 | N31: 0% APR ends MAR 2026
B32: FALSE | C32: Groceries + Toiletries | D32: 7 | E32: 250 | F32: =IF($B32=TRUE, 0, IF(ISERROR(MATCH(C32, INDIRECT("'"&$D$4&"'!$B$8:$B$12"), 0)), -1*E32,E32)) -> -250 | G32: =DATE(2025, $D$2, $D32) -> 45998 | H32: =H31+F32 -> 1441.31 | J32: FALSE | K32: 1000 | L32: =L31-K32 -> 5246.15
B33: FALSE | C33: Maintenance (Lawn) | D33: 10 | E33: 80 | F33: =IF($B33=TRUE, 0, IF(ISERROR(MATCH(C33, INDIRECT("'"&$D$4&"'!$B$8:$B$12"), 0)), -1*E33,E33)) -> -80 | G33: =DATE(2025, $D$2, $D33) -> 46001 | H33: =H32+F33 -> 1361.31 | J33: FALSE | K33: 1000 | L33: =L32-K33 -> 4246.15
B34: FALSE | C34: CITIZENS Clear Value | D34: 13 | E34: 62 | F34: =IF($B34=TRUE, 0, IF(ISERROR(MATCH(C34, INDIRECT("'"&$D$4&"'!$B$8:$B$12"), 0)), -1*E34,E34)) -> -62 | G34: =DATE(2025, $D$2, $D34) -> 46004 | H34: =H33+F34 -> 1299.31 | J34: FALSE | K34: 1000 | L34: =L33-K34 -> 3246.15
B35: FALSE | C35: CVS Income | D35: 14 | E35: -3205.07 | F35: =IF($B35=TRUE, 0, IF(ISERROR(MATCH(C35, INDIRECT("'"&$D$4&"'!$B$8:$B$12"), 0)), -1*E35,E35)) -> 3205.07 | G35: =DATE(2025, $D$2, $D35) -> 46005 | H35: =H34+F35 -> 4504.38 | J35: FALSE | K35: 1000 | L35: =L34-K35 -> 2246.15
B36: FALSE | C36: Groceries + Toiletries | D36: 14 | E36: 250 | F36: =IF($B36=TRUE, 0, IF(ISERROR(MATCH(C36, INDIRECT("'"&$D$4&"'!$B$8:$B$12"), 0)), -1*E36,E36)) -> -250 | G36: =DATE(2025, $D$2, $D36) -> 46005 | H36: =H35+F36 -> 4254.38 | J36: FALSE | K36: 1000 | L36: =L35-K36 -> 1246.15
B37: FALSE | C37: Gym Trainer (Brittany) | D37: 14 | E37: 105.29 | F37: =IF($B37=TRUE, 0, IF(ISERROR(MATCH(C37, INDIRECT("'"&$D$4&"'!$B$8:$B$12"), 0)), -1*E37,E37)) -> -105.29 | G37: =DATE(2025, $D$2, $D37) -> 46005 | H37: =H36+F37 -> 4149.09 | K37: 1000 | L37: =L36-K37 -> 246.15
B38: FALSE | C38: Amazon Prime | D38: 14 | E38: 14.99 | F38: =IF($B38=TRUE, 0, IF(ISERROR(MATCH(C38, INDIRECT("'"&$D$4&"'!$B$8:$B$12"), 0)), -1*E38,E38)) -> -14.99 | G38: =DATE(2025, $D$2, $D38) -> 46005 | H38: =H37+F38 -> 4134.1 | K38: =L37 -> 246.15 | L38: =L37-K38 -> 0
B39: FALSE | C39: CITI Diamond Preferred | D39: 14 | E39: 120 | F39: =IF($B39=TRUE, 0, IF(ISERROR(MATCH(C39, INDIRECT("'"&$D$4&"'!$B$8:$B$12"), 0)), -1*E39,E39)) -> -120 | G39: =DATE(2025, $D$2, $D39) -> 46005 | H39: =H38+F39 -> 4014.1 | K39: CITI Diamond Preferred | L39: 11685.1 | M39: 0 | N39: 0% APR ends SEP 2026
B40: FALSE | C40: UPSTART Debt Consolidation | D40: 14 | E40: 181.13 | F40: =IF($B40=TRUE, 0, IF(ISERROR(MATCH(C40, INDIRECT("'"&$D$4&"'!$B$8:$B$12"), 0)), -1*E40,E40)) -> -181.13 | G40: =DATE(2025, $D$2, $D40) -> 46005 | H40: =H39+F40 -> 3832.97 | J40: FALSE | K40: 1000 | L40: =L39-K40 -> 10685.1
B41: FALSE | C41: Heating/Natural Gas | D41: 14 | E41: 175 | F41: =IF($B41=TRUE, 0, IF(ISERROR(MATCH(C41, INDIRECT("'"&$D$4&"'!$B$8:$B$12"), 0)), -1*E41,E41)) -> -175 | G41: =DATE(2025, $D$2, $D41) -> 46005 | H41: =H40+F41 -> 3657.97 | J41: FALSE | K41: 1000 | L41: =L40-K41 -> 9685.1
B42: FALSE | C42: Electricity | D42: 14 | E42: 143.35 | F42: =IF($B42=TRUE, 0, IF(ISERROR(MATCH(C42, INDIRECT("'"&$D$4&"'!$B$8:$B$12"), 0)), -1*E42,E42)) -> -143.35 | G42: =DATE(2025, $D$2, $D42) -> 46005 | H42: =H41+F42 -> 3514.62 | J42: FALSE | K42: 1000 | L42: =L41-K42 -> 8685.1
B43: FALSE | C43: CITIZENS HELOC | D43: 14 | E43: 729.29 | F43: =IF($B43=TRUE, 0, IF(ISERROR(MATCH(C43, INDIRECT("'"&$D$4&"'!$B$8:$B$12"), 0)), -1*E43,E43)) -> -729.29 | G43: =DATE(2025, $D$2, $D43) -> 46005 | H43: =H42+F43 -> 2785.33 | J43: FALSE | K43: 1000 | L43: =L42-K43 -> 7685.1
B44: FALSE | C44: Internet | D44: 14 | E44: 74.95 | F44: =IF($B44=TRUE, 0, IF(ISERROR(MATCH(C44, INDIRECT("'"&$D$4&"'!$B$8:$B$12"), 0)), -1*E44,E44)) -> -74.95 | G44: =DATE(2025, $D$2, $D44) -> 46005 | H44: =H43+F44 -> 2710.38 | J44: FALSE | K44: 1000 | L44: =L43-K44 -> 6685.1
B45: FALSE | C45: Life Insurance | D45: 14 | E45: 82.37 | F45: =IF($B45=TRUE, 0, IF(ISERROR(MATCH(C45, INDIRECT("'"&$D$4&"'!$B$8:$B$12"), 0)), -1*E45,E45)) -> -82.37 | G45: =DATE(2025, $D$2, $D45) -> 46005 | H45: =H44+F45 -> 2628.01 | J45: FALSE | K45: 1000 | L45: =L44-K45 -> 5685.1
B46: FALSE | C46: Microsoft 365 | D46: 14 | E46: 14.14 | F46: =IF($B46=TRUE, 0, IF(ISERROR(MATCH(C46, INDIRECT("'"&$D$4&"'!$B$8:$B$12"), 0)), -1*E46,E46)) -> -14.14 | G46: =DATE(2025, $D$2, $D46) -> 46005 | H46: =H45+F46 -> 2613.87 | K46: UPSTART Debt Consolidation | L46: 3877.83 | M46: 0.1888
B47: FALSE | C47: TD Auto Loan | D47: 14 | E47: 595.68 | F47: =IF($B47=TRUE, 0, IF(ISERROR(MATCH(C47, INDIRECT("'"&$D$4&"'!$B$8:$B$12"), 0)), -1*E47,E47)) -> -595.68 | G47: =DATE(2025, $D$2, $D47) -> 46005 | H47: =H46+F47 -> 2018.19 | J47: FALSE | K47: 1000 | L47: =L46-K47 -> 2877.83
B48: FALSE | C48: Wife Hair | D48: 15 | E48: 400 | F48: =IF($B48=TRUE, 0, IF(ISERROR(MATCH(C48, INDIRECT("'"&$D$4&"'!$B$8:$B$12"), 0)), -1*E48,E48)) -> -400 | G48: =DATE(2025, $D$2, $D48) -> 46006 | H48: =H47+F48 -> 1618.19 | J48: FALSE | K48: 1000 | L48: =L47-K48 -> 1877.83
B49: FALSE | C49: Wife Repayment | D49: 15 | E49: 500 | F49: =IF($B49=TRUE, 0, IF(ISERROR(MATCH(C49, INDIRECT("'"&$D$4&"'!$B$8:$B$12"), 0)), -1*E49,E49)) -> -500 | G49: =DATE(2025, $D$2, $D49) -> 46006 | H49: =H48+F49 -> 1118.19 | J49: FALSE | K49: 1000 | L49: =L48-K49 -> 877.83
B50: FALSE | C50: Wife Fall Clothes | D50: 15 | E50: 500 | F50: =IF($B50=TRUE, 0, IF(ISERROR(MATCH(C50, INDIRECT("'"&$D$4&"'!$B$8:$B$12"), 0)), -1*E50,E50)) -> -500 | G50: =DATE(2025, $D$2, $D50) -> 46006 | H50: =H49+F50 -> 618.19 | J50: FALSE | K50: 877.83 | L50: =L49-K50 -> 0
B51: FALSE | C51: Phone (Nykosi) | D51: 16 | E51: 30 | F51: =IF($B51=TRUE, 0, IF(ISERROR(MATCH(C51, INDIRECT("'"&$D$4&"'!$B$8:$B$12"), 0)), -1*E51,E51)) -> -30 | G51: =DATE(2025, $D$2, $D51) -> 46007 | H51: =H50+F51 -> 588.19
B52: FALSE | C52: Phone (Brittany) | D52: 16 | E52: 50 | F52: =IF($B52=TRUE, 0, IF(ISERROR(MATCH(C52, INDIRECT("'"&$D$4&"'!$B$8:$B$12"), 0)), -1*E52,E52)) -> -50 | G52: =DATE(2025, $D$2, $D52) -> 46007 | H52: =H51+F52 -> 538.19
B53: FALSE | C53: OpenAI | D53: 16 | E53: 20.2 | F53: =IF($B53=TRUE, 0, IF(ISERROR(MATCH(C53, INDIRECT("'"&$D$4&"'!$B$8:$B$12"), 0)), -1*E53,E53)) -> -20.2 | G53: =DATE(2025, $D$2, $D53) -> 46007 | H53: =H52+F53 -> 517.99
B54: FALSE | C54: Groceries + Toiletries | D54: 21 | E54: 250 | F54: =IF($B54=TRUE, 0, IF(ISERROR(MATCH(C54, INDIRECT("'"&$D$4&"'!$B$8:$B$12"), 0)), -1*E54,E54)) -> -250 | G54: =DATE(2025, $D$2, $D54) -> 46012 | H54: =H53+F54 -> 267.99
B55: FALSE | C55: Netflix | D55: 23 | E55: 19.3 | F55: =IF($B55=TRUE, 0, IF(ISERROR(MATCH(C55, INDIRECT("'"&$D$4&"'!$B$8:$B$12"), 0)), -1*E55,E55)) -> -19.3 | G55: =DATE(2025, $D$2, $D55) -> 46014 | H55: =H54+F55 -> 248.69
B56: FALSE | C56: Mom Loan (Repayment) | D56: 24 | E56: -500 | F56: =IF($B56=TRUE, 0, IF(ISERROR(MATCH(C56, INDIRECT("'"&$D$4&"'!$B$8:$B$12"), 0)), -1*E56,E56)) -> 500 | G56: =DATE(2025, $D$2, $D56) -> 46015 | H56: =H55+F56 -> 748.69
B57: FALSE | C57: Maintenance (Lawn) | D57: 24 | E57: 80 | F57: =IF($B57=TRUE, 0, IF(ISERROR(MATCH(C57, INDIRECT("'"&$D$4&"'!$B$8:$B$12"), 0)), -1*E57,E57)) -> -80 | G57: =DATE(2025, $D$2, $D57) -> 46015 | H57: =H56+F57 -> 668.69
B58: FALSE | C58: Gym Membership (Nykosi) | D58: 24 | E58: 22.23 | F58: =IF($B58=TRUE, 0, IF(ISERROR(MATCH(C58, INDIRECT("'"&$D$4&"'!$B$8:$B$12"), 0)), -1*E58,E58)) -> -22.23 | G58: =DATE(2025, $D$2, $D58) -> 46015 | H58: =H57+F58 -> 646.46
B59: FALSE | C59: Groceries + Toiletries | D59: 28 | E59: 250 | F59: =IF($B59=TRUE, 0, IF(ISERROR(MATCH(C59, INDIRECT("'"&$D$4&"'!$B$8:$B$12"), 0)), -1*E59,E59)) -> -250 | G59: =DATE(2025, $D$2, $D59) -> 46019 | H59: =H58+F59 -> 396.46
B60: FALSE | C60: Gym Trainer (Brittany) | D60: 28 | E60: 105.29 | F60: =IF($B60=TRUE, 0, IF(ISERROR(MATCH(C60, INDIRECT("'"&$D$4&"'!$B$8:$B$12"), 0)), -1*E60,E60)) -> -105.29 | G60: =DATE(2025, $D$2, $D60) -> 46019 | H60: =H59+F60 -> 291.17
B61: FALSE | C61: CVS Income | D61: 31 | E61: -3205.07 | F61: =IF($B61=TRUE, 0, IF(ISERROR(MATCH(C61, INDIRECT("'"&$D$4&"'!$B$8:$B$12"), 0)), -1*E61,E61)) -> 3205.07 | G61: =DATE(2025, $D$2, $D61) -> 46022 | H61: =H60+F61 -> 3496.24
B62: FALSE | C62: UPSTART Debt Consolidation | D62: 31 | E62: 1000 | F62: =IF($B62=TRUE, 0, IF(ISERROR(MATCH(C62, INDIRECT("'"&$D$4&"'!$B$8:$B$12"), 0)), -1*E62,E62)) -> -1000 | G62: =DATE(2025, $D$2, $D62) -> 46022 | H62: =H61+F62 -> 2496.24
